{
  "type": "Feature",
  "properties": {
    "gn:admin1_code":"07",
    "gn:admin2_code":"601",
    "gn:admin3_code":"60109.0",
    "gn:asciiname":"La Lindora",
    "gn:country_code":"CR",
    "gn:dem":1029,
    "gn:feature_class":"P",
    "gn:feature_code":"PPLL",
    "gn:name":"La Lindora",
    "gn:population":0,
    "gn:timezone":"America/Costa_Rica",
    "iso:country":"CR",
    "wof:name":"La Lindora",
    "wof:placetype":"locality"
},
  "geometry": {"coordinates":[-84.8366,10.28388],"type":"Point"}
}