{
  "type": "Feature",
  "properties": {
    "gn:admin1_code":"01",
    "gn:admin2_code":"215",
    "gn:admin3_code":"21501.0",
    "gn:asciiname":"Cucaracha",
    "gn:country_code":"CR",
    "gn:dem":93,
    "gn:feature_class":"P",
    "gn:feature_code":"PPL",
    "gn:name":"Cucaracha",
    "gn:population":0,
    "gn:timezone":"America/Costa_Rica",
    "iso:country":"CR",
    "name:und_x_variant":[
        "San Josecito",
        "Cucaracha"
    ],
    "wof:name":"Cucaracha",
    "wof:placetype":"locality"
},
  "geometry": {"coordinates":[-84.76048,10.62806],"type":"Point"}
}