{
  "type": "Feature",
  "properties": {
    "gn:admin1_code":"01",
    "gn:admin2_code":"206",
    "gn:admin3_code":"20601.0",
    "gn:asciiname":"Corrales",
    "gn:country_code":"CR",
    "gn:dem":1106,
    "gn:feature_class":"P",
    "gn:feature_code":"PPL",
    "gn:name":"Corrales",
    "gn:population":0,
    "gn:timezone":"America/Costa_Rica",
    "iso:country":"CR",
    "name:und_x_variant":[
        "Bajo Corrales",
        "Corrales"
    ],
    "wof:name":"Corrales",
    "wof:placetype":"locality"
},
  "geometry": {"coordinates":[-84.40031,10.10919],"type":"Point"}
}