{
  "type": "Feature",
  "properties": {
    "gn:admin1_code":"03",
    "gn:admin2_code":"509",
    "gn:admin3_code":"50902.0",
    "gn:asciiname":"Cacao",
    "gn:country_code":"CR",
    "gn:dem":48,
    "gn:feature_class":"P",
    "gn:feature_code":"PPL",
    "gn:name":"Cacao",
    "gn:population":0,
    "gn:timezone":"America/Costa_Rica",
    "iso:country":"CR",
    "wof:name":"Cacao",
    "wof:placetype":"locality"
},
  "geometry": {"coordinates":[-85.28641999999998,10.05115],"type":"Point"}
}