{
  "type": "Feature",
  "properties": {
    "iso:country":"CR",
    "name:ita_x_preferred":[
        "Nosara"
    ],
    "name:nor_x_preferred":[
        "Nosara"
    ],
    "name:spa_x_preferred":[
        "Nosara"
    ],
    "name:vie_x_preferred":[
        "Nosara"
    ],
    "name:zho_x_preferred":[
        "\u8afe\u85a9\u62c9\u5340"
    ],
    "qs:gn_pop":0,
    "qs:name":"Nosara",
    "qs:name_adm0":"Costa Rica",
    "qs:name_adm1":"Guanacaste",
    "qs:photos":24,
    "qs:photos_1k":5,
    "qs:photos_9k":9,
    "qs:photos_9r":9,
    "qs:photos_all":1935,
    "qs:photos_sr":1,
    "qs:placetype":"LocalAdmin",
    "qs:pop_sr":"0",
    "qs:woe_adm0":23424791,
    "wof:name":"Nosara",
    "wof:placetype":"localadmin"
},
  "geometry": {"coordinates":[-85.6707,9.948223],"type":"Point"}
}