{
  "type": "Feature",
  "properties": {
    "gn:admin1_code":"02",
    "gn:admin2_code":"301",
    "gn:admin3_code":"30107.0",
    "gn:asciiname":"San Antonio",
    "gn:country_code":"CR",
    "gn:dem":1564,
    "gn:feature_class":"P",
    "gn:feature_code":"PPL",
    "gn:name":"San Antonio",
    "gn:population":0,
    "gn:timezone":"America/Costa_Rica",
    "iso:country":"CR",
    "name:und_x_variant":[
        "San Antonio de Corralillo",
        "San Antonio"
    ],
    "wof:name":"San Antonio",
    "wof:placetype":"locality"
},
  "geometry": {"coordinates":[-84.04685000000001,9.78312],"type":"Point"}
}