{
  "type": "Feature",
  "properties": {
    "iso:country":"CR",
    "name:cat_x_preferred":[
        "Nossa Senhora do Perp\u00e9tuo Socorro"
    ],
    "name:fra_x_preferred":[
        "Nossa Senhora do Perp\u00e9tuo Socorro"
    ],
    "name:glg_x_preferred":[
        "Nossa Senhora do Perp\u00e9tuo Socorro"
    ],
    "name:por_x_preferred":[
        "Nossa Senhora do Perp\u00e9tuo Socorro"
    ],
    "name:spa_x_preferred":[
        "Perpetuo Socorro",
        "Nossa Senhora do Perp\u00e9tuo Socorro"
    ],
    "qs:gn_adm0_cc":"CR",
    "qs:gn_local":3621849,
    "qs:gn_nam_loc":"San Jose, San Jos\u00e9, San Jos\u00e9, CR",
    "qs:gn_namadm1":"08",
    "qs:local_max":6857,
    "qs:local_sum":19186,
    "qs:localhoods":27,
    "qs:name":"Perpetuo Socorro",
    "qs:name_adm0":"Costa Rica",
    "qs:name_adm1":"San Jose",
    "qs:name_adm2":"San Jos\u00e9",
    "qs:name_lau":"Hospital",
    "qs:name_local":"San Jos\u00e9",
    "qs:photo_max":31,
    "qs:photo_sum":78,
    "qs:placetype":"Suburb",
    "qs:quad_count":4,
    "qs:woe_adm0":23424791,
    "qs:woe_adm1":2345088,
    "qs:woe_adm2":26808844,
    "qs:woe_lau":26809014,
    "qs:woe_local":59426,
    "qs:woe_ver":"7.10.0",
    "qs_pg:name":"Perpetuo Socorro",
    "qs_pg:name_adm0":"Costa Rica",
    "qs_pg:name_adm1":"San Jose",
    "qs_pg:photos":96,
    "qs_pg:photos_1k":19,
    "qs_pg:photos_9k":1,
    "qs_pg:photos_9r":3,
    "qs_pg:photos_all":96,
    "qs_pg:photos_sr":3,
    "qs_pg:pop_sr":0,
    "qs_pg:qs_pg_placetype":"neighbourhood",
    "qs_pg:qs_pg_placetype_gp":"Suburb",
    "qs_pg:woe_adm0":23424791,
    "woe:adm0_id":23424791,
    "woe:name_adm0":"Costa Rica",
    "woe:name_adm1":"San Jose",
    "woe:placetype":"Suburb",
    "wof:lang":[
        "spa"
    ],
    "wof:name":"Perpetuo Socorro",
    "wof:placetype":"neighbourhood"
},
  "geometry": {"coordinates":[-84.103714,9.934283],"type":"Point"}
}