{
  "type": "Feature",
  "properties": {
    "gn:admin1_code":"02",
    "gn:admin2_code":"306",
    "gn:admin3_code":"30603.0",
    "gn:asciiname":"Coliblanco",
    "gn:country_code":"CR",
    "gn:dem":1695,
    "gn:feature_class":"P",
    "gn:feature_code":"PPL",
    "gn:name":"Coliblanco",
    "gn:population":0,
    "gn:timezone":"America/Costa_Rica",
    "iso:country":"CR",
    "wof:name":"Coliblanco",
    "wof:placetype":"locality"
},
  "geometry": {"coordinates":[-83.77399,9.9458],"type":"Point"}
}