{
  "type": "Feature",
  "properties": {
    "gn:admin1_code":"01",
    "gn:admin2_code":"204",
    "gn:admin3_code":"20403.0",
    "gn:asciiname":"Labrador",
    "gn:country_code":"CR",
    "gn:dem":193,
    "gn:feature_class":"P",
    "gn:feature_code":"PPL",
    "gn:name":"Labrador",
    "gn:population":0,
    "gn:timezone":"America/Costa_Rica",
    "iso:country":"CR",
    "name:und_x_variant":[
        "Oricuajo",
        "Labrador"
    ],
    "wof:name":"Labrador",
    "wof:placetype":"locality"
},
  "geometry": {"coordinates":[-84.61239999999999,9.94607],"type":"Point"}
}