{
  "type": "Feature",
  "properties": {
    "gn:admin1_code":"08",
    "gn:admin2_code":"115",
    "gn:admin3_code":"11501.0",
    "gn:asciiname":"Universidad",
    "gn:country_code":"CR",
    "gn:dem":1208,
    "gn:feature_class":"P",
    "gn:feature_code":"PPL",
    "gn:name":"Universidad",
    "gn:population":0,
    "gn:timezone":"America/Costa_Rica",
    "iso:country":"CR",
    "name:und_x_variant":[
        "Ciudad Universitaria",
        "University City",
        "Universidad"
    ],
    "wof:name":"Universidad",
    "wof:placetype":"locality"
},
  "geometry": {"coordinates":[-84.05110000000001,9.93629],"type":"Point"}
}