{
  "type": "Feature",
  "properties": {
    "gn:admin1_code":"03",
    "gn:admin2_code":"502",
    "gn:admin3_code":"50207.0",
    "gn:asciiname":"Cuajiniquil",
    "gn:country_code":"CR",
    "gn:dem":242,
    "gn:feature_class":"P",
    "gn:feature_code":"PPL",
    "gn:name":"Cuajiniquil",
    "gn:population":0,
    "gn:timezone":"America/Costa_Rica",
    "iso:country":"CR",
    "wof:name":"Cuajiniquil",
    "wof:placetype":"locality"
},
  "geometry": {"coordinates":[-85.52328,10.0365],"type":"Point"}
}