{
  "type": "Feature",
  "properties": {
    "iso:country":"CR",
    "qs:gn_pop":0,
    "qs:name":"Playa Matapalo",
    "qs:name_adm0":"Costa Rica",
    "qs:name_adm1":"Puntarenas",
    "qs:photos":107,
    "qs:photos_1k":22,
    "qs:photos_9k":1,
    "qs:photos_9r":3,
    "qs:photos_all":107,
    "qs:photos_sr":3,
    "qs:placetype":"Town",
    "qs:pop_sr":"0",
    "qs:woe_adm0":23424791,
    "wof:name":"Playa Matapalo",
    "wof:placetype":"locality"
},
  "geometry": {"coordinates":[-83.89349,9.277316],"type":"Point"}
}