{
  "type": "Feature",
  "properties": {
    "gn:admin1_code":"07",
    "gn:admin2_code":"604",
    "gn:admin3_code":"60402.0",
    "gn:asciiname":"Tajo Alto",
    "gn:country_code":"CR",
    "gn:dem":755,
    "gn:feature_class":"P",
    "gn:feature_code":"PPL",
    "gn:name":"Tajo Alto",
    "gn:population":0,
    "gn:timezone":"America/Costa_Rica",
    "iso:country":"CR",
    "wof:name":"Tajo Alto",
    "wof:placetype":"locality"
},
  "geometry": {"coordinates":[-84.72235999999999,10.13427],"type":"Point"}
}