{
  "type": "Feature",
  "properties": {
    "gn:admin1_code":"07",
    "gn:admin2_code":"602",
    "gn:admin3_code":"60205.0",
    "gn:asciiname":"Cerrillos",
    "gn:country_code":"CR",
    "gn:dem":602,
    "gn:feature_class":"P",
    "gn:feature_code":"PPL",
    "gn:name":"Cerrillos",
    "gn:population":0,
    "gn:timezone":"America/Costa_Rica",
    "iso:country":"CR",
    "name:cat_x_preferred":[
        "Cerrillos"
    ],
    "name:ceb_x_preferred":[
        "Cerrillos"
    ],
    "name:deu_x_preferred":[
        "Cerrillos"
    ],
    "name:fra_x_preferred":[
        "Cerrillos"
    ],
    "name:nld_x_preferred":[
        "Cerrillos"
    ],
    "name:por_x_preferred":[
        "Cerrillos"
    ],
    "name:rus_x_preferred":[
        "\u0421\u0435\u0440\u0440\u0438\u043b\u044c\u043e\u0441"
    ],
    "name:spa_x_preferred":[
        "Cerrillos"
    ],
    "name:swe_x_preferred":[
        "Cerrillos"
    ],
    "wof:name":"Cerrillos",
    "wof:placetype":"locality"
},
  "geometry": {"coordinates":[-84.65321999999998,10.08467],"type":"Point"}
}