{
  "type": "Feature",
  "properties": {
    "gn:admin1_code":"07",
    "gn:admin2_code":"602",
    "gn:admin3_code":"60205.0",
    "gn:asciiname":"Cerrillos",
    "gn:country_code":"CR",
    "gn:dem":602,
    "gn:feature_class":"P",
    "gn:feature_code":"PPL",
    "gn:name":"Cerrillos",
    "gn:population":0,
    "gn:timezone":"America/Costa_Rica",
    "iso:country":"CR",
    "name:ben_x_preferred":[
        "\u0995\u09c7\u09b0\u09b0\u09bf\u09b2\u09cd\u09b2\u09cb\u09b8"
    ],
    "name:cat_x_preferred":[
        "Cerrillos"
    ],
    "name:ceb_x_preferred":[
        "Cerrillos"
    ],
    "name:deu_x_preferred":[
        "Cerrillos"
    ],
    "name:ell_x_preferred":[
        "\u03a3\u03b5\u03c1\u03af\u03b3\u03b9\u03bf\u03c2"
    ],
    "name:fas_x_preferred":[
        "\u06a9\u0631\u06cc\u0644\u0648\u0633"
    ],
    "name:fra_x_preferred":[
        "Cerrillos"
    ],
    "name:heb_x_preferred":[
        "\u05e7\u05e8\u05d9\u05dc\u05d5\u05e1"
    ],
    "name:hin_x_preferred":[
        "\u0938\u0947\u0930\u093f\u0932\u094b\u0938"
    ],
    "name:hun_x_preferred":[
        "Cerrillos"
    ],
    "name:ind_x_preferred":[
        "Cerrillos"
    ],
    "name:jpn_x_preferred":[
        "\u30bb\u30ea\u30ed\u30b9"
    ],
    "name:kor_x_preferred":[
        "\uc138\ub9ac\uc694"
    ],
    "name:nld_x_preferred":[
        "Cerrillos"
    ],
    "name:pol_x_preferred":[
        "Cerrillos"
    ],
    "name:por_x_preferred":[
        "Cerrillos"
    ],
    "name:rus_x_preferred":[
        "\u0421\u0435\u0440\u0440\u0438\u043b\u044c\u043e\u0441"
    ],
    "name:spa_x_preferred":[
        "Cerrillos"
    ],
    "name:swe_x_preferred":[
        "Cerrillos"
    ],
    "name:urd_x_preferred":[
        "\u0633\u06cc\u0631\u06cc\u0644\u0648\u0633"
    ],
    "name:vie_x_preferred":[
        "Cerrillos"
    ],
    "wof:name":"Cerrillos",
    "wof:placetype":"locality"
},
  "geometry": {"coordinates":[-84.65322,10.08467],"type":"Point"}
}