{
  "type": "Feature",
  "properties": {
    "gn:admin1_code":"08",
    "gn:admin2_code":"104",
    "gn:admin3_code":"10402.0",
    "gn:asciiname":"Mercedes Sur",
    "gn:country_code":"CR",
    "gn:dem":905,
    "gn:feature_class":"P",
    "gn:feature_code":"PPL",
    "gn:name":"Mercedes Sur",
    "gn:population":0,
    "gn:timezone":"America/Costa_Rica",
    "iso:country":"CR",
    "wof:name":"Mercedes Sur",
    "wof:placetype":"locality"
},
  "geometry": {"coordinates":[-84.36168000000001,9.82194],"type":"Point"}
}