{
  "type": "Feature",
  "properties": {
    "gn:admin1_code":"02",
    "gn:admin2_code":"302",
    "gn:admin3_code":"30203.0",
    "gn:asciiname":"Nubes",
    "gn:country_code":"CR",
    "gn:dem":1678,
    "gn:feature_class":"P",
    "gn:feature_code":"PPL",
    "gn:name":"Nubes",
    "gn:population":0,
    "gn:timezone":"America/Costa_Rica",
    "iso:country":"CR",
    "wof:name":"Nubes",
    "wof:placetype":"locality"
},
  "geometry": {"coordinates":[-83.82438,9.7416],"type":"Point"}
}