{
  "type": "Feature",
  "properties": {
    "gn:admin1_code":"04",
    "gn:admin2_code":"403",
    "gn:admin3_code":"40302.0",
    "gn:asciiname":"Quintana",
    "gn:country_code":"CR",
    "gn:dem":1190,
    "gn:feature_class":"P",
    "gn:feature_code":"PPL",
    "gn:name":"Quintana",
    "gn:population":0,
    "gn:timezone":"America/Costa_Rica",
    "iso:country":"CR",
    "name:und_x_variant":[
        "La Quintana",
        "Quintana"
    ],
    "wof:name":"Quintana",
    "wof:placetype":"locality"
},
  "geometry": {"coordinates":[-84.08538,9.98617],"type":"Point"}
}