{
  "type": "Feature",
  "properties": {
    "gn:admin1_code":"04",
    "gn:admin2_code":"403",
    "gn:admin3_code":"40302.0",
    "gn:asciiname":"Quintana",
    "gn:country_code":"CR",
    "gn:dem":1190,
    "gn:feature_class":"P",
    "gn:feature_code":"PPL",
    "gn:name":"Quintana",
    "gn:population":0,
    "gn:timezone":"America/Costa_Rica",
    "iso:country":"CR",
    "name:ast_x_preferred":[
        "Quintana"
    ],
    "name:cat_x_preferred":[
        "Quintana"
    ],
    "name:ceb_x_preferred":[
        "Quintana"
    ],
    "name:deu_x_preferred":[
        "Quintana"
    ],
    "name:eus_x_preferred":[
        "Quintana"
    ],
    "name:fra_x_preferred":[
        "Quintana"
    ],
    "name:glg_x_preferred":[
        "Quintana"
    ],
    "name:ita_x_preferred":[
        "Quintana"
    ],
    "name:nld_x_preferred":[
        "Quintana"
    ],
    "name:pol_x_preferred":[
        "Quintana"
    ],
    "name:por_x_preferred":[
        "Quintana"
    ],
    "name:rus_x_preferred":[
        "\u041a\u0438\u043d\u0442\u0430\u043d\u0430"
    ],
    "name:spa_x_preferred":[
        "Quintana"
    ],
    "name:swe_x_preferred":[
        "Quintana"
    ],
    "name:und_x_variant":[
        "La Quintana",
        "Quintana"
    ],
    "wof:name":"Quintana",
    "wof:placetype":"locality"
},
  "geometry": {"coordinates":[-84.08538,9.98617],"type":"Point"}
}