{
  "type": "Feature",
  "properties": {
    "gn:admin1_code":"08",
    "gn:admin2_code":"106",
    "gn:admin3_code":"10601.0",
    "gn:asciiname":"Lamparas",
    "gn:country_code":"CR",
    "gn:dem":1411,
    "gn:feature_class":"P",
    "gn:feature_code":"PPL",
    "gn:name":"L\u00e1mparas",
    "gn:population":0,
    "gn:timezone":"America/Costa_Rica",
    "iso:country":"CR",
    "wof:name":"Lamparas",
    "wof:placetype":"locality"
},
  "geometry": {"coordinates":[-84.10373,9.87341],"type":"Point"}
}