{
  "type": "Feature",
  "properties": {
    "gn:country":"CR",
    "iso:country":"CR",
    "qs:name":"Samara",
    "qs:name_adm0":"Costa Rica",
    "qs:name_adm1":"Guanacaste",
    "qs:photos":2,
    "qs:photos_1k":1,
    "qs:photos_9k":7,
    "qs:photos_9r":8,
    "qs:photos_all":1551,
    "qs:photos_sr":1,
    "qs:placetype":"LocalAdmin",
    "qs:pop_sr":"0",
    "wd:wordcount":276,
    "wof:name":"Samara",
    "wof:placetype":"localadmin"
},
  "geometry": {"coordinates":[-85.5195605,9.876948],"type":"Point"}
}