{
  "type": "Feature",
  "properties": {
    "gn:admin1_code":"01",
    "gn:admin2_code":"201",
    "gn:admin3_code":"20103.0",
    "gn:asciiname":"Concordia",
    "gn:country_code":"CR",
    "gn:dem":1785,
    "gn:feature_class":"P",
    "gn:feature_code":"PPL",
    "gn:name":"Concordia",
    "gn:population":0,
    "gn:timezone":"America/Costa_Rica",
    "iso:country":"CR",
    "name:und_x_variant":[
        "La Concordia",
        "Concordia"
    ],
    "wof:name":"Concordia",
    "wof:placetype":"locality"
},
  "geometry": {"coordinates":[-84.16373,10.11735],"type":"Point"}
}