{
  "type": "Feature",
  "properties": {
    "gn:admin1_code":"07",
    "gn:admin2_code":"610",
    "gn:admin3_code":"61002.0",
    "gn:asciiname":"La Cuesta",
    "gn:country_code":"CR",
    "gn:dem":42,
    "gn:feature_class":"P",
    "gn:feature_code":"PPL",
    "gn:name":"La Cuesta",
    "gn:population":0,
    "gn:timezone":"America/Costa_Rica",
    "iso:country":"CR",
    "wof:name":"La Cuesta",
    "wof:placetype":"locality"
},
  "geometry": {"coordinates":[-82.84846,8.49124],"type":"Point"}
}