{
  "type": "Feature",
  "properties": {
    "gn:admin1_code":"08",
    "gn:admin2_code":"111",
    "gn:admin3_code":"11103.0",
    "gn:asciiname":"Dulce Nombre de Jesus",
    "gn:country_code":"CR",
    "gn:dem":634,
    "gn:feature_class":"P",
    "gn:feature_code":"PPLA3",
    "gn:name":"Dulce Nombre de Jesus",
    "gn:population":0,
    "gn:timezone":"America/Costa_Rica",
    "iso:country":"CR",
    "wof:name":"Dulce Nombre de Jesus",
    "wof:placetype":"locality"
},
  "geometry": {"coordinates":[-83.97748,10.15144],"type":"Point"}
}