{
  "type": "Feature",
  "properties": {
    "gn:admin1_code":"03",
    "gn:admin2_code":"507",
    "gn:admin3_code":"50704.0",
    "gn:asciiname":"Jobal",
    "gn:country_code":"CR",
    "gn:dem":40,
    "gn:feature_class":"P",
    "gn:feature_code":"PPL",
    "gn:name":"Jobal",
    "gn:population":0,
    "gn:timezone":"America/Costa_Rica",
    "iso:country":"CR",
    "wof:name":"Jobal",
    "wof:placetype":"locality"
},
  "geometry": {"coordinates":[-85.13894000000001,10.22898],"type":"Point"}
}