{
  "type": "Feature",
  "properties": {
    "gn:admin1_code":"01",
    "gn:admin2_code":"210",
    "gn:admin3_code":"21006.0",
    "gn:asciiname":"Hacienda La Ester",
    "gn:cc2":"CR",
    "gn:country_code":"CR",
    "gn:dem":108,
    "gn:feature_class":"P",
    "gn:feature_code":"PPL",
    "gn:name":"Hacienda La Ester",
    "gn:population":0,
    "gn:timezone":"America/Costa_Rica",
    "iso:country":"CR",
    "name:und_x_variant":[
        "La Ester",
        "Hacienda La Ester"
    ],
    "wof:name":"Hacienda La Ester",
    "wof:placetype":"locality"
},
  "geometry": {"coordinates":[-84.26666999999998,10.55],"type":"Point"}
}