{
  "type": "Feature",
  "properties": {
    "gn:admin1_code":"02",
    "gn:admin2_code":"305",
    "gn:admin3_code":"30509.0",
    "gn:asciiname":"Aquiares",
    "gn:country_code":"CR",
    "gn:dem":1013,
    "gn:feature_class":"P",
    "gn:feature_code":"PPL",
    "gn:name":"Aquiares",
    "gn:population":0,
    "gn:timezone":"America/Costa_Rica",
    "iso:country":"CR",
    "name:und_x_variant":[
        "La Isla",
        "Hacienda Aquiares",
        "Aquiares"
    ],
    "wof:name":"Aquiares",
    "wof:placetype":"locality"
},
  "geometry": {"coordinates":[-83.72020999999999,9.93889],"type":"Point"}
}