{
  "type": "Feature",
  "properties": {
    "gn:admin1_code":"08",
    "gn:admin2_code":"119",
    "gn:admin3_code":"11901.0",
    "gn:asciiname":"Pavones",
    "gn:country_code":"CR",
    "gn:dem":706,
    "gn:feature_class":"P",
    "gn:feature_code":"PPL",
    "gn:name":"Pavones",
    "gn:population":0,
    "gn:timezone":"America/Costa_Rica",
    "iso:country":"CR",
    "name:cat_x_preferred":[
        "Pavones"
    ],
    "name:epo_x_preferred":[
        "Pavono"
    ],
    "name:eus_x_preferred":[
        "Pavones"
    ],
    "name:por_x_preferred":[
        "Pavones"
    ],
    "name:spa_x_preferred":[
        "Pavones"
    ],
    "wof:name":"Pavones",
    "wof:placetype":"locality"
},
  "geometry": {"coordinates":[-83.69596,9.34633],"type":"Point"}
}