{
  "type": "Feature",
  "properties": {
    "gn:admin1_code":"07",
    "gn:admin2_code":"603",
    "gn:admin3_code":"60303.0",
    "gn:asciiname":"Paso Real",
    "gn:country_code":"CR",
    "gn:dem":157,
    "gn:feature_class":"P",
    "gn:feature_code":"PPL",
    "gn:name":"Paso Real",
    "gn:population":0,
    "gn:timezone":"America/Costa_Rica",
    "iso:country":"CR",
    "name:und_x_variant":[
        "Pazo Real",
        "Paso Real"
    ],
    "wof:name":"Paso Real",
    "wof:placetype":"locality"
},
  "geometry": {"coordinates":[-83.22866999999999,9.01178],"type":"Point"}
}