{
  "type": "Feature",
  "properties": {
    "gn:admin1_code":"07",
    "gn:admin2_code":"603",
    "gn:admin3_code":"60305.0",
    "gn:asciiname":"Danta",
    "gn:country_code":"CR",
    "gn:dem":537,
    "gn:feature_class":"P",
    "gn:feature_code":"PPL",
    "gn:name":"Danta",
    "gn:population":0,
    "gn:timezone":"America/Costa_Rica",
    "iso:country":"CR",
    "name:ceb_x_preferred":[
        "Danta"
    ],
    "name:deu_x_preferred":[
        "Danta"
    ],
    "name:por_x_preferred":[
        "Danta"
    ],
    "name:swe_x_preferred":[
        "Danta"
    ],
    "wof:name":"Danta",
    "wof:placetype":"locality"
},
  "geometry": {"coordinates":[-83.46807,9.1016],"type":"Point"}
}