{
  "type": "Feature",
  "properties": {
    "gn:admin1_code":"07",
    "gn:admin2_code":"601",
    "gn:admin3_code":"60111.0",
    "gn:asciiname":"Pavon",
    "gn:country_code":"CR",
    "gn:dem":130,
    "gn:feature_class":"P",
    "gn:feature_code":"PPL",
    "gn:name":"Pav\u00f3n",
    "gn:population":0,
    "gn:timezone":"America/Costa_Rica",
    "iso:country":"CR",
    "name:ceb_x_preferred":[
        "Pavon"
    ],
    "name:deu_x_preferred":[
        "Pav\u00f3n"
    ],
    "name:fra_x_preferred":[
        "Pavon"
    ],
    "name:ita_x_preferred":[
        "Pav\u00f3n"
    ],
    "name:por_x_preferred":[
        "Pav\u00f3n"
    ],
    "name:rus_x_preferred":[
        "\u041f\u0430\u0432\u043e\u043d"
    ],
    "name:spa_x_preferred":[
        "Pav\u00f3n"
    ],
    "name:swe_x_preferred":[
        "Pavon"
    ],
    "name:ukr_x_preferred":[
        "\u041f\u0430\u0432\u043e\u043d"
    ],
    "wof:name":"Pavon",
    "wof:placetype":"locality"
},
  "geometry": {"coordinates":[-85.08091999999998,9.74492],"type":"Point"}
}