{
  "type": "Feature",
  "properties": {
    "iso:country":"CR",
    "name:eng_x_preferred":[
        "Bols\u00f3n District"
    ],
    "name:ita_x_preferred":[
        "Bols\u00f3n"
    ],
    "name:spa_x_preferred":[
        "Bols\u00f3n"
    ],
    "name:unk_x_variant":[
        "Bolg\u00f3n"
    ],
    "name:zho_x_preferred":[
        "\u535a\u723e\u677e\u5340"
    ],
    "qs:gn_country":"CR",
    "qs:gn_fcode":"PPL",
    "qs:gn_pop":0,
    "qs:name":"Bols\u00f3n",
    "qs:name_adm0":"Costa Rica",
    "qs:name_adm1":"Guanacaste",
    "qs:photos":9,
    "qs:photos_1k":2,
    "qs:photos_9k":1,
    "qs:photos_9r":1,
    "qs:photos_all":9,
    "qs:photos_sr":1,
    "qs:placetype":"Town",
    "qs:pop_sr":"3",
    "qs:woe_adm0":23424791,
    "wd:wordcount":109,
    "wof:name":"Bols\u00f3n",
    "wof:placetype":"locality"
},
  "geometry": {"coordinates":[-85.45133,10.36282],"type":"Point"}
}