{
  "type": "Feature",
  "properties": {
    "gn:admin1_code":"01",
    "gn:admin2_code":"202",
    "gn:admin3_code":"20212.0",
    "gn:asciiname":"Bajo Castillo",
    "gn:country_code":"CR",
    "gn:dem":712,
    "gn:feature_class":"P",
    "gn:feature_code":"PPL",
    "gn:name":"Bajo Castillo",
    "gn:population":0,
    "gn:timezone":"America/Costa_Rica",
    "iso:country":"CR",
    "wof:name":"Bajo Castillo",
    "wof:placetype":"locality"
},
  "geometry": {"coordinates":[-84.64089,10.13726],"type":"Point"}
}