{
  "type": "Feature",
  "properties": {
    "gn:admin1_code":"08",
    "gn:admin2_code":"107",
    "gn:admin3_code":"10704.0",
    "gn:asciiname":"Dantas",
    "gn:country_code":"CR",
    "gn:dem":633,
    "gn:feature_class":"P",
    "gn:feature_code":"PPL",
    "gn:name":"Dantas",
    "gn:population":0,
    "gn:timezone":"America/Costa_Rica",
    "iso:country":"CR",
    "name:rus_x_preferred":[
        "\u0414\u0430\u043d\u0442\u0430\u0441"
    ],
    "wof:name":"Dantas",
    "wof:placetype":"locality"
},
  "geometry": {"coordinates":[-84.32039,9.89044],"type":"Point"}
}