{
  "type": "Feature",
  "properties": {
    "gn:admin1_code":"08",
    "gn:admin2_code":"104",
    "gn:admin3_code":"10406.0",
    "gn:asciiname":"Candelarita",
    "gn:country_code":"CR",
    "gn:dem":980,
    "gn:feature_class":"P",
    "gn:feature_code":"PPL",
    "gn:name":"Candelarita",
    "gn:population":0,
    "gn:timezone":"America/Costa_Rica",
    "iso:country":"CR",
    "wof:name":"Candelarita",
    "wof:placetype":"locality"
},
  "geometry": {"coordinates":[-84.33866999999999,9.79498],"type":"Point"}
}