{
  "type": "Feature",
  "properties": {
    "gn:admin1_code":"06",
    "gn:admin2_code":"703",
    "gn:admin3_code":"70302.0",
    "gn:asciiname":"Madre de Dios",
    "gn:country_code":"CR",
    "gn:dem":61,
    "gn:feature_class":"P",
    "gn:feature_code":"PPL",
    "gn:name":"Madre de Dios",
    "gn:population":0,
    "gn:timezone":"America/Costa_Rica",
    "iso:country":"CR",
    "name:ceb_x_preferred":[
        "Madre de Dios"
    ],
    "name:deu_x_preferred":[
        "Madre de Dios"
    ],
    "name:fra_x_preferred":[
        "Madre de Dios"
    ],
    "name:glg_x_preferred":[
        "Madre de Dios"
    ],
    "name:ita_x_preferred":[
        "Madre de Dios"
    ],
    "name:kaz_x_preferred":[
        "\u041c\u0430\u0434\u0440\u0435-\u0434\u0435-\u0414\u044c\u043e\u0441"
    ],
    "name:lit_x_preferred":[
        "Madre de Diosas"
    ],
    "name:nld_x_preferred":[
        "Madre de Dios"
    ],
    "name:por_x_preferred":[
        "Madre de Dios"
    ],
    "name:que_x_preferred":[
        "Madre de Dios"
    ],
    "name:rus_x_preferred":[
        "\u041c\u0430\u0434\u0440\u0435-\u0434\u0435-\u0414\u044c\u043e\u0441"
    ],
    "name:spa_x_preferred":[
        "Madre de Dios"
    ],
    "name:swe_x_preferred":[
        "Madre de Dios"
    ],
    "wof:name":"Madre de Dios",
    "wof:placetype":"locality"
},
  "geometry": {"coordinates":[-83.40099000000002,10.09356],"type":"Point"}
}