{
  "type": "Feature",
  "properties": {
    "gn:admin1_code":"06",
    "gn:admin2_code":"703",
    "gn:admin3_code":"70302.0",
    "gn:asciiname":"Madre de Dios",
    "gn:country_code":"CR",
    "gn:dem":61,
    "gn:feature_class":"P",
    "gn:feature_code":"PPL",
    "gn:name":"Madre de Dios",
    "gn:population":0,
    "gn:timezone":"America/Costa_Rica",
    "iso:country":"CR",
    "name:ara_x_preferred":[
        "\u0645\u0627\u062f\u0631 \u062f\u064a \u062f\u064a\u0648\u0633"
    ],
    "name:ben_x_preferred":[
        "\u09ae\u09be\u09a6\u09cd\u09b0\u09c7 \u09a6\u09c7 \u09a6\u09bf\u0993\u09b8"
    ],
    "name:hin_x_preferred":[
        "\u092e\u093e\u0926\u094d\u0930\u0947 \u0926 \u0921\u093e\u092f\u0913\u0938"
    ],
    "name:hun_x_preferred":[
        "Madre de Dios"
    ],
    "name:ind_x_preferred":[
        "Madre de Dios"
    ],
    "name:kaz_x_preferred":[
        "\u041c\u0430\u0434\u0440\u0435-\u0434\u0435-\u0414\u044c\u043e\u0441"
    ],
    "name:kor_x_preferred":[
        "\ub9c8\ub4dc\ub808 \ub4dc \ub514\uc624\uc2a4"
    ],
    "name:por_x_preferred":[
        "Madre de Deus"
    ],
    "name:rus_x_preferred":[
        "\u041c\u0430\u0434\u0440\u0435-\u0434\u0435-\u0414\u044c\u043e\u0441"
    ],
    "name:tur_x_preferred":[
        "Madre de Dios"
    ],
    "name:urd_x_preferred":[
        "\u0645\u0627\u062f\u0631\u06d2 \u0688\u06cc \u0688\u0627\u0626\u0648\u0633"
    ],
    "wof:name":"Madre de Dios",
    "wof:placetype":"locality"
},
  "geometry": {"coordinates":[-83.40098999999999,10.09356],"type":"Point"}
}