{
  "type": "Feature",
  "properties": {
    "iso:country":"CR",
    "name:ceb_x_preferred":[
        "Ulloa"
    ],
    "name:deu_x_preferred":[
        "Ulloa"
    ],
    "name:fra_x_preferred":[
        "Ulloa"
    ],
    "name:glg_x_preferred":[
        "Ulloa"
    ],
    "name:ita_x_preferred":[
        "Ulloa"
    ],
    "name:jpn_x_preferred":[
        "\u30a6\u30b8\u30e7\u30a2"
    ],
    "name:msa_x_preferred":[
        "Ulloa"
    ],
    "name:rus_x_preferred":[
        "\u0423\u043b\u044c\u043e\u0430"
    ],
    "name:sco_x_preferred":[
        "Ulloa"
    ],
    "name:spa_x_preferred":[
        "Ulloa"
    ],
    "name:swe_x_preferred":[
        "Ulloa"
    ],
    "name:ukr_x_preferred":[
        "\u0423\u043b\u044c\u043e\u0430"
    ],
    "name:vie_x_preferred":[
        "Ulloa"
    ],
    "qs:gn_pop":0,
    "qs:name":"Ulloa",
    "qs:name_adm0":"Costa Rica",
    "qs:name_adm1":"Heredia",
    "qs:photos":6,
    "qs:photos_1k":1,
    "qs:photos_9k":1,
    "qs:photos_9r":1,
    "qs:photos_all":6,
    "qs:photos_sr":1,
    "qs:placetype":"LocalAdmin",
    "qs:pop_sr":"0",
    "qs:woe_adm0":23424791,
    "wof:name":"Ulloa",
    "wof:placetype":"localadmin"
},
  "geometry": {"coordinates":[-84.146406,9.981039],"type":"Point"}
}