{
  "type": "Feature",
  "properties": {
    "gn:admin1_code":"01",
    "gn:admin2_code":"215",
    "gn:admin3_code":"21502.0",
    "gn:asciiname":"Argelia",
    "gn:country_code":"CR",
    "gn:dem":47,
    "gn:feature_class":"P",
    "gn:feature_code":"PPL",
    "gn:name":"Argelia",
    "gn:population":0,
    "gn:timezone":"America/Costa_Rica",
    "iso:country":"CR",
    "name:ceb_x_preferred":[
        "Argelia"
    ],
    "name:deu_x_preferred":[
        "Argelia"
    ],
    "name:fra_x_preferred":[
        "Argelia"
    ],
    "name:ita_x_preferred":[
        "Argelia"
    ],
    "name:nld_x_preferred":[
        "Argelia"
    ],
    "name:por_x_preferred":[
        "Arg\u00e9lia"
    ],
    "name:sco_x_preferred":[
        "Argelia"
    ],
    "name:spa_x_preferred":[
        "Argelia"
    ],
    "name:swe_x_preferred":[
        "Argelia"
    ],
    "name:vie_x_preferred":[
        "Argelia"
    ],
    "name:war_x_preferred":[
        "Argelia"
    ],
    "wof:name":"Argelia",
    "wof:placetype":"locality"
},
  "geometry": {"coordinates":[-84.78001,10.75263],"type":"Point"}
}