{
  "type": "Feature",
  "properties": {
    "iso:country":"CR",
    "name:ceb_x_preferred":[
        "Pavon"
    ],
    "name:deu_x_preferred":[
        "Pav\u00f3n"
    ],
    "name:fra_x_preferred":[
        "Pavon"
    ],
    "name:ita_x_preferred":[
        "Pav\u00f3n"
    ],
    "name:por_x_preferred":[
        "Pav\u00f3n"
    ],
    "name:rus_x_preferred":[
        "\u041f\u0430\u0432\u043e\u043d"
    ],
    "name:spa_x_preferred":[
        "Pav\u00f3n"
    ],
    "name:swe_x_preferred":[
        "Pavon"
    ],
    "name:ukr_x_preferred":[
        "\u041f\u0430\u0432\u043e\u043d"
    ],
    "qs:gn_pop":0,
    "qs:name":"Pavon",
    "qs:name_adm0":"Costa Rica",
    "qs:name_adm1":"Puntarenas",
    "qs:photos":1,
    "qs:photos_1k":1,
    "qs:photos_9k":1,
    "qs:photos_9r":2,
    "qs:photos_all":35,
    "qs:photos_sr":1,
    "qs:placetype":"LocalAdmin",
    "qs:pop_sr":"0",
    "qs:woe_adm0":23424791,
    "wof:name":"Pavon",
    "wof:placetype":"localadmin"
},
  "geometry": {"coordinates":[-83.14229899999999,8.539008],"type":"Point"}
}