{
  "type": "Feature",
  "properties": {
    "gn:admin1_code":"06",
    "gn:admin2_code":"705",
    "gn:admin3_code":"70502.0",
    "gn:asciiname":"Margarita",
    "gn:country_code":"CR",
    "gn:dem":13,
    "gn:feature_class":"P",
    "gn:feature_code":"PPL",
    "gn:name":"Margarita",
    "gn:population":0,
    "gn:timezone":"America/Costa_Rica",
    "iso:country":"CR",
    "wof:name":"Margarita",
    "wof:placetype":"locality"
},
  "geometry": {"coordinates":[-83.32250999999999,10.0819],"type":"Point"}
}