{
  "type": "Feature",
  "properties": {
    "gn:admin1_code":"06",
    "gn:admin2_code":"703",
    "gn:admin3_code":"70301.0",
    "gn:asciiname":"San Alberto de Siquirres",
    "gn:country_code":"CR",
    "gn:dem":31,
    "gn:feature_class":"P",
    "gn:feature_code":"PPL",
    "gn:name":"San Alberto de Siquirres",
    "gn:population":0,
    "gn:timezone":"America/Costa_Rica",
    "iso:country":"CR",
    "wof:name":"San Alberto de Siquirres",
    "wof:placetype":"locality"
},
  "geometry": {"coordinates":[-83.48430999999999,10.14972],"type":"Point"}
}