{
  "type": "Feature",
  "properties": {
    "iso:country":"CR",
    "name:cat_x_preferred":[
        "Palmira"
    ],
    "name:ceb_x_preferred":[
        "Palmira"
    ],
    "name:deu_x_preferred":[
        "Palmira"
    ],
    "name:fra_x_preferred":[
        "Palmira"
    ],
    "name:hun_x_preferred":[
        "Palmira"
    ],
    "name:ita_x_preferred":[
        "Palmira"
    ],
    "name:mlg_x_preferred":[
        "Palmira"
    ],
    "name:nld_x_preferred":[
        "Palmira"
    ],
    "name:pol_x_preferred":[
        "Palmira"
    ],
    "name:por_x_preferred":[
        "Palmira"
    ],
    "name:sco_x_preferred":[
        "Palmira"
    ],
    "name:slv_x_preferred":[
        "Palmira"
    ],
    "name:spa_x_preferred":[
        "Palmira"
    ],
    "name:srp_x_preferred":[
        "\u041f\u0430\u043b\u043c\u0438\u0440\u0430"
    ],
    "name:swe_x_preferred":[
        "Palmira"
    ],
    "name:xmf_x_preferred":[
        "\u10de\u10d0\u10da\u10db\u10d8\u10e0\u10d0"
    ],
    "qs:gn_pop":0,
    "qs:name":"Palmira",
    "qs:name_adm0":"Costa Rica",
    "qs:name_adm1":"Guanacaste",
    "qs:photos":2226,
    "qs:photos_1k":451,
    "qs:photos_9k":10,
    "qs:photos_9r":9,
    "qs:photos_all":2236,
    "qs:photos_sr":16,
    "qs:placetype":"LocalAdmin",
    "qs:pop_sr":"0",
    "qs:woe_adm0":23424791,
    "wof:name":"Palmira",
    "wof:placetype":"localadmin"
},
  "geometry": {"coordinates":[-85.07906850000001,10.6683675],"type":"Point"}
}