{
  "type": "Feature",
  "properties": {
    "gn:admin1_code":"06",
    "gn:admin2_code":"701",
    "gn:admin3_code":"70104.0",
    "gn:asciiname":"Westfalia",
    "gn:country_code":"CR",
    "gn:dem":4,
    "gn:feature_class":"P",
    "gn:feature_code":"PPL",
    "gn:name":"Westfalia",
    "gn:population":0,
    "gn:timezone":"America/Costa_Rica",
    "iso:country":"CR",
    "name:deu_x_preferred":[
        "Westfalia Mobil"
    ],
    "name:fra_x_preferred":[
        "Westfalia"
    ],
    "name:nld_x_preferred":[
        "Westfalia Mobil"
    ],
    "name:swe_x_preferred":[
        "Westfalia"
    ],
    "wof:name":"Westfalia",
    "wof:placetype":"locality"
},
  "geometry": {"coordinates":[-83.00995,9.94145],"type":"Point"}
}