{
  "type": "Feature",
  "properties": {
    "gn:admin1_code":"08",
    "gn:admin2_code":"119",
    "gn:admin3_code":"11907.0",
    "gn:asciiname":"Gibre",
    "gn:country_code":"CR",
    "gn:dem":493,
    "gn:feature_class":"P",
    "gn:feature_code":"PPL",
    "gn:name":"Gibre",
    "gn:population":0,
    "gn:timezone":"America/Costa_Rica",
    "iso:country":"CR",
    "wof:name":"Gibre",
    "wof:placetype":"locality"
},
  "geometry": {"coordinates":[-83.54149,9.15762],"type":"Point"}
}