{
  "type": "Feature",
  "properties": {
    "gn:admin1_code":"06",
    "gn:admin2_code":"703",
    "gn:admin3_code":"70303.0",
    "gn:asciiname":"Bonilla Abajo",
    "gn:country_code":"CR",
    "gn:dem":276,
    "gn:feature_class":"P",
    "gn:feature_code":"PPL",
    "gn:name":"Bonilla Abajo",
    "gn:population":0,
    "gn:timezone":"America/Costa_Rica",
    "iso:country":"CR",
    "wof:name":"Bonilla Abajo",
    "wof:placetype":"locality"
},
  "geometry": {"coordinates":[-83.6056,10.01243],"type":"Point"}
}