{
  "type": "Feature",
  "properties": {
    "gn:admin1_code":"08",
    "gn:admin2_code":"115",
    "gn:admin3_code":"11501.0",
    "gn:asciiname":"Lourdes",
    "gn:country_code":"CR",
    "gn:dem":1238,
    "gn:feature_class":"P",
    "gn:feature_code":"PPL",
    "gn:name":"Lourdes",
    "gn:population":0,
    "gn:timezone":"America/Costa_Rica",
    "iso:country":"CR",
    "wof:name":"Lourdes",
    "wof:placetype":"locality"
},
  "geometry": {"coordinates":[-84.03974000000002,9.93664],"type":"Point"}
}