{
  "type": "Feature",
  "properties": {
    "gn:admin1_code":"08",
    "gn:admin2_code":"103",
    "gn:admin3_code":"10304.0",
    "gn:asciiname":"Mendez",
    "gn:country_code":"CR",
    "gn:dem":1168,
    "gn:feature_class":"P",
    "gn:feature_code":"PPL",
    "gn:name":"M\u00e9ndez",
    "gn:population":0,
    "gn:timezone":"America/Costa_Rica",
    "iso:country":"CR",
    "name:srp_x_preferred":[
        "\u041c\u0435\u043d\u0434\u0435\u0437"
    ],
    "wof:name":"Mendez",
    "wof:placetype":"locality"
},
  "geometry": {"coordinates":[-84.06667,9.88333],"type":"Point"}
}