{
  "type": "Feature",
  "properties": {
    "gn:admin1_code":"02",
    "gn:admin2_code":"308",
    "gn:asciiname":"Casa Mata",
    "gn:country_code":"CR",
    "gn:dem":1878,
    "gn:feature_class":"P",
    "gn:feature_code":"PPL",
    "gn:name":"Casa Mata",
    "gn:population":0,
    "gn:timezone":"America/Costa_Rica",
    "iso:country":"CR",
    "wof:name":"Casa Mata",
    "wof:placetype":"locality"
},
  "geometry": {"coordinates":[-83.9901,9.77756],"type":"Point"}
}