{
  "type": "Feature",
  "properties": {
    "gn:admin1_code":"06",
    "gn:admin2_code":"703",
    "gn:admin3_code":"70301.0",
    "gn:asciiname":"San Alberto Nuevo",
    "gn:country_code":"CR",
    "gn:dem":24,
    "gn:feature_class":"P",
    "gn:feature_code":"PPL",
    "gn:name":"San Alberto Nuevo",
    "gn:population":0,
    "gn:timezone":"America/Costa_Rica",
    "iso:country":"CR",
    "name:und_x_variant":[
        "San Alberto",
        "San Alberto Nuevo"
    ],
    "wof:name":"San Alberto Nuevo",
    "wof:placetype":"locality"
},
  "geometry": {"coordinates":[-83.47373,10.15575],"type":"Point"}
}