{
  "type": "Feature",
  "properties": {
    "gn:admin1_code":"07",
    "gn:admin2_code":"603",
    "gn:admin3_code":"60304.0",
    "gn:asciiname":"Doboncragua",
    "gn:country_code":"CR",
    "gn:dem":437,
    "gn:feature_class":"P",
    "gn:feature_code":"PPL",
    "gn:name":"Doboncragua",
    "gn:population":0,
    "gn:timezone":"America/Costa_Rica",
    "iso:country":"CR",
    "wof:name":"Doboncragua",
    "wof:placetype":"locality"
},
  "geometry": {"coordinates":[-83.3199,9.04701],"type":"Point"}
}