{
  "type": "Feature",
  "properties": {
    "gn:admin1_code":"07",
    "gn:admin2_code":"601",
    "gn:admin3_code":"60113.0",
    "gn:asciiname":"Curazao",
    "gn:cc2":"CR",
    "gn:country_code":"CR",
    "gn:dem":22,
    "gn:feature_class":"P",
    "gn:feature_code":"PPL",
    "gn:name":"Curazao",
    "gn:population":0,
    "gn:timezone":"America/Costa_Rica",
    "iso:country":"CR",
    "name:und_x_variant":[
        "Curacao",
        "Curazao"
    ],
    "wof:name":"Curazao",
    "wof:placetype":"locality"
},
  "geometry": {"coordinates":[-85.16667,10.11667],"type":"Point"}
}