{
  "type": "Feature",
  "properties": {
    "gn:admin1_code":"04",
    "gn:admin2_code":"406",
    "gn:admin3_code":"40602.0",
    "gn:asciiname":"San Josecito",
    "gn:country_code":"CR",
    "gn:dem":1330,
    "gn:feature_class":"P",
    "gn:feature_code":"PPL",
    "gn:name":"San Josecito",
    "gn:population":0,
    "gn:timezone":"America/Costa_Rica",
    "iso:country":"CR",
    "wof:name":"San Josecito",
    "wof:placetype":"locality"
},
  "geometry": {"coordinates":[-84.03716999999997,10.01908],"type":"Point"}
}