{
  "type": "Feature",
  "properties": {
    "gn:admin1_code":"03",
    "gn:admin2_code":"502",
    "gn:admin3_code":"50203.0",
    "gn:asciiname":"Chira",
    "gn:country_code":"CR",
    "gn:dem":61,
    "gn:feature_class":"P",
    "gn:feature_code":"PPL",
    "gn:name":"Chira",
    "gn:population":0,
    "gn:timezone":"America/Costa_Rica",
    "iso:country":"CR",
    "name:ceb_x_preferred":[
        "Chira"
    ],
    "name:deu_x_preferred":[
        "Chira"
    ],
    "name:ita_x_preferred":[
        "Chira"
    ],
    "name:nor_x_preferred":[
        "Chira"
    ],
    "name:ron_x_preferred":[
        "Chira"
    ],
    "wof:name":"Chira",
    "wof:placetype":"locality"
},
  "geometry": {"coordinates":[-85.48333000000002,10.25],"type":"Point"}
}