{
  "type": "Feature",
  "properties": {
    "iso:country":"CR",
    "qs:gn_country":"CR",
    "qs:gn_fcode":"PPL",
    "qs:gn_pop":0,
    "qs:name":"Bananito Sur",
    "qs:name_adm0":"Costa Rica",
    "qs:name_adm1":"Limon",
    "qs:photos":22,
    "qs:photos_1k":4,
    "qs:photos_9k":1,
    "qs:photos_9r":1,
    "qs:photos_all":22,
    "qs:photos_sr":1,
    "qs:placetype":"Town",
    "qs:pop_sr":"0",
    "qs:woe_adm0":23424791,
    "wof:name":"Bananito Sur",
    "wof:placetype":"locality"
},
  "geometry": {"coordinates":[-83.00378000000001,9.87199],"type":"Point"}
}