{
  "type": "Feature",
  "properties": {
    "gn:admin1_code":"03",
    "gn:admin2_code":"508",
    "gn:admin3_code":"50804.0",
    "gn:asciiname":"Naranjos Agrios",
    "gn:country_code":"CR",
    "gn:dem":580,
    "gn:feature_class":"P",
    "gn:feature_code":"PPL",
    "gn:name":"Naranjos Agrios",
    "gn:population":0,
    "gn:timezone":"America/Costa_Rica",
    "iso:country":"CR",
    "wof:name":"Naranjos Agrios",
    "wof:placetype":"locality"
},
  "geometry": {"coordinates":[-84.98414,10.54153],"type":"Point"}
}