{
  "type": "Feature",
  "properties": {
    "gn:admin1_code":"07",
    "gn:admin2_code":"605",
    "gn:admin3_code":"60501.0",
    "gn:asciiname":"Punta Mala",
    "gn:country_code":"CR",
    "gn:dem":16,
    "gn:feature_class":"P",
    "gn:feature_code":"PPL",
    "gn:name":"Punta Mala",
    "gn:population":0,
    "gn:timezone":"America/Costa_Rica",
    "iso:country":"CR",
    "wof:name":"Punta Mala",
    "wof:placetype":"locality"
},
  "geometry": {"coordinates":[-83.63673,9.05592],"type":"Point"}
}