{
  "type": "Feature",
  "properties": {
    "gn:admin1_code":"08",
    "gn:admin2_code":"117",
    "gn:admin3_code":"11701.0",
    "gn:asciiname":"Llano de Piedra",
    "gn:cc2":"CR",
    "gn:country_code":"CR",
    "gn:dem":1655,
    "gn:feature_class":"P",
    "gn:feature_code":"PPL",
    "gn:name":"Llano de Piedra",
    "gn:population":0,
    "gn:timezone":"America/Costa_Rica",
    "iso:country":"CR",
    "name:und_x_variant":[
        "Llano de la Piedra",
        "Llano de Piedra"
    ],
    "wof:name":"Llano de Piedra",
    "wof:placetype":"locality"
},
  "geometry": {"coordinates":[-83.98333000000002,9.65],"type":"Point"}
}