{
  "type": "Feature",
  "properties": {
    "gn:admin1_code":"03",
    "gn:admin2_code":"503",
    "gn:admin3_code":"50304.0",
    "gn:asciiname":"Canafistula",
    "gn:country_code":"CR",
    "gn:dem":62,
    "gn:feature_class":"P",
    "gn:feature_code":"PPL",
    "gn:name":"Ca\u00f1af\u00edstula",
    "gn:population":0,
    "gn:timezone":"America/Costa_Rica",
    "iso:country":"CR",
    "wof:name":"Canafistula",
    "wof:placetype":"locality"
},
  "geometry": {"coordinates":[-85.70899,10.38686],"type":"Point"}
}