{
  "type": "Feature",
  "properties": {
    "gn:admin1_code":"06",
    "gn:admin2_code":"705",
    "gn:admin3_code":"70501.0",
    "gn:asciiname":"Chirripo",
    "gn:country_code":"CR",
    "gn:dem":50,
    "gn:feature_class":"P",
    "gn:feature_code":"PPL",
    "gn:name":"Chirrip\u00f3",
    "gn:population":0,
    "gn:timezone":"America/Costa_Rica",
    "iso:country":"CR",
    "wof:name":"Chirripo",
    "wof:placetype":"locality"
},
  "geometry": {"coordinates":[-83.30011,9.97228],"type":"Point"}
}