{
  "type": "Feature",
  "properties": {
    "gn:admin1_code":"03",
    "gn:admin2_code":"507",
    "gn:admin3_code":"50702.0",
    "gn:asciiname":"Sierra",
    "gn:country_code":"CR",
    "gn:dem":287,
    "gn:feature_class":"P",
    "gn:feature_code":"PPL",
    "gn:name":"Sierra",
    "gn:population":0,
    "gn:timezone":"America/Costa_Rica",
    "iso:country":"CR",
    "name:und_x_variant":[
        "La Sierra",
        "Sierra"
    ],
    "wof:name":"Sierra",
    "wof:placetype":"locality"
},
  "geometry": {"coordinates":[-84.92797,10.28512],"type":"Point"}
}