{
  "type": "Feature",
  "properties": {
    "gn:admin1_code":"03",
    "gn:admin2_code":"507",
    "gn:admin3_code":"50702.0",
    "gn:asciiname":"Sierra",
    "gn:country_code":"CR",
    "gn:dem":287,
    "gn:feature_class":"P",
    "gn:feature_code":"PPL",
    "gn:name":"Sierra",
    "gn:population":0,
    "gn:timezone":"America/Costa_Rica",
    "iso:country":"CR",
    "name:bre_x_preferred":[
        "Sierra"
    ],
    "name:ceb_x_preferred":[
        "Sierra"
    ],
    "name:ces_x_preferred":[
        "Sierra"
    ],
    "name:deu_x_preferred":[
        "Sierra"
    ],
    "name:fra_x_preferred":[
        "Sierra"
    ],
    "name:heb_x_preferred":[
        "\u05e1\u05d9\u05d9\u05e8\u05d4"
    ],
    "name:hrv_x_preferred":[
        "Sierra"
    ],
    "name:ita_x_preferred":[
        "Sierra"
    ],
    "name:jpn_x_preferred":[
        "\u30b7\u30a8\u30e9"
    ],
    "name:kor_x_preferred":[
        "\uc2dc\uc5d0\ub77c"
    ],
    "name:nld_x_preferred":[
        "Sierra"
    ],
    "name:pol_x_preferred":[
        "Sierra"
    ],
    "name:por_x_preferred":[
        "Sierra"
    ],
    "name:que_x_preferred":[
        "Sierra"
    ],
    "name:ron_x_preferred":[
        "Sierra"
    ],
    "name:rus_x_preferred":[
        "\u0421\u044c\u0435\u0440\u0440\u0430"
    ],
    "name:spa_x_preferred":[
        "Sierra"
    ],
    "name:srp_x_preferred":[
        "\u0421\u0438\u0458\u0435\u0440\u0430"
    ],
    "name:swe_x_preferred":[
        "Sierra"
    ],
    "name:tur_x_preferred":[
        "Sierra"
    ],
    "name:und_x_variant":[
        "La Sierra",
        "Sierra"
    ],
    "name:zho_x_preferred":[
        "Sierra"
    ],
    "wof:name":"Sierra",
    "wof:placetype":"locality"
},
  "geometry": {"coordinates":[-84.92797,10.28512],"type":"Point"}
}