{
  "type": "Feature",
  "properties": {
    "gn:admin1_code":"08",
    "gn:admin2_code":"101",
    "gn:admin3_code":"10111.0",
    "gn:asciiname":"Luna Park",
    "gn:country_code":"CR",
    "gn:dem":1129,
    "gn:feature_class":"P",
    "gn:feature_code":"PPL",
    "gn:name":"Luna Park",
    "gn:population":0,
    "gn:timezone":"America/Costa_Rica",
    "iso:country":"CR",
    "name:fra_x_preferred":[
        "Luna Park"
    ],
    "name:ita_x_preferred":[
        "Luna park"
    ],
    "name:jpn_x_preferred":[
        "\u30eb\u30ca\u30d1\u30fc\u30af"
    ],
    "name:kor_x_preferred":[
        "\ub8e8\ub098\ud30c\ud06c"
    ],
    "name:rus_x_preferred":[
        "\u041b\u0443\u043d\u0430-\u043f\u0430\u0440\u043a"
    ],
    "name:ukr_x_preferred":[
        "\u041b\u0443\u043d\u0430-\u043f\u0430\u0440\u043a"
    ],
    "wof:name":"Luna Park",
    "wof:placetype":"locality"
},
  "geometry": {"coordinates":[-84.08333,9.91667],"type":"Point"}
}