{
  "type": "Feature",
  "properties": {
    "gn:admin1_code":"08",
    "gn:admin2_code":"103",
    "gn:asciiname":"La Sierra",
    "gn:country_code":"CR",
    "gn:dem":1968,
    "gn:feature_class":"P",
    "gn:feature_code":"PPL",
    "gn:name":"La Sierra",
    "gn:population":0,
    "gn:timezone":"America/Costa_Rica",
    "iso:country":"CR",
    "name:ast_x_preferred":[
        "La Sierra"
    ],
    "name:ceb_x_preferred":[
        "La Sierra"
    ],
    "name:ita_x_preferred":[
        "La Sierra"
    ],
    "name:spa_x_preferred":[
        "La Sierra"
    ],
    "name:swe_x_preferred":[
        "La Sierra"
    ],
    "name:vie_x_preferred":[
        "La Sierra"
    ],
    "wof:name":"La Sierra",
    "wof:placetype":"locality"
},
  "geometry": {"coordinates":[-83.97955,9.74633],"type":"Point"}
}