{
  "type": "Feature",
  "properties": {
    "gn:admin1_code":"06",
    "gn:admin2_code":"703",
    "gn:admin3_code":"70306.0",
    "gn:asciiname":"Alegria",
    "gn:country_code":"CR",
    "gn:dem":408,
    "gn:feature_class":"P",
    "gn:feature_code":"PPL",
    "gn:name":"Alegr\u00eda",
    "gn:population":0,
    "gn:timezone":"America/Costa_Rica",
    "iso:country":"CR",
    "name:bul_x_preferred":[
        "\u0410\u043b\u0435\u0433\u0440\u0438\u044f"
    ],
    "name:ceb_x_preferred":[
        "Alegria"
    ],
    "name:ita_x_preferred":[
        "Alegria"
    ],
    "name:nld_x_preferred":[
        "Alegria"
    ],
    "name:por_x_preferred":[
        "Alegria"
    ],
    "name:rus_x_preferred":[
        "\u0410\u043b\u0435\u0433\u0440\u0438\u044f"
    ],
    "name:scn_x_preferred":[
        "Alligrizza"
    ],
    "name:swe_x_preferred":[
        "Alegria"
    ],
    "name:war_x_preferred":[
        "Alegria"
    ],
    "wof:name":"Alegria",
    "wof:placetype":"locality"
},
  "geometry": {"coordinates":[-83.60035000000001,10.08894],"type":"Point"}
}