{
  "type": "Feature",
  "properties": {
    "gn:country":"CR",
    "iso:country":"CR",
    "name:ceb_x_preferred":[
        "Golfito"
    ],
    "name:deu_x_preferred":[
        "Golfito"
    ],
    "name:fra_x_preferred":[
        "Golfito"
    ],
    "name:ita_x_preferred":[
        "Golfito"
    ],
    "name:lit_x_preferred":[
        "Golfitas"
    ],
    "name:nor_x_preferred":[
        "Golfito"
    ],
    "name:ron_x_preferred":[
        "Golfito"
    ],
    "name:spa_x_preferred":[
        "Golfito"
    ],
    "name:swe_x_preferred":[
        "Golfito"
    ],
    "name:zho_x_preferred":[
        "\u6208\u723e\u83f2\u6258\u5340"
    ],
    "qs:name":"Golfito",
    "qs:name_adm0":"Costa Rica",
    "qs:name_adm1":"Puntarenas",
    "qs:photos":190,
    "qs:photos_1k":39,
    "qs:photos_9k":5,
    "qs:photos_9r":7,
    "qs:photos_all":1168,
    "qs:photos_sr":4,
    "qs:placetype":"LocalAdmin",
    "qs:pop_sr":"0",
    "wd:wordcount":703,
    "wof:name":"Golfito",
    "wof:placetype":"localadmin"
},
  "geometry": {"coordinates":[-83.17440000000001,8.630836],"type":"Point"}
}