{
  "type": "Feature",
  "properties": {
    "gn:country":"CR",
    "iso:country":"CR",
    "name:ara_x_preferred":[
        "\u062c\u0648\u0644\u0641\u064a\u062a\u0648"
    ],
    "name:ben_x_preferred":[
        "\u0997\u09cb\u09b2\u09ab\u09bf\u09a4\u09cb"
    ],
    "name:ceb_x_preferred":[
        "Golfito"
    ],
    "name:deu_x_preferred":[
        "Golfito"
    ],
    "name:ell_x_preferred":[
        "\u0393\u03ba\u03bf\u03bb\u03c6\u03af\u03c4\u03bf"
    ],
    "name:eng_x_preferred":[
        "Golfito"
    ],
    "name:fas_x_preferred":[
        "\u06af\u0644\u0641\u06cc\u062a\u0648"
    ],
    "name:fra_x_preferred":[
        "Golfito"
    ],
    "name:heb_x_preferred":[
        "\u05d2\u05d5\u05dc\u05e4\u05d9\u05d8\u05d5"
    ],
    "name:hin_x_preferred":[
        "\u0917\u094b\u0932\u094d\u092b\u093c\u093f\u0924\u094b"
    ],
    "name:hun_x_preferred":[
        "Golfito"
    ],
    "name:ind_x_preferred":[
        "Golfito"
    ],
    "name:ita_x_preferred":[
        "Golfito"
    ],
    "name:jpn_x_preferred":[
        "\u30b4\u30eb\u30d5\u30a3\u30fc\u30c8"
    ],
    "name:kor_x_preferred":[
        "\uace8\ud53c\ud1a0"
    ],
    "name:lit_x_preferred":[
        "Golfitas"
    ],
    "name:nld_x_preferred":[
        "Golfito"
    ],
    "name:nob_x_preferred":[
        "Golfito"
    ],
    "name:por_x_preferred":[
        "Golfito"
    ],
    "name:ron_x_preferred":[
        "Golfito"
    ],
    "name:rus_x_preferred":[
        "\u0413\u043e\u043b\u044c\u0444\u0438\u0442\u043e"
    ],
    "name:spa_x_preferred":[
        "Golfito"
    ],
    "name:swe_x_preferred":[
        "Golfito"
    ],
    "name:tur_x_preferred":[
        "Golfito"
    ],
    "name:urd_x_preferred":[
        "\u06af\u0648\u0644\u0641\u06cc\u0679\u0648"
    ],
    "name:vie_x_preferred":[
        "Golfito"
    ],
    "name:zho_x_preferred":[
        "\u6208\u723e\u83f2\u6258\u5340"
    ],
    "qs:name":"Golfito",
    "qs:name_adm0":"Costa Rica",
    "qs:name_adm1":"Puntarenas",
    "qs:photos":190,
    "qs:photos_1k":39,
    "qs:photos_9k":5,
    "qs:photos_9r":7,
    "qs:photos_all":1168,
    "qs:photos_sr":4,
    "qs:placetype":"LocalAdmin",
    "qs:pop_sr":"0",
    "wd:wordcount":703,
    "wof:name":"Golfito",
    "wof:placetype":"localadmin"
},
  "geometry": {"coordinates":[-83.17440000000001,8.630836],"type":"Point"}
}