{
  "type": "Feature",
  "properties": {
    "gn:admin1_code":"07",
    "gn:admin2_code":"601",
    "gn:admin3_code":"60104.0",
    "gn:asciiname":"Cabo Blanco",
    "gn:country_code":"CR",
    "gn:dem":12,
    "gn:feature_class":"P",
    "gn:feature_code":"PPL",
    "gn:name":"Cabo Blanco",
    "gn:population":0,
    "gn:timezone":"America/Costa_Rica",
    "iso:country":"CR",
    "name:bre_x_preferred":[
        "Cabo Blanco"
    ],
    "name:ceb_x_preferred":[
        "Cabo Blanco"
    ],
    "name:fin_x_preferred":[
        "Cabo Blanco"
    ],
    "name:fra_x_preferred":[
        "Cabo Blanco"
    ],
    "name:por_x_preferred":[
        "Cabo Blanco"
    ],
    "name:spa_x_preferred":[
        "Cabo Blanco"
    ],
    "name:swe_x_preferred":[
        "Cabo Blanco"
    ],
    "name:und_x_variant":[
        "Cabo Blanco del Golfo",
        "Cabo Blanco"
    ],
    "wof:name":"Cabo Blanco",
    "wof:placetype":"locality"
},
  "geometry": {"coordinates":[-84.98976,9.93376],"type":"Point"}
}