{
  "type": "Feature",
  "properties": {
    "gn:admin1_code":"07",
    "gn:admin2_code":"601",
    "gn:admin3_code":"60104.0",
    "gn:asciiname":"Cerro Frio",
    "gn:country_code":"CR",
    "gn:dem":578,
    "gn:feature_class":"P",
    "gn:feature_code":"PPL",
    "gn:name":"Cerro Fr\u00edo",
    "gn:population":0,
    "gn:timezone":"America/Costa_Rica",
    "iso:country":"CR",
    "wof:name":"Cerro Frio",
    "wof:placetype":"locality"
},
  "geometry": {"coordinates":[-85.12188,9.81898],"type":"Point"}
}