{
  "type": "Feature",
  "properties": {
    "iso:country":"CR",
    "name:ceb_x_preferred":[
        "Central"
    ],
    "name:deu_x_preferred":[
        "Central"
    ],
    "name:est_x_preferred":[
        "Central"
    ],
    "name:fas_x_preferred":[
        "\u0645\u0631\u06a9\u0632\u06cc"
    ],
    "name:fra_x_preferred":[
        "Central"
    ],
    "name:heb_x_preferred":[
        "\u05de\u05e8\u05db\u05d6"
    ],
    "name:hun_x_preferred":[
        "K\u00f6z\u00e9p"
    ],
    "name:ita_x_preferred":[
        "Central"
    ],
    "name:jpn_x_preferred":[
        "\u30bb\u30f3\u30c8\u30e9\u30eb"
    ],
    "name:kor_x_preferred":[
        "\uc13c\ud2b8\ub7f4"
    ],
    "name:nld_x_preferred":[
        "Central"
    ],
    "name:pol_x_preferred":[
        "Central"
    ],
    "name:por_x_preferred":[
        "Central"
    ],
    "name:rus_x_preferred":[
        "\u0426\u0435\u043d\u0442\u0440\u0430\u043b\u044c"
    ],
    "name:slk_x_preferred":[
        "Centr\u00e1l"
    ],
    "name:spa_x_preferred":[
        "Central"
    ],
    "name:swe_x_preferred":[
        "Central"
    ],
    "name:tam_x_preferred":[
        "\u0b9a\u0bc6\u0ba9\u0bcd\u0b9f\u0bcd\u0bb0\u0bb2\u0bcd"
    ],
    "name:tha_x_preferred":[
        "\u0e01\u0e25\u0e32\u0e07"
    ],
    "name:ukr_x_preferred":[
        "\u0421\u0435\u043d\u0442\u0440\u0430\u043b"
    ],
    "name:vol_x_preferred":[
        "Central"
    ],
    "name:zho_x_preferred":[
        "\u4e2d"
    ],
    "qs:gn_pop":0,
    "qs:name":"Central",
    "qs:name_adm0":"Costa Rica",
    "qs:name_adm1":"San Jose",
    "qs:photos":361,
    "qs:photos_1k":73,
    "qs:photos_9k":2,
    "qs:photos_9r":5,
    "qs:photos_all":361,
    "qs:photos_sr":6,
    "qs:placetype":"Suburb",
    "qs:pop_sr":"0",
    "qs:woe_adm0":23424791,
    "wof:name":"Central",
    "wof:placetype":"neighbourhood"
},
  "geometry": {"coordinates":[-84.07974,9.936894],"type":"Point"}
}