{
  "type": "Feature",
  "properties": {
    "iso:country":"CR",
    "qs:gn_pop":0,
    "qs:name":"Central",
    "qs:name_adm0":"Costa Rica",
    "qs:name_adm1":"San Jose",
    "qs:photos":361,
    "qs:photos_1k":73,
    "qs:photos_9k":2,
    "qs:photos_9r":5,
    "qs:photos_all":361,
    "qs:photos_sr":6,
    "qs:placetype":"Suburb",
    "qs:pop_sr":"0",
    "qs:woe_adm0":23424791,
    "wof:name":"Central",
    "wof:placetype":"neighbourhood"
},
  "geometry": {"coordinates":[-84.07974,9.936894],"type":"Point"}
}