{
  "type": "Feature",
  "properties": {
    "gn:admin1_code":"01",
    "gn:admin2_code":"204",
    "gn:admin3_code":"20402.0",
    "gn:asciiname":"Patio de Agua",
    "gn:country_code":"CR",
    "gn:dem":622,
    "gn:feature_class":"P",
    "gn:feature_code":"PPL",
    "gn:name":"Patio de Agua",
    "gn:population":0,
    "gn:timezone":"America/Costa_Rica",
    "iso:country":"CR",
    "wof:name":"Patio de Agua",
    "wof:placetype":"locality"
},
  "geometry": {"coordinates":[-84.47315999999999,9.94708],"type":"Point"}
}