{
  "type": "Feature",
  "properties": {
    "gn:admin1_code":"03",
    "gn:admin2_code":"510",
    "gn:admin3_code":"51001.0",
    "gn:asciiname":"Cacao",
    "gn:country_code":"CR",
    "gn:dem":201,
    "gn:feature_class":"P",
    "gn:feature_code":"PPL",
    "gn:name":"Cacao",
    "gn:population":0,
    "gn:timezone":"America/Costa_Rica",
    "iso:country":"CR",
    "name:ceb_x_preferred":[
        "Cacao"
    ],
    "name:dan_x_preferred":[
        "Kakao"
    ],
    "name:deu_x_preferred":[
        "Kakao"
    ],
    "name:fra_x_preferred":[
        "Cacao"
    ],
    "name:hun_x_preferred":[
        "Kaka\u00f3"
    ],
    "name:ind_x_preferred":[
        "Cacao"
    ],
    "name:ita_x_preferred":[
        "Cacao"
    ],
    "name:kor_x_preferred":[
        "\uce74\uce74\uc624"
    ],
    "name:nld_x_preferred":[
        "Cacao"
    ],
    "name:pol_x_preferred":[
        "Kakao"
    ],
    "name:rus_x_preferred":[
        "Cacao"
    ],
    "name:spa_x_preferred":[
        "Cacao"
    ],
    "name:swe_x_preferred":[
        "Cacao"
    ],
    "wof:name":"Cacao",
    "wof:placetype":"locality"
},
  "geometry": {"coordinates":[-85.63333,11.11667],"type":"Point"}
}