{
  "type": "Feature",
  "properties": {
    "gn:country":"CR",
    "gn:fcode":"PPL",
    "gn:population":1556,
    "iso:country":"CR",
    "qs:name":"Pacayas",
    "qs:photos_9r":0,
    "qs:photos_sr":0,
    "qs:pop_sr":"3",
    "wof:name":"Pacayas",
    "wof:placetype":"locality",
    "wof:population":1556
},
  "geometry": {"coordinates":[-84.04764,9.80709],"type":"Point"}
}