{
  "type": "Feature",
  "properties": {
    "gn:admin1_code":"04",
    "gn:admin2_code":"405",
    "gn:admin3_code":"40504.0",
    "gn:asciiname":"Getsemani",
    "gn:country_code":"CR",
    "gn:dem":1387,
    "gn:feature_class":"P",
    "gn:feature_code":"PPL",
    "gn:name":"Getseman\u00ed",
    "gn:population":0,
    "gn:timezone":"America/Costa_Rica",
    "iso:country":"CR",
    "wof:name":"Getsemani",
    "wof:placetype":"locality"
},
  "geometry": {"coordinates":[-84.10705,10.0362],"type":"Point"}
}