{
  "type": "Feature",
  "properties": {
    "gn:admin1_code":"07",
    "gn:admin2_code":"608",
    "gn:admin3_code":"60802.0",
    "gn:asciiname":"San Ramon",
    "gn:country_code":"CR",
    "gn:dem":934,
    "gn:feature_class":"P",
    "gn:feature_code":"PPL",
    "gn:name":"San Ram\u00f3n",
    "gn:population":0,
    "gn:timezone":"America/Costa_Rica",
    "iso:country":"CR",
    "wof:name":"San Ramon",
    "wof:placetype":"locality"
},
  "geometry": {"coordinates":[-82.91667,8.85],"type":"Point"}
}