{
  "type": "Feature",
  "properties": {
    "gn:admin1_code":"03",
    "gn:admin2_code":"503",
    "gn:admin3_code":"50307.0",
    "gn:asciiname":"Duendes",
    "gn:country_code":"CR",
    "gn:dem":30,
    "gn:feature_class":"P",
    "gn:feature_code":"PPL",
    "gn:name":"Duendes",
    "gn:population":0,
    "gn:timezone":"America/Costa_Rica",
    "iso:country":"CR",
    "wof:name":"Duendes",
    "wof:placetype":"locality"
},
  "geometry": {"coordinates":[-85.52129000000002,10.29392],"type":"Point"}
}