{
  "type": "Feature",
  "properties": {
    "iso:country":"CR",
    "name:eng_x_preferred":[
        "Nacascolo"
    ],
    "name:ita_x_preferred":[
        "Nacascolo"
    ],
    "name:nld_x_preferred":[
        "Nacascolo"
    ],
    "name:unk_x_variant":[
        "Nacascola"
    ],
    "name:zho_x_preferred":[
        "\u7d0d\u5361\u65af\u79d1\u6d1b\u5340"
    ],
    "qs:gn_country":"CR",
    "qs:gn_fcode":"PPL",
    "qs:gn_pop":0,
    "qs:name":"Nacascolo",
    "qs:name_adm0":"Costa Rica",
    "qs:name_adm1":"Guanacaste",
    "qs:photos":651,
    "qs:photos_1k":132,
    "qs:photos_9k":3,
    "qs:photos_9r":5,
    "qs:photos_all":651,
    "qs:photos_sr":8,
    "qs:placetype":"Town",
    "qs:pop_sr":"0",
    "qs:woe_adm0":23424791,
    "wd:wordcount":51,
    "wof:name":"Nacascolo",
    "wof:placetype":"locality"
},
  "geometry": {"coordinates":[-85.67682000000001,10.62844],"type":"Point"}
}