{
  "type": "Feature",
  "properties": {
    "gn:admin1_code":"01",
    "gn:admin2_code":"202",
    "gn:admin3_code":"20205.0",
    "gn:asciiname":"Bureal",
    "gn:country_code":"CR",
    "gn:dem":1254,
    "gn:feature_class":"P",
    "gn:feature_code":"PPL",
    "gn:name":"Bureal",
    "gn:population":0,
    "gn:timezone":"America/Costa_Rica",
    "iso:country":"CR",
    "wof:name":"Bureal",
    "wof:placetype":"locality"
},
  "geometry": {"coordinates":[-84.56050999999999,10.12885],"type":"Point"}
}