{
  "type": "Feature",
  "properties": {
    "gn:admin1_code":"06",
    "gn:admin2_code":"703",
    "gn:admin3_code":"70306.0",
    "gn:asciiname":"Altos Herediana",
    "gn:country_code":"CR",
    "gn:dem":201,
    "gn:feature_class":"P",
    "gn:feature_code":"PPL",
    "gn:name":"Altos Herediana",
    "gn:population":0,
    "gn:timezone":"America/Costa_Rica",
    "iso:country":"CR",
    "wof:name":"Altos Herediana",
    "wof:placetype":"locality"
},
  "geometry": {"coordinates":[-83.57437,10.11933],"type":"Point"}
}