{
  "type": "Feature",
  "properties": {
    "iso:country":"CR",
    "qs:gn_pop":0,
    "qs:name":"Rio Blanco",
    "qs:name_adm0":"Costa Rica",
    "qs:name_adm1":"Limon",
    "qs:photos":340,
    "qs:photos_1k":69,
    "qs:photos_9k":2,
    "qs:photos_9r":5,
    "qs:photos_all":377,
    "qs:photos_sr":5,
    "qs:placetype":"LocalAdmin",
    "qs:pop_sr":"0",
    "qs:woe_adm0":23424791,
    "wof:name":"Rio Blanco",
    "wof:placetype":"localadmin"
},
  "geometry": {"coordinates":[-83.123245,10.006167],"type":"Point"}
}