{
  "type": "Feature",
  "properties": {
    "iso:country":"CR",
    "name:eng_x_preferred":[
        "Tronadora"
    ],
    "name:ita_x_preferred":[
        "Tronadora"
    ],
    "qs:gn_country":"CR",
    "qs:gn_fcode":"PPL",
    "qs:gn_pop":0,
    "qs:name":"Tronadora",
    "qs:name_adm0":"Costa Rica",
    "qs:name_adm1":"Guanacaste",
    "qs:photos":36,
    "qs:photos_1k":7,
    "qs:photos_9k":1,
    "qs:photos_9r":2,
    "qs:photos_all":36,
    "qs:photos_sr":2,
    "qs:placetype":"Town",
    "qs:pop_sr":"0",
    "qs:woe_adm0":23424791,
    "wd:wordcount":114,
    "wof:name":"Tronadora",
    "wof:placetype":"locality"
},
  "geometry": {"coordinates":[-84.8973,10.49524],"type":"Point"}
}