{
  "type": "Feature",
  "properties": {
    "gn:admin1_code":"06",
    "gn:admin2_code":"701",
    "gn:admin3_code":"70103.0",
    "gn:asciiname":"Rio Madre",
    "gn:country_code":"CR",
    "gn:dem":19,
    "gn:feature_class":"P",
    "gn:feature_code":"PPL",
    "gn:name":"R\u00edo Madre",
    "gn:population":0,
    "gn:timezone":"America/Costa_Rica",
    "iso:country":"CR",
    "wof:name":"Rio Madre",
    "wof:placetype":"locality"
},
  "geometry": {"coordinates":[-83.15042,9.99302],"type":"Point"}
}