{
  "type": "Feature",
  "properties": {
    "gn:admin1_code":"04",
    "gn:admin2_code":"410",
    "gn:admin3_code":"41003.0",
    "gn:asciiname":"El Salvador",
    "gn:cc2":"CR",
    "gn:country_code":"CR",
    "gn:dem":212,
    "gn:feature_class":"P",
    "gn:feature_code":"PPL",
    "gn:name":"El Salvador",
    "gn:population":0,
    "gn:timezone":"America/Costa_Rica",
    "iso:country":"CR",
    "name:und_x_variant":[
        "Salvador",
        "El Salvador"
    ],
    "wof:name":"El Salvador",
    "wof:placetype":"locality"
},
  "geometry": {"coordinates":[-83.90000000000001,10.23333],"type":"Point"}
}