{
  "type": "Feature",
  "properties": {
    "gn:admin1_code":"03",
    "gn:admin2_code":"502",
    "gn:admin3_code":"50201.0",
    "gn:asciiname":"Pilas Blancas",
    "gn:country_code":"CR",
    "gn:dem":200,
    "gn:feature_class":"P",
    "gn:feature_code":"PPL",
    "gn:name":"Pilas Blancas",
    "gn:population":0,
    "gn:timezone":"America/Costa_Rica",
    "iso:country":"CR",
    "name:spa_x_preferred":[
        "Las Pilas"
    ],
    "wof:name":"Pilas Blancas",
    "wof:placetype":"locality"
},
  "geometry": {"coordinates":[-85.58333,10.03333],"type":"Point"}
}