{
  "type": "Feature",
  "properties": {
    "iso:country":"CR",
    "name:ceb_x_preferred":[
        "Tobos\u00ed"
    ],
    "name:eng_x_preferred":[
        "Tobosi"
    ],
    "name:ita_x_preferred":[
        "Tobosi"
    ],
    "name:spa_x_preferred":[
        "Tobosi"
    ],
    "name:swe_x_preferred":[
        "Tobos\u00ed"
    ],
    "name:zho_x_preferred":[
        "\u6258\u6c83\u897f\u5340"
    ],
    "qs:gn_country":"CR",
    "qs:gn_fcode":"PPL",
    "qs:gn_pop":4060,
    "qs:name":"Tobos\u00ed",
    "qs:name_adm0":"Costa Rica",
    "qs:name_adm1":"Cartago",
    "qs:photos":0,
    "qs:photos_1k":0,
    "qs:photos_9k":1,
    "qs:photos_9r":1,
    "qs:photos_all":1,
    "qs:photos_sr":0,
    "qs:placetype":"Town",
    "qs:pop_sr":"4",
    "qs:woe_adm0":23424791,
    "wd:wordcount":365,
    "wof:name":"Tobos\u00ed",
    "wof:placetype":"locality",
    "wof:population":4060
},
  "geometry": {"coordinates":[-83.98390999999999,9.83837],"type":"Point"}
}