{
  "type": "Feature",
  "properties": {
    "gn:admin1_code":"03",
    "gn:admin2_code":"505",
    "gn:admin3_code":"50502.0",
    "gn:asciiname":"Angeles",
    "gn:country_code":"CR",
    "gn:dem":29,
    "gn:feature_class":"P",
    "gn:feature_code":"PPL",
    "gn:name":"\u00c1ngeles",
    "gn:population":0,
    "gn:timezone":"America/Costa_Rica",
    "iso:country":"CR",
    "name:ceb_x_preferred":[
        "Angeles"
    ],
    "name:deu_x_preferred":[
        "Angeles"
    ],
    "name:ita_x_preferred":[
        "Angeles"
    ],
    "name:kor_x_preferred":[
        "\uc564\uc824\ub808\uc2a4"
    ],
    "name:rus_x_preferred":[
        "\u0410\u043d\u0445\u0435\u043b\u0435\u0441"
    ],
    "name:swe_x_preferred":[
        "Angeles"
    ],
    "name:und_x_variant":[
        "Boquerones",
        "Los \u00c1ngeles",
        "Paquerones",
        "\u00c1ngeles"
    ],
    "name:war_x_preferred":[
        "Angeles"
    ],
    "wof:name":"Angeles",
    "wof:placetype":"locality"
},
  "geometry": {"coordinates":[-85.58083000000001,10.52317],"type":"Point"}
}