{
  "type": "Feature",
  "properties": {
    "gn:admin1_code":"03",
    "gn:admin2_code":"505",
    "gn:admin3_code":"50502.0",
    "gn:asciiname":"Angeles",
    "gn:country_code":"CR",
    "gn:dem":29,
    "gn:feature_class":"P",
    "gn:feature_code":"PPL",
    "gn:name":"\u00c1ngeles",
    "gn:population":0,
    "gn:timezone":"America/Costa_Rica",
    "iso:country":"CR",
    "name:und_x_variant":[
        "Boquerones",
        "Los \u00c1ngeles",
        "Paquerones",
        "\u00c1ngeles"
    ],
    "wof:name":"Angeles",
    "wof:placetype":"locality"
},
  "geometry": {"coordinates":[-85.58083000000001,10.52317],"type":"Point"}
}