{
  "type": "Feature",
  "properties": {
    "gn:admin1_code":"04",
    "gn:admin2_code":"404",
    "gn:admin3_code":"40406.0",
    "gn:asciiname":"Lajas",
    "gn:country_code":"CR",
    "gn:dem":1612,
    "gn:feature_class":"P",
    "gn:feature_code":"PPL",
    "gn:name":"Lajas",
    "gn:population":0,
    "gn:timezone":"America/Costa_Rica",
    "iso:country":"CR",
    "name:ceb_x_preferred":[
        "Lajas"
    ],
    "name:fra_x_preferred":[
        "Lajas"
    ],
    "name:ita_x_preferred":[
        "Lajas"
    ],
    "name:nld_x_preferred":[
        "Lajas"
    ],
    "name:pol_x_preferred":[
        "Lajas"
    ],
    "name:swe_x_preferred":[
        "Lajas"
    ],
    "wof:name":"Lajas",
    "wof:placetype":"locality"
},
  "geometry": {"coordinates":[-84.14081999999998,10.08515],"type":"Point"}
}