{
  "type": "Feature",
  "properties": {
    "gn:admin1_code":"02",
    "gn:admin2_code":"308",
    "gn:admin3_code":"30802.0",
    "gn:asciiname":"Paso Macho",
    "gn:country_code":"CR",
    "gn:dem":2498,
    "gn:feature_class":"P",
    "gn:feature_code":"PPL",
    "gn:name":"Paso Macho",
    "gn:population":0,
    "gn:timezone":"America/Costa_Rica",
    "iso:country":"CR",
    "wof:name":"Paso Macho",
    "wof:placetype":"locality"
},
  "geometry": {"coordinates":[-83.89790000000001,9.68774],"type":"Point"}
}