{
  "type": "Feature",
  "properties": {
    "gn:admin1_code":"06",
    "gn:admin2_code":"704",
    "gn:admin3_code":"70403.0",
    "gn:asciiname":"Hone Creek",
    "gn:country_code":"CR",
    "gn:dem":10,
    "gn:feature_class":"P",
    "gn:feature_code":"PPL",
    "gn:name":"Hone Creek",
    "gn:population":0,
    "gn:timezone":"America/Costa_Rica",
    "iso:country":"CR",
    "wof:name":"Hone Creek",
    "wof:placetype":"locality"
},
  "geometry": {"coordinates":[-82.79759,9.65894],"type":"Point"}
}