{
  "type": "Feature",
  "properties": {
    "gn:admin1_code":"07",
    "gn:admin2_code":"603",
    "gn:admin3_code":"60305.0",
    "gn:asciiname":"Pilas",
    "gn:country_code":"CR",
    "gn:dem":247,
    "gn:feature_class":"P",
    "gn:feature_code":"PPL",
    "gn:name":"Pilas",
    "gn:population":0,
    "gn:timezone":"America/Costa_Rica",
    "iso:country":"CR",
    "wof:name":"Pilas",
    "wof:placetype":"locality"
},
  "geometry": {"coordinates":[-83.43326,9.08358],"type":"Point"}
}