{
  "type": "Feature",
  "properties": {
    "gn:admin1_code":"03",
    "gn:admin2_code":"501",
    "gn:admin3_code":"50105.0",
    "gn:asciiname":"Castilla",
    "gn:country_code":"CR",
    "gn:dem":267,
    "gn:feature_class":"P",
    "gn:feature_code":"PPL",
    "gn:name":"Castilla",
    "gn:population":0,
    "gn:timezone":"America/Costa_Rica",
    "iso:country":"CR",
    "wof:name":"Castilla",
    "wof:placetype":"locality"
},
  "geometry": {"coordinates":[-85.43356999999997,10.71824],"type":"Point"}
}