{
  "type": "Feature",
  "properties": {
    "gn:admin1_code":"03",
    "gn:admin2_code":"503",
    "gn:admin3_code":"50304.0",
    "gn:asciiname":"Tempate",
    "gn:country_code":"CR",
    "gn:dem":66,
    "gn:feature_class":"P",
    "gn:feature_code":"PPL",
    "gn:name":"Tempate",
    "gn:population":0,
    "gn:timezone":"America/Costa_Rica",
    "iso:country":"CR",
    "wof:name":"Tempate",
    "wof:placetype":"locality"
},
  "geometry": {"coordinates":[-85.72020999999999,10.41416],"type":"Point"}
}