{
  "type": "Feature",
  "properties": {
    "iso:country":"CR",
    "qs:gn_country":"CR",
    "qs:gn_fcode":"PPL",
    "qs:gn_pop":12195,
    "qs:name":"San Josecito",
    "qs:name_adm0":"Costa Rica",
    "qs:name_adm1":"Heredia",
    "qs:photos":0,
    "qs:photos_1k":0,
    "qs:photos_9k":0,
    "qs:photos_9r":0,
    "qs:photos_all":0,
    "qs:photos_sr":0,
    "qs:placetype":"Town",
    "qs:pop_sr":"6",
    "qs:woe_adm0":23424791,
    "wof:name":"San Josecito",
    "wof:placetype":"locality",
    "wof:population":12195
},
  "geometry": {"coordinates":[-84.09999999999999,10.01667],"type":"Point"}
}