{
  "type": "Feature",
  "properties": {
    "iso:country":"CR",
    "qs:gn_country":"CR",
    "qs:gn_fcode":"PPL",
    "qs:gn_pop":1090,
    "qs:name":"Bijagua",
    "qs:name_adm0":"Costa Rica",
    "qs:name_adm1":"Alajuela",
    "qs:photos":0,
    "qs:photos_1k":0,
    "qs:photos_9k":1,
    "qs:photos_9r":1,
    "qs:photos_all":3,
    "qs:photos_sr":0,
    "qs:placetype":"Town",
    "qs:pop_sr":"3",
    "qs:woe_adm0":23424791,
    "wof:name":"Bijagua",
    "wof:placetype":"locality",
    "wof:population":1090
},
  "geometry": {"coordinates":[-85.05676,10.7328],"type":"Point"}
}