{
  "type": "Feature",
  "properties": {
    "iso:country":"CR",
    "qs:gn_country":"CR",
    "qs:gn_fcode":"PPL",
    "qs:gn_pop":0,
    "qs:name":"Raicero",
    "qs:name_adm0":"Costa Rica",
    "qs:name_adm1":"Cartago",
    "qs:photos":132,
    "qs:photos_1k":27,
    "qs:photos_9k":1,
    "qs:photos_9r":3,
    "qs:photos_all":132,
    "qs:photos_sr":3,
    "qs:placetype":"Town",
    "qs:pop_sr":"0",
    "qs:woe_adm0":23424791,
    "wof:name":"Raicero",
    "wof:placetype":"locality"
},
  "geometry": {"coordinates":[-83.74133999999999,9.97998],"type":"Point"}
}