{
  "type": "Feature",
  "properties": {
    "gn:admin1_code":"01",
    "gn:admin2_code":"210",
    "gn:admin3_code":"21007.0",
    "gn:asciiname":"Angeles",
    "gn:country_code":"CR",
    "gn:dem":85,
    "gn:feature_class":"P",
    "gn:feature_code":"PPL",
    "gn:name":"\u00c1ngeles",
    "gn:population":0,
    "gn:timezone":"America/Costa_Rica",
    "iso:country":"CR",
    "name:ceb_x_preferred":[
        "Angeles"
    ],
    "name:deu_x_preferred":[
        "Angeles"
    ],
    "name:ita_x_preferred":[
        "Angeles"
    ],
    "name:kor_x_preferred":[
        "\uc564\uc824\ub808\uc2a4"
    ],
    "name:rus_x_preferred":[
        "\u0410\u043d\u0445\u0435\u043b\u0435\u0441"
    ],
    "name:swe_x_preferred":[
        "Angeles"
    ],
    "name:war_x_preferred":[
        "Angeles"
    ],
    "wof:name":"Angeles",
    "wof:placetype":"locality"
},
  "geometry": {"coordinates":[-84.55620999999999,10.45763],"type":"Point"}
}