{
  "type": "Feature",
  "properties": {
    "gn:admin1_code":"01",
    "gn:admin2_code":"210",
    "gn:admin3_code":"21007.0",
    "gn:asciiname":"Angeles",
    "gn:country_code":"CR",
    "gn:dem":85,
    "gn:feature_class":"P",
    "gn:feature_code":"PPL",
    "gn:name":"\u00c1ngeles",
    "gn:population":0,
    "gn:timezone":"America/Costa_Rica",
    "iso:country":"CR",
    "name:ceb_x_preferred":[
        "Angeles"
    ],
    "name:deu_x_preferred":[
        "Angeles"
    ],
    "name:ita_x_preferred":[
        "Angeles"
    ],
    "name:kor_x_preferred":[
        "\uc564\uc824\ub808\uc2a4"
    ],
    "name:rus_x_preferred":[
        "\u0410\u043d\u0434\u0436\u0435\u043b\u0435\u0441"
    ],
    "name:rus_x_variant":[
        "\u0410\u043d\u0445\u0435\u043b\u0435\u0441"
    ],
    "name:swe_x_preferred":[
        "Angeles City"
    ],
    "name:swe_x_variant":[
        "Angeles"
    ],
    "name:tur_x_preferred":[
        "Angeles"
    ],
    "name:ukr_x_preferred":[
        "\u0410\u043d\u0434\u0436\u0435\u043b\u0435\u0441"
    ],
    "name:urd_x_preferred":[
        "\u0627\u06cc\u0646\u062c\u0644\u06cc\u0633"
    ],
    "name:vie_x_preferred":[
        "Angeles"
    ],
    "name:war_x_preferred":[
        "Angeles"
    ],
    "name:zho_cn_x_preferred":[
        "\u5b89\u8d6b\u83b1\u65af"
    ],
    "name:zho_tw_x_preferred":[
        "\u5b89\u742a\u4f86\u65af"
    ],
    "wof:name":"Angeles",
    "wof:placetype":"locality"
},
  "geometry": {"coordinates":[-84.55620999999999,10.45763],"type":"Point"}
}