{
  "type": "Feature",
  "properties": {
    "gn:admin1_code":"03",
    "gn:admin2_code":"503",
    "gn:admin3_code":"50303.0",
    "gn:asciiname":"Caimito",
    "gn:cc2":"CR",
    "gn:country_code":"CR",
    "gn:dem":53,
    "gn:feature_class":"P",
    "gn:feature_code":"PPL",
    "gn:name":"Caimito",
    "gn:population":0,
    "gn:timezone":"America/Costa_Rica",
    "iso:country":"CR",
    "name:und_x_variant":[
        "Hacienda Caimito",
        "Caimito"
    ],
    "wof:name":"Caimito",
    "wof:placetype":"locality"
},
  "geometry": {"coordinates":[-85.71666999999999,10.28333],"type":"Point"}
}