{
  "type": "Feature",
  "properties": {
    "gn:admin1_code":"01",
    "gn:admin2_code":"201",
    "gn:admin3_code":"20113.0",
    "gn:asciiname":"Cuesta Colorada",
    "gn:country_code":"CR",
    "gn:dem":844,
    "gn:feature_class":"P",
    "gn:feature_code":"PPL",
    "gn:name":"Cuesta Colorada",
    "gn:population":0,
    "gn:timezone":"America/Costa_Rica",
    "iso:country":"CR",
    "wof:name":"Cuesta Colorada",
    "wof:placetype":"locality"
},
  "geometry": {"coordinates":[-84.26760999999998,10.00836],"type":"Point"}
}