{
  "type": "Feature",
  "properties": {
    "gn:admin1_code":"01",
    "gn:admin2_code":"214",
    "gn:admin3_code":"21404.0",
    "gn:asciiname":"Corrales",
    "gn:cc2":"CR",
    "gn:country_code":"CR",
    "gn:dem":74,
    "gn:feature_class":"P",
    "gn:feature_code":"PPL",
    "gn:name":"Corrales",
    "gn:population":0,
    "gn:timezone":"America/Costa_Rica",
    "iso:country":"CR",
    "name:und_x_variant":[
        "Los Corrales",
        "Corrales"
    ],
    "wof:name":"Corrales",
    "wof:placetype":"locality"
},
  "geometry": {"coordinates":[-84.68333,10.76667],"type":"Point"}
}