{
  "type": "Feature",
  "properties": {
    "gn:admin1_code":"03",
    "gn:admin2_code":"504",
    "gn:admin3_code":"50401.0",
    "gn:asciiname":"Huacalito",
    "gn:country_code":"CR",
    "gn:dem":94,
    "gn:feature_class":"P",
    "gn:feature_code":"PPL",
    "gn:name":"Huacalito",
    "gn:population":0,
    "gn:timezone":"America/Costa_Rica",
    "iso:country":"CR",
    "wof:name":"Huacalito",
    "wof:placetype":"locality"
},
  "geometry": {"coordinates":[-85.16667,10.53333],"type":"Point"}
}