{
  "type": "Feature",
  "properties": {
    "gn:admin1_code":"02",
    "gn:admin2_code":"305",
    "gn:admin3_code":"30511.0",
    "gn:asciiname":"Jesus Maria",
    "gn:country_code":"CR",
    "gn:dem":531,
    "gn:feature_class":"P",
    "gn:feature_code":"PPL",
    "gn:name":"Jes\u00fas Mar\u00eda",
    "gn:population":0,
    "gn:timezone":"America/Costa_Rica",
    "iso:country":"CR",
    "wof:name":"Jesus Maria",
    "wof:placetype":"locality"
},
  "geometry": {"coordinates":[-83.64657,9.92941],"type":"Point"}
}