{
  "type": "Feature",
  "properties": {
    "gn:admin1_code":"02",
    "gn:admin2_code":"302",
    "gn:admin3_code":"30201.0",
    "gn:asciiname":"Sanchiri",
    "gn:country_code":"CR",
    "gn:dem":1163,
    "gn:feature_class":"P",
    "gn:feature_code":"PPL",
    "gn:name":"Sanchir\u00ed",
    "gn:population":0,
    "gn:timezone":"America/Costa_Rica",
    "iso:country":"CR",
    "wof:name":"Sanchiri",
    "wof:placetype":"locality"
},
  "geometry": {"coordinates":[-83.86256999999998,9.81572],"type":"Point"}
}