{
  "type": "Feature",
  "properties": {
    "iso:country":"CR",
    "name:ceb_x_preferred":[
        "Quepos"
    ],
    "name:fra_x_preferred":[
        "Qu\u00e9pos"
    ],
    "name:ita_x_preferred":[
        "Quepos"
    ],
    "name:lit_x_preferred":[
        "Keposas"
    ],
    "name:nor_x_preferred":[
        "Quepos"
    ],
    "name:spa_x_preferred":[
        "Quepos"
    ],
    "name:swe_x_preferred":[
        "Quepos"
    ],
    "name:zho_x_preferred":[
        "\u514b\u6ce2\u65af\u533a"
    ],
    "qs:gn_pop":0,
    "qs:name":"Quepos",
    "qs:name_adm0":"Costa Rica",
    "qs:name_adm1":"Puntarenas",
    "qs:photos":3,
    "qs:photos_1k":1,
    "qs:photos_9k":46,
    "qs:photos_9r":16,
    "qs:photos_all":10277,
    "qs:photos_sr":1,
    "qs:placetype":"LocalAdmin",
    "qs:pop_sr":"0",
    "qs:woe_adm0":23424791,
    "wof:name":"Quepos",
    "wof:placetype":"localadmin"
},
  "geometry": {"coordinates":[-84.15046599999999,9.399359],"type":"Point"}
}