{
  "type": "Feature",
  "properties": {
    "gn:admin1_code":"03",
    "gn:admin2_code":"503",
    "gn:admin3_code":"50301.0",
    "gn:asciiname":"Lagunilla",
    "gn:country_code":"CR",
    "gn:dem":57,
    "gn:feature_class":"P",
    "gn:feature_code":"PPL",
    "gn:name":"Lagunilla",
    "gn:population":0,
    "gn:timezone":"America/Costa_Rica",
    "iso:country":"CR",
    "wof:name":"Lagunilla",
    "wof:placetype":"locality"
},
  "geometry": {"coordinates":[-85.64731999999999,10.2669],"type":"Point"}
}