{
  "type": "Feature",
  "properties": {
    "gn:admin1_code":"07",
    "gn:admin2_code":"610",
    "gn:admin3_code":"61001.0",
    "gn:asciiname":"Neily",
    "gn:country_code":"CR",
    "gn:dem":52,
    "gn:feature_class":"P",
    "gn:feature_code":"PPL",
    "gn:name":"Neily",
    "gn:population":0,
    "gn:timezone":"America/Costa_Rica",
    "iso:country":"CR",
    "name:und_x_variant":[
        "Villa Neilly",
        "Villa Neily",
        "Neily"
    ],
    "wof:name":"Neily",
    "wof:placetype":"locality"
},
  "geometry": {"coordinates":[-82.94096,8.64825],"type":"Point"}
}