{
  "type": "Feature",
  "properties": {
    "gn:admin1_code":"02",
    "gn:admin2_code":"306",
    "gn:admin3_code":"30602.0",
    "gn:asciiname":"Cervantes",
    "gn:country_code":"CR",
    "gn:dem":1432,
    "gn:feature_class":"P",
    "gn:feature_code":"PPL",
    "gn:name":"Cervantes",
    "gn:population":0,
    "gn:timezone":"America/Costa_Rica",
    "iso:country":"CR",
    "wof:name":"Cervantes",
    "wof:placetype":"locality"
},
  "geometry": {"coordinates":[-83.80696,9.88673],"type":"Point"}
}