{
  "type": "Feature",
  "properties": {
    "iso:country":"CR",
    "qs:gn_country":"CR",
    "qs:gn_fcode":"PPL",
    "qs:gn_pop":0,
    "qs:name":"Concepci\u00f3n",
    "qs:name_adm0":"Costa Rica",
    "qs:name_adm1":"Heredia",
    "qs:photos":66,
    "qs:photos_1k":13,
    "qs:photos_9k":1,
    "qs:photos_9r":2,
    "qs:photos_all":66,
    "qs:photos_sr":2,
    "qs:placetype":"Town",
    "qs:pop_sr":"0",
    "qs:woe_adm0":23424791,
    "wof:name":"Concepci\u00f3n",
    "wof:placetype":"locality"
},
  "geometry": {"coordinates":[-84.04732,10.02247],"type":"Point"}
}