{
  "type": "Feature",
  "properties": {
    "iso:country":"CR",
    "name:ast_x_preferred":[
        "Aeropuertu La Managua"
    ],
    "name:ceb_x_preferred":[
        "Quepos La Managua Airport"
    ],
    "name:eng_x_preferred":[
        "Quepos La Managua Airport"
    ],
    "name:fas_x_preferred":[
        "\u0641\u0631\u0648\u062f\u06af\u0627\u0647 \u06a9\u0648\u0626\u067e\u0648\u0633 \u0645\u0627\u0646\u0627\u06af\u0648\u0627"
    ],
    "name:jpn_x_preferred":[
        "\u30b1\u30dd\u30b9\u30fb\u30de\u30ca\u30b0\u30a2\u7a7a\u6e2f"
    ],
    "name:msa_x_preferred":[
        "Lapangan Terbang La Managua"
    ],
    "name:pol_x_preferred":[
        "Port lotniczy Quepos Managua"
    ],
    "name:ron_x_preferred":[
        "Aeroportul Quepos La Managua"
    ],
    "name:spa_x_preferred":[
        "Aeropuerto La Managua"
    ],
    "name:swe_x_preferred":[
        "Aeropuerto La Managua"
    ],
    "name:tgk_x_preferred":[
        "\u0424\u0443\u0440\u0443\u0434\u0433\u043e\u04b3\u0438 \u043a\u0443\u0435\u04b3\u043f\u0443\u0441 \u043c\u043e\u043d\u043e\u0433\u04ef\u043e"
    ],
    "oa:elevation_ft":"85",
    "oa:type":"medium_airport",
    "wd:wordcount":306,
    "woe:hierarchy":{
        "country_id":23424791,
        "county_id":26808785,
        "localadmin_id":26809132,
        "planet_id":1,
        "state_id":2345087
    },
    "wof:name":"Quepos Managua Airport",
    "wof:placetype":"campus"
},
  "geometry": {"coordinates":[-84.129722222222,9.4430555555556],"type":"Point"}
}