{
  "type": "Feature",
  "properties": {
    "gn:admin1_code":"06",
    "gn:admin2_code":"702",
    "gn:admin3_code":"70205.0",
    "gn:asciiname":"Cariari",
    "gn:country_code":"CR",
    "gn:dem":65,
    "gn:feature_class":"P",
    "gn:feature_code":"PPLA3",
    "gn:name":"Cariari",
    "gn:population":0,
    "gn:timezone":"America/Costa_Rica",
    "iso:country":"CR",
    "wof:name":"Cariari",
    "wof:placetype":"locality"
},
  "geometry": {"coordinates":[-83.7362,10.35719],"type":"Point"}
}