{
  "type": "Feature",
  "properties": {
    "gn:admin1_code":"08",
    "gn:admin2_code":"107",
    "gn:admin3_code":"10705.0",
    "gn:asciiname":"Llano Grande",
    "gn:country_code":"CR",
    "gn:dem":815,
    "gn:feature_class":"P",
    "gn:feature_code":"PPL",
    "gn:name":"Llano Grande",
    "gn:population":0,
    "gn:timezone":"America/Costa_Rica",
    "iso:country":"CR",
    "wof:name":"Llano Grande",
    "wof:placetype":"locality"
},
  "geometry": {"coordinates":[-84.35639999999999,9.89108],"type":"Point"}
}