{
  "type": "Feature",
  "properties": {
    "iso:country":"CR",
    "name:und_x_variant":[
        "Puerto Ballena"
    ],
    "qs:gn_country":"CR",
    "qs:gn_fcode":"PPL",
    "qs:gn_pop":0,
    "qs:name":"Ballena",
    "qs:name_adm0":"Costa Rica",
    "qs:name_adm1":"Guanacaste",
    "qs:photos":131,
    "qs:photos_1k":27,
    "qs:photos_9k":1,
    "qs:photos_9r":3,
    "qs:photos_all":131,
    "qs:photos_sr":3,
    "qs:placetype":"Town",
    "qs:pop_sr":"0",
    "qs:woe_adm0":23424791,
    "wof:name":"Ballena",
    "wof:placetype":"locality"
},
  "geometry": {"coordinates":[-85.43604000000001,10.3647],"type":"Point"}
}