{
  "type": "Feature",
  "properties": {
    "iso:country":"CR",
    "name:ita_x_preferred":[
        "Carate"
    ],
    "name:por_x_preferred":[
        "Carate"
    ],
    "qs:gn_country":"CR",
    "qs:gn_fcode":"PPL",
    "qs:gn_pop":0,
    "qs:name":"Carate",
    "qs:name_adm0":"Costa Rica",
    "qs:name_adm1":"Puntarenas",
    "qs:photos":1108,
    "qs:photos_1k":225,
    "qs:photos_9k":5,
    "qs:photos_9r":7,
    "qs:photos_all":1108,
    "qs:photos_sr":11,
    "qs:placetype":"Town",
    "qs:pop_sr":"0",
    "qs:woe_adm0":23424791,
    "wd:wordcount":37,
    "wof:name":"Carate",
    "wof:placetype":"locality"
},
  "geometry": {"coordinates":[-83.46203,8.44348],"type":"Point"}
}