{
  "type": "Feature",
  "properties": {
    "gn:admin1_code":"08",
    "gn:admin2_code":"112",
    "gn:admin3_code":"11204.0",
    "gn:asciiname":"Naranjal",
    "gn:country_code":"CR",
    "gn:dem":1034,
    "gn:feature_class":"P",
    "gn:feature_code":"PPL",
    "gn:name":"Naranjal",
    "gn:population":0,
    "gn:timezone":"America/Costa_Rica",
    "iso:country":"CR",
    "name:ceb_x_preferred":[
        "Naranjal"
    ],
    "name:deu_x_preferred":[
        "Naranjal"
    ],
    "name:pol_x_preferred":[
        "Naranjal"
    ],
    "name:spa_x_preferred":[
        "Naranjal"
    ],
    "name:swe_x_preferred":[
        "Naranjal"
    ],
    "wof:name":"Naranjal",
    "wof:placetype":"locality"
},
  "geometry": {"coordinates":[-84.22331,9.74717],"type":"Point"}
}