{
  "type": "Feature",
  "properties": {
    "gn:admin1_code":"06",
    "gn:admin2_code":"704",
    "gn:admin3_code":"70401.0",
    "gn:asciiname":"Chase",
    "gn:country_code":"CR",
    "gn:dem":41,
    "gn:feature_class":"P",
    "gn:feature_code":"PPL",
    "gn:name":"Chase",
    "gn:population":0,
    "gn:timezone":"America/Costa_Rica",
    "iso:country":"CR",
    "name:und_x_variant":[
        "Chasse",
        "Chase"
    ],
    "wof:name":"Chase",
    "wof:placetype":"locality"
},
  "geometry": {"coordinates":[-82.86703,9.59977],"type":"Point"}
}