{
  "type": "Feature",
  "properties": {
    "iso:country":"CR",
    "name:bul_x_preferred":[
        "\u041a\u043e\u043b\u043e\u043d"
    ],
    "name:ceb_x_preferred":[
        "Colon"
    ],
    "name:deu_x_preferred":[
        "Colon"
    ],
    "name:eus_x_preferred":[
        "Colon"
    ],
    "name:fas_x_preferred":[
        "\u06a9\u0648\u0644\u0648\u0646"
    ],
    "name:fra_x_preferred":[
        "Colon"
    ],
    "name:heb_x_preferred":[
        "\u05e7\u05d5\u05dc\u05d5\u05df"
    ],
    "name:ita_x_preferred":[
        "Colon"
    ],
    "name:jpn_x_preferred":[
        "\u30b3\u30ed\u30f3"
    ],
    "name:nld_x_preferred":[
        "Colon"
    ],
    "name:nno_x_preferred":[
        "Colon"
    ],
    "name:pol_x_preferred":[
        "Colon"
    ],
    "name:por_x_preferred":[
        "Colon"
    ],
    "name:sco_x_preferred":[
        "Colon"
    ],
    "name:srp_x_preferred":[
        "\u041a\u043e\u043b\u043e\u043d"
    ],
    "name:tha_x_preferred":[
        "Colon"
    ],
    "name:tur_x_preferred":[
        "Koloni"
    ],
    "name:vol_x_preferred":[
        "Colon"
    ],
    "name:wln_x_preferred":[
        "Colon"
    ],
    "qs:gn_pop":0,
    "qs:name":"Colon",
    "qs:name_adm0":"Costa Rica",
    "qs:name_adm1":"San Jose",
    "qs:photos":3,
    "qs:photos_1k":1,
    "qs:photos_9k":1,
    "qs:photos_9r":3,
    "qs:photos_all":109,
    "qs:photos_sr":1,
    "qs:placetype":"LocalAdmin",
    "qs:pop_sr":"0",
    "qs:woe_adm0":23424791,
    "wof:name":"Colon",
    "wof:placetype":"localadmin"
},
  "geometry": {"coordinates":[-84.24590999999999,9.9192245],"type":"Point"}
}