{
  "type": "Feature",
  "properties": {
    "gn:admin1_code":"04",
    "gn:admin2_code":"410",
    "gn:admin3_code":"41002.0",
    "gn:asciiname":"Colonia Carvajal",
    "gn:country_code":"CR",
    "gn:dem":227,
    "gn:feature_class":"P",
    "gn:feature_code":"PPL",
    "gn:name":"Colonia Carvajal",
    "gn:population":0,
    "gn:timezone":"America/Costa_Rica",
    "iso:country":"CR",
    "wof:name":"Colonia Carvajal",
    "wof:placetype":"locality"
},
  "geometry": {"coordinates":[-84.15000000000001,10.38333],"type":"Point"}
}