{
  "type": "Feature",
  "properties": {
    "gn:admin1_code":"03",
    "gn:admin2_code":"502",
    "gn:admin3_code":"50201.0",
    "gn:asciiname":"Quirimancito",
    "gn:country_code":"CR",
    "gn:dem":357,
    "gn:feature_class":"P",
    "gn:feature_code":"PPL",
    "gn:name":"Quirimancito",
    "gn:population":0,
    "gn:timezone":"America/Costa_Rica",
    "iso:country":"CR",
    "wof:name":"Quirimancito",
    "wof:placetype":"locality"
},
  "geometry": {"coordinates":[-85.48333000000002,10.15],"type":"Point"}
}