{
  "type": "Feature",
  "properties": {
    "gn:admin1_code":"03",
    "gn:admin2_code":"502",
    "gn:admin3_code":"50202.0",
    "gn:asciiname":"Iguanita",
    "gn:country_code":"CR",
    "gn:dem":88,
    "gn:feature_class":"P",
    "gn:feature_code":"PPL",
    "gn:name":"Iguanita",
    "gn:population":0,
    "gn:timezone":"America/Costa_Rica",
    "iso:country":"CR",
    "wof:name":"Iguanita",
    "wof:placetype":"locality"
},
  "geometry": {"coordinates":[-85.35209,10.06931],"type":"Point"}
}