{
  "type": "Feature",
  "properties": {
    "iso:country":"CR",
    "name:ast_x_preferred":[
        "Barva"
    ],
    "name:avk_x_preferred":[
        "Barva"
    ],
    "name:dan_x_preferred":[
        "Barva"
    ],
    "name:deu_x_preferred":[
        "Barva"
    ],
    "name:ell_x_preferred":[
        "\u03a3\u03b1\u03bd \u03a7\u03bf\u03c3\u03ad \u03b4\u03b5 \u03bb\u03b1 \u039c\u03bf\u03bd\u03c4\u03ac\u03bd\u03b9\u03b1 \u03b4\u03b5 \u039c\u03c0\u03ac\u03c1\u03b2\u03b1"
    ],
    "name:eng_x_preferred":[
        "Barva"
    ],
    "name:fra_x_preferred":[
        "Barva"
    ],
    "name:heb_x_preferred":[
        "\u05d1\u05e8\u05d1\u05d4"
    ],
    "name:ita_x_preferred":[
        "Barva"
    ],
    "name:lit_x_preferred":[
        "Barva"
    ],
    "name:nld_x_preferred":[
        "Barva"
    ],
    "name:nob_x_preferred":[
        "Barva"
    ],
    "name:nor_x_preferred":[
        "Barva"
    ],
    "name:spa_x_preferred":[
        "Barva"
    ],
    "name:swe_x_preferred":[
        "Barva"
    ],
    "name:und_x_variant":[
        "Barba"
    ],
    "name:zho_x_preferred":[
        "\u5df4\u723e\u74e6\u5340"
    ],
    "qs:gn_country":"CR",
    "qs:gn_fcode":"PPL",
    "qs:gn_pop":0,
    "qs:name":"Barva",
    "qs:name_adm0":"Costa Rica",
    "qs:name_adm1":"Heredia",
    "qs:photos":119,
    "qs:photos_1k":24,
    "qs:photos_9k":1,
    "qs:photos_9r":3,
    "qs:photos_all":119,
    "qs:photos_sr":3,
    "qs:placetype":"Town",
    "qs:pop_sr":"0",
    "qs:woe_adm0":23424791,
    "wof:name":"Barva",
    "wof:placetype":"locality"
},
  "geometry": {"coordinates":[-84.12451,10.02024],"type":"Point"}
}