{
  "type": "Feature",
  "properties": {
    "gn:admin1_code":"02",
    "gn:admin2_code":"307",
    "gn:admin3_code":"30705.0",
    "gn:asciiname":"Lecheria San Gerardo",
    "gn:country_code":"CR",
    "gn:dem":2503,
    "gn:feature_class":"P",
    "gn:feature_code":"PPL",
    "gn:name":"Lecheria San Gerardo",
    "gn:population":0,
    "gn:timezone":"America/Costa_Rica",
    "iso:country":"CR",
    "wof:name":"Lecheria San Gerardo",
    "wof:placetype":"locality"
},
  "geometry": {"coordinates":[-83.84551,10.00942],"type":"Point"}
}