{
  "type": "Feature",
  "properties": {
    "gn:admin1_code":"07",
    "gn:admin2_code":"606",
    "gn:admin3_code":"60602.0",
    "gn:asciiname":"Hatillo",
    "gn:country_code":"CR",
    "gn:dem":13,
    "gn:feature_class":"P",
    "gn:feature_code":"PPL",
    "gn:name":"Hatillo",
    "gn:population":0,
    "gn:timezone":"America/Costa_Rica",
    "iso:country":"CR",
    "wof:name":"Hatillo",
    "wof:placetype":"locality"
},
  "geometry": {"coordinates":[-83.90007,9.29577],"type":"Point"}
}