{
  "type": "Feature",
  "properties": {
    "gn:admin1_code":"07",
    "gn:admin2_code":"606",
    "gn:admin3_code":"60602.0",
    "gn:asciiname":"Hatillo",
    "gn:country_code":"CR",
    "gn:dem":13,
    "gn:feature_class":"P",
    "gn:feature_code":"PPL",
    "gn:name":"Hatillo",
    "gn:population":0,
    "gn:timezone":"America/Costa_Rica",
    "iso:country":"CR",
    "name:ceb_x_preferred":[
        "Hatillo"
    ],
    "name:fra_x_preferred":[
        "Hatillo"
    ],
    "name:ita_x_preferred":[
        "Hatillo"
    ],
    "name:nld_x_preferred":[
        "Hatillo"
    ],
    "name:pol_x_preferred":[
        "Hatillo"
    ],
    "name:spa_x_preferred":[
        "Hatillo"
    ],
    "name:swe_x_preferred":[
        "Hatillo"
    ],
    "wof:name":"Hatillo",
    "wof:placetype":"locality"
},
  "geometry": {"coordinates":[-83.90007,9.29577],"type":"Point"}
}