{
  "type": "Feature",
  "properties": {
    "gn:admin1_code":"03",
    "gn:admin2_code":"510",
    "gn:admin3_code":"51003.0",
    "gn:asciiname":"Espavel",
    "gn:cc2":"CR",
    "gn:country_code":"CR",
    "gn:dem":137,
    "gn:feature_class":"P",
    "gn:feature_code":"PPL",
    "gn:name":"Espavel",
    "gn:population":0,
    "gn:timezone":"America/Costa_Rica",
    "iso:country":"CR",
    "name:und_x_variant":[
        "Espabel",
        "Espavel"
    ],
    "wof:name":"Espavel",
    "wof:placetype":"locality"
},
  "geometry": {"coordinates":[-85.46666999999999,11.13333],"type":"Point"}
}