{
  "type": "Feature",
  "properties": {
    "gn:admin1_code":"07",
    "gn:admin2_code":"605",
    "gn:admin3_code":"60503.0",
    "gn:asciiname":"Potrero",
    "gn:country_code":"CR",
    "gn:dem":12,
    "gn:feature_class":"P",
    "gn:feature_code":"PPL",
    "gn:name":"Potrero",
    "gn:population":0,
    "gn:timezone":"America/Costa_Rica",
    "iso:country":"CR",
    "wof:name":"Potrero",
    "wof:placetype":"locality"
},
  "geometry": {"coordinates":[-83.52269,8.80306],"type":"Point"}
}