{
  "type": "Feature",
  "properties": {
    "gn:admin1_code":"07",
    "gn:admin2_code":"601",
    "gn:admin3_code":"60111.0",
    "gn:asciiname":"Ario",
    "gn:country_code":"CR",
    "gn:dem":28,
    "gn:feature_class":"P",
    "gn:feature_code":"PPL",
    "gn:name":"Ar\u00edo",
    "gn:population":0,
    "gn:timezone":"America/Costa_Rica",
    "iso:country":"CR",
    "name:und_x_variant":[
        "Boca de Ario",
        "Ario Oeste",
        "Ar\u00edo"
    ],
    "wof:name":"Ario",
    "wof:placetype":"locality"
},
  "geometry": {"coordinates":[-85.20902,9.70064],"type":"Point"}
}