{
  "type": "Feature",
  "properties": {
    "gn:admin1_code":"07",
    "gn:admin2_code":"601",
    "gn:admin3_code":"60101.0",
    "gn:asciiname":"Las Ciruelas",
    "gn:cc2":"CR",
    "gn:country_code":"CR",
    "gn:dem":8,
    "gn:feature_class":"P",
    "gn:feature_code":"PPL",
    "gn:name":"Las Ciruelas",
    "gn:population":0,
    "gn:timezone":"America/Costa_Rica",
    "iso:country":"CR",
    "name:und_x_variant":[
        "Ciruelitas",
        "La Ciruelas",
        "Las Ciruelas"
    ],
    "wof:name":"Las Ciruelas",
    "wof:placetype":"locality"
},
  "geometry": {"coordinates":[-84.76666999999998,10.01667],"type":"Point"}
}