{
  "type": "Feature",
  "properties": {
    "gn:admin1_code":"03",
    "gn:admin2_code":"503",
    "gn:admin3_code":"50302.0",
    "gn:asciiname":"Ortega",
    "gn:country_code":"CR",
    "gn:dem":18,
    "gn:feature_class":"P",
    "gn:feature_code":"PPL",
    "gn:name":"Ortega",
    "gn:population":0,
    "gn:timezone":"America/Costa_Rica",
    "iso:country":"CR",
    "wof:name":"Ortega",
    "wof:placetype":"locality"
},
  "geometry": {"coordinates":[-85.46064,10.36121],"type":"Point"}
}