{
  "type": "Feature",
  "properties": {
    "gn:admin1_code":"07",
    "gn:admin2_code":"601",
    "gn:asciiname":"Cuchillo",
    "gn:country_code":"CR",
    "gn:dem":13,
    "gn:feature_class":"P",
    "gn:feature_code":"PPL",
    "gn:name":"Cuchillo",
    "gn:population":0,
    "gn:timezone":"America/Costa_Rica",
    "iso:country":"CR",
    "name:spa_x_preferred":[
        "Cuchillo"
    ],
    "wof:name":"Cuchillo",
    "wof:placetype":"locality"
},
  "geometry": {"coordinates":[-85.05,9.66667],"type":"Point"}
}