{
  "type": "Feature",
  "properties": {
    "gn:admin1_code":"03",
    "gn:admin2_code":"507",
    "gn:admin3_code":"50702.0",
    "gn:asciiname":"Tres Amigos",
    "gn:country_code":"CR",
    "gn:dem":544,
    "gn:feature_class":"P",
    "gn:feature_code":"PPL",
    "gn:name":"Tres Amigos",
    "gn:population":0,
    "gn:timezone":"America/Costa_Rica",
    "iso:country":"CR",
    "name:ceb_x_preferred":[
        "Tres Amigos"
    ],
    "name:srp_x_preferred":[
        "\u0422\u0440\u0435\u0441 \u0410\u043c\u0438\u0433\u043e\u0441"
    ],
    "name:swe_x_preferred":[
        "Tres Amigos"
    ],
    "wof:name":"Tres Amigos",
    "wof:placetype":"locality"
},
  "geometry": {"coordinates":[-84.93604000000001,10.31118],"type":"Point"}
}