{
  "type": "Feature",
  "properties": {
    "gn:gn_country":"CR",
    "iso:country":"CR",
    "qs_pg:aaroncc":"CR",
    "qs_pg:gn_country":"CR",
    "qs_pg:name":"San Pablo",
    "qs_pg:name_adm0":"Costa Rica",
    "qs_pg:name_adm1":"Guanacaste",
    "qs_pg:photos":4,
    "qs_pg:photos_1k":1,
    "qs_pg:photos_9k":1,
    "qs_pg:photos_9r":1,
    "qs_pg:photos_all":4,
    "qs_pg:photos_sr":1,
    "qs_pg:pop_sr":0,
    "qs_pg:qs_pg_placetype":"localadmin",
    "qs_pg:qs_pg_placetype_gp":"LocalAdmin",
    "qs_pg:woe_adm0":23424791,
    "woe:adm0_id":23424791,
    "woe:name_adm0":"Costa Rica",
    "woe:name_adm1":"Guanacaste",
    "woe:placetype":"LocalAdmin",
    "wof:name":"San Pablo",
    "wof:placetype":"localadmin"
},
  "geometry": {"coordinates":[-85.242919,9.722593],"type":"Point"}
}