{
  "type": "Feature",
  "properties": {
    "gn:country":"CR",
    "iso:country":"CR",
    "name:bre_x_preferred":[
        "San Pablo"
    ],
    "name:cat_x_preferred":[
        "San Pablo"
    ],
    "name:ceb_x_preferred":[
        "San Pablo"
    ],
    "name:ces_x_preferred":[
        "San Pablo"
    ],
    "name:deu_x_preferred":[
        "San Pablo"
    ],
    "name:fas_x_preferred":[
        "\u0633\u0627\u0646 \u067e\u0627\u0628\u0644\u0648"
    ],
    "name:fra_x_preferred":[
        "San Pablo"
    ],
    "name:ilo_x_preferred":[
        "San Pablo"
    ],
    "name:ita_x_preferred":[
        "San Pablo"
    ],
    "name:jpn_x_preferred":[
        "\u30b5\u30f3\u30fb\u30d1\u30d6\u30ed"
    ],
    "name:kor_x_preferred":[
        "\uc0b0\ud30c\ube14\ub85c"
    ],
    "name:nds_x_preferred":[
        "San Pablo"
    ],
    "name:nld_x_preferred":[
        "San Pablo"
    ],
    "name:pol_x_preferred":[
        "San Pablo"
    ],
    "name:por_x_preferred":[
        "San Pablo"
    ],
    "name:que_x_preferred":[
        "San Pawlu"
    ],
    "name:rus_x_preferred":[
        "\u0421\u0430\u043d-\u041f\u0430\u0431\u043b\u043e"
    ],
    "name:sco_x_preferred":[
        "San Pablo"
    ],
    "name:spa_x_preferred":[
        "San Pablo"
    ],
    "name:srp_x_preferred":[
        "\u0421\u0430\u043d \u041f\u0430\u0431\u043b\u043e"
    ],
    "name:swe_x_preferred":[
        "San Pablo"
    ],
    "name:tgl_x_preferred":[
        "San Pablo"
    ],
    "name:vol_x_preferred":[
        "San Pablo"
    ],
    "name:war_x_preferred":[
        "San Pablo"
    ],
    "qs_pg:aaroncc":"CR",
    "qs_pg:gn_country":"CR",
    "qs_pg:name":"San Pablo",
    "qs_pg:name_adm0":"Costa Rica",
    "qs_pg:name_adm1":"Guanacaste",
    "qs_pg:photos":4,
    "qs_pg:photos_1k":1,
    "qs_pg:photos_9k":1,
    "qs_pg:photos_9r":1,
    "qs_pg:photos_all":4,
    "qs_pg:photos_sr":1,
    "qs_pg:pop_sr":0,
    "qs_pg:qs_pg_placetype":"localadmin",
    "qs_pg:qs_pg_placetype_gp":"LocalAdmin",
    "qs_pg:woe_adm0":23424791,
    "woe:adm0_id":23424791,
    "woe:name_adm0":"Costa Rica",
    "woe:name_adm1":"Guanacaste",
    "woe:placetype":"LocalAdmin",
    "wof:name":"San Pablo",
    "wof:placetype":"localadmin"
},
  "geometry": {"coordinates":[-85.242919,9.722593],"type":"Point"}
}