{
  "type": "Feature",
  "properties": {
    "gn:admin1_code":"03",
    "gn:admin2_code":"502",
    "gn:admin3_code":"50201.0",
    "gn:asciiname":"Guastomatal",
    "gn:country_code":"CR",
    "gn:dem":395,
    "gn:feature_class":"P",
    "gn:feature_code":"PPL",
    "gn:name":"Guastomatal",
    "gn:population":0,
    "gn:timezone":"America/Costa_Rica",
    "iso:country":"CR",
    "wof:name":"Guastomatal",
    "wof:placetype":"locality"
},
  "geometry": {"coordinates":[-85.56214,10.04734],"type":"Point"}
}