{
  "type": "Feature",
  "properties": {
    "iso:country":"CR",
    "qs:gn_pop":0,
    "qs:name":"Pacayas",
    "qs:name_adm0":"Costa Rica",
    "qs:name_adm1":"Cartago",
    "qs:photos":12,
    "qs:photos_1k":2,
    "qs:photos_9k":1,
    "qs:photos_9r":2,
    "qs:photos_all":37,
    "qs:photos_sr":1,
    "qs:placetype":"LocalAdmin",
    "qs:pop_sr":"0",
    "qs:woe_adm0":23424791,
    "wof:name":"Pacayas",
    "wof:placetype":"localadmin"
},
  "geometry": {"coordinates":[-83.813323,9.957015],"type":"Point"}
}