{
  "type": "Feature",
  "properties": {
    "gn:admin1_code":"01",
    "gn:admin2_code":"202",
    "gn:admin3_code":"20209.0",
    "gn:asciiname":"Catarata",
    "gn:country_code":"CR",
    "gn:dem":965,
    "gn:feature_class":"P",
    "gn:feature_code":"PPL",
    "gn:name":"Catarata",
    "gn:population":0,
    "gn:timezone":"America/Costa_Rica",
    "iso:country":"CR",
    "wof:name":"Catarata",
    "wof:placetype":"locality"
},
  "geometry": {"coordinates":[-84.50541,10.08935],"type":"Point"}
}