{
  "type": "Feature",
  "properties": {
    "gn:admin1_code":"06",
    "gn:admin2_code":"701",
    "gn:admin3_code":"70104.0",
    "gn:asciiname":"Quitaria",
    "gn:country_code":"CR",
    "gn:dem":42,
    "gn:feature_class":"P",
    "gn:feature_code":"PPL",
    "gn:name":"Quitar\u00eda",
    "gn:population":0,
    "gn:timezone":"America/Costa_Rica",
    "iso:country":"CR",
    "wof:name":"Quitaria",
    "wof:placetype":"locality"
},
  "geometry": {"coordinates":[-83.09029,9.90708],"type":"Point"}
}