{
  "type": "Feature",
  "properties": {
    "gn:admin1_code":"03",
    "gn:admin2_code":"509",
    "gn:admin3_code":"50902.0",
    "gn:asciiname":"Tacanis",
    "gn:country_code":"CR",
    "gn:dem":204,
    "gn:feature_class":"P",
    "gn:feature_code":"PPL",
    "gn:name":"Tacanis",
    "gn:population":0,
    "gn:timezone":"America/Costa_Rica",
    "iso:country":"CR",
    "wof:name":"Tacanis",
    "wof:placetype":"locality"
},
  "geometry": {"coordinates":[-85.32163,10.0342],"type":"Point"}
}