{
  "type": "Feature",
  "properties": {
    "gn:admin1_code":"03",
    "gn:admin2_code":"502",
    "gn:admin3_code":"50203.0",
    "gn:asciiname":"San Lazaro",
    "gn:country_code":"CR",
    "gn:dem":29,
    "gn:feature_class":"P",
    "gn:feature_code":"PPL",
    "gn:name":"San L\u00e1zaro",
    "gn:population":0,
    "gn:timezone":"America/Costa_Rica",
    "iso:country":"CR",
    "name:ceb_x_preferred":[
        "San L\u00e1zaro"
    ],
    "name:deu_x_preferred":[
        "San L\u00e1zaro"
    ],
    "name:glg_x_preferred":[
        "San L\u00e1zaro"
    ],
    "name:nds_x_preferred":[
        "San L\u00e1zaro"
    ],
    "name:spa_x_preferred":[
        "San L\u00e1zaro"
    ],
    "name:srp_x_preferred":[
        "\u0421\u0430\u043d \u041b\u0430\u0437\u0430\u0440\u043e"
    ],
    "name:swe_x_preferred":[
        "San L\u00e1zaro"
    ],
    "wof:name":"San Lazaro",
    "wof:placetype":"locality"
},
  "geometry": {"coordinates":[-85.46245,10.2715],"type":"Point"}
}