{
  "type": "Feature",
  "properties": {
    "gn:admin1_code":"03",
    "gn:admin2_code":"511",
    "gn:admin3_code":"51101.0",
    "gn:asciiname":"Rio Brujo",
    "gn:country_code":"CR",
    "gn:dem":471,
    "gn:feature_class":"P",
    "gn:feature_code":"PPL",
    "gn:name":"R\u00edo Brujo",
    "gn:population":0,
    "gn:timezone":"America/Costa_Rica",
    "iso:country":"CR",
    "wof:name":"Rio Brujo",
    "wof:placetype":"locality"
},
  "geometry": {"coordinates":[-85.43333,10.01667],"type":"Point"}
}