{
  "type": "Feature",
  "properties": {
    "gn:admin1_code":"07",
    "gn:admin2_code":"601",
    "gn:admin3_code":"60104.0",
    "gn:asciiname":"Gloria",
    "gn:country_code":"CR",
    "gn:dem":491,
    "gn:feature_class":"P",
    "gn:feature_code":"PPL",
    "gn:name":"Gloria",
    "gn:population":0,
    "gn:timezone":"America/Costa_Rica",
    "iso:country":"CR",
    "wof:name":"Gloria",
    "wof:placetype":"locality"
},
  "geometry": {"coordinates":[-85.06149000000001,9.94019],"type":"Point"}
}