{
  "type": "Feature",
  "properties": {
    "iso:country":"CR",
    "name:ceb_x_preferred":[
        "Jaco"
    ],
    "name:deu_x_preferred":[
        "Jaco"
    ],
    "name:fra_x_preferred":[
        "Jaco"
    ],
    "name:ita_x_preferred":[
        "Jaco"
    ],
    "name:nld_x_preferred":[
        "Jaco"
    ],
    "name:nor_x_preferred":[
        "Jaco"
    ],
    "name:rus_x_preferred":[
        "\u0416\u0430\u043a\u043e"
    ],
    "name:swe_x_preferred":[
        "Jaco"
    ],
    "qs:gn_pop":0,
    "qs:name":"Jaco",
    "qs:name_adm0":"Costa Rica",
    "qs:name_adm1":"Puntarenas",
    "qs:photos":25,
    "qs:photos_1k":5,
    "qs:photos_9k":18,
    "qs:photos_9r":12,
    "qs:photos_all":4063,
    "qs:photos_sr":1,
    "qs:placetype":"LocalAdmin",
    "qs:pop_sr":"0",
    "qs:woe_adm0":23424791,
    "wof:name":"Jaco",
    "wof:placetype":"localadmin"
},
  "geometry": {"coordinates":[-84.632835,9.617252],"type":"Point"}
}