{
  "type": "Feature",
  "properties": {
    "gn:admin1_code":"03",
    "gn:admin2_code":"506",
    "gn:admin3_code":"50605.0",
    "gn:asciiname":"Quesera",
    "gn:country_code":"CR",
    "gn:dem":8,
    "gn:feature_class":"P",
    "gn:feature_code":"PPL",
    "gn:name":"Quesera",
    "gn:population":0,
    "gn:timezone":"America/Costa_Rica",
    "iso:country":"CR",
    "wof:name":"Quesera",
    "wof:placetype":"locality"
},
  "geometry": {"coordinates":[-85.18257,10.32211],"type":"Point"}
}