{
  "type": "Feature",
  "properties": {
    "gn:admin1_code":"03",
    "gn:admin2_code":"501",
    "gn:admin3_code":"50104.0",
    "gn:asciiname":"Trinidad",
    "gn:country_code":"CR",
    "gn:dem":187,
    "gn:feature_class":"P",
    "gn:feature_code":"PPL",
    "gn:name":"Trinidad",
    "gn:population":0,
    "gn:timezone":"America/Costa_Rica",
    "iso:country":"CR",
    "name:und_x_variant":[
        "La Trinidad",
        "Trinidad"
    ],
    "wof:name":"Trinidad",
    "wof:placetype":"locality"
},
  "geometry": {"coordinates":[-85.62513,10.7294],"type":"Point"}
}