{
  "type": "Feature",
  "properties": {
    "gn:admin1_code":"03",
    "gn:admin2_code":"510",
    "gn:admin3_code":"51001.0",
    "gn:asciiname":"San Dimas",
    "gn:country_code":"CR",
    "gn:dem":67,
    "gn:feature_class":"P",
    "gn:feature_code":"PPL",
    "gn:name":"San Dimas",
    "gn:population":0,
    "gn:timezone":"America/Costa_Rica",
    "iso:country":"CR",
    "name:ceb_x_preferred":[
        "San Dimas"
    ],
    "name:deu_x_preferred":[
        "San Dimas"
    ],
    "name:hun_x_preferred":[
        "San Dimas"
    ],
    "name:ita_x_preferred":[
        "San Dimas"
    ],
    "name:pol_x_preferred":[
        "San Dimas"
    ],
    "name:por_x_preferred":[
        "San Dimas"
    ],
    "name:sco_x_preferred":[
        "San Dimas"
    ],
    "name:srp_x_preferred":[
        "\u0421\u0430\u043d \u0414\u0438\u043c\u0430\u0441"
    ],
    "name:swe_x_preferred":[
        "San Dimas"
    ],
    "wof:name":"San Dimas",
    "wof:placetype":"locality"
},
  "geometry": {"coordinates":[-85.60436,11.17763],"type":"Point"}
}