{
  "type": "Feature",
  "properties": {
    "gn:admin1_code":"03",
    "gn:admin2_code":"506",
    "gn:admin3_code":"50605.0",
    "gn:asciiname":"Taboga",
    "gn:country_code":"CR",
    "gn:dem":10,
    "gn:feature_class":"P",
    "gn:feature_code":"PPL",
    "gn:name":"Taboga",
    "gn:population":0,
    "gn:timezone":"America/Costa_Rica",
    "iso:country":"CR",
    "name:fra_x_preferred":[
        "Taboga"
    ],
    "name:spa_x_preferred":[
        "Taboga"
    ],
    "name:und_x_variant":[
        "Hacienda Taboga",
        "Taboga"
    ],
    "wof:name":"Taboga",
    "wof:placetype":"locality"
},
  "geometry": {"coordinates":[-85.20149000000001,10.33333],"type":"Point"}
}