{
  "type": "Feature",
  "properties": {
    "gn:admin1_code":"01",
    "gn:admin2_code":"203",
    "gn:admin3_code":"20303.0",
    "gn:asciiname":"Santa Gertrudis Norte",
    "gn:country_code":"CR",
    "gn:dem":1068,
    "gn:feature_class":"P",
    "gn:feature_code":"PPL",
    "gn:name":"Santa Gertrudis Norte",
    "gn:population":0,
    "gn:timezone":"America/Costa_Rica",
    "iso:country":"CR",
    "wof:name":"Santa Gertrudis Norte",
    "wof:placetype":"locality"
},
  "geometry": {"coordinates":[-84.28509,10.08891],"type":"Point"}
}