{
  "type": "Feature",
  "properties": {
    "gn:admin1_code":"03",
    "gn:admin2_code":"507",
    "gn:admin3_code":"50701.0",
    "gn:asciiname":"Palma",
    "gn:country_code":"CR",
    "gn:dem":51,
    "gn:feature_class":"P",
    "gn:feature_code":"PPL",
    "gn:name":"Palma",
    "gn:population":0,
    "gn:timezone":"America/Costa_Rica",
    "iso:country":"CR",
    "name:und_x_variant":[
        "La Palma",
        "Palma"
    ],
    "wof:name":"Palma",
    "wof:placetype":"locality"
},
  "geometry": {"coordinates":[-85.05082,10.25528],"type":"Point"}
}