{
  "type": "Feature",
  "properties": {
    "iso:country":"CR",
    "name:arg_x_preferred":[
        "Queixumes dos Pinos"
    ],
    "name:cat_x_preferred":[
        "Os Pinos"
    ],
    "name:ces_x_preferred":[
        "Galicijsk\u00e1 hymna"
    ],
    "name:eus_x_preferred":[
        "Os Pinos"
    ],
    "name:fra_x_preferred":[
        "Hymne galicien"
    ],
    "name:glg_x_preferred":[
        "Os Pinos"
    ],
    "name:kor_x_preferred":[
        "\uac08\ub9ac\uc2dc\uc544\uc758 \uad6d\uac00"
    ],
    "name:nor_x_preferred":[
        "Dos Pinos"
    ],
    "name:pol_x_preferred":[
        "Hymn Galicji"
    ],
    "name:por_x_preferred":[
        "Os Pinos"
    ],
    "name:spa_x_preferred":[
        "Os Pinos"
    ],
    "name:yor_x_preferred":[
        "Os Pinos"
    ],
    "name:zho_yue_x_preferred":[
        "\u677e\u6a39\u4e4b\u6b4c"
    ],
    "qs:gn_pop":0,
    "qs:name":"Dos Pinos",
    "qs:name_adm0":"Costa Rica",
    "qs:name_adm1":"San Jose",
    "qs:photos":16,
    "qs:photos_1k":3,
    "qs:photos_9k":1,
    "qs:photos_9r":1,
    "qs:photos_all":16,
    "qs:photos_sr":1,
    "qs:placetype":"Suburb",
    "qs:pop_sr":"0",
    "qs:woe_adm0":23424791,
    "wof:name":"Dos Pinos",
    "wof:placetype":"neighbourhood"
},
  "geometry": {"coordinates":[-84.06698,9.9285],"type":"Point"}
}