{
  "type": "Feature",
  "properties": {
    "gn:admin1_code":"02",
    "gn:admin2_code":"302",
    "gn:admin3_code":"30204.0",
    "gn:asciiname":"Urasca",
    "gn:country_code":"CR",
    "gn:dem":1095,
    "gn:feature_class":"P",
    "gn:feature_code":"PPL",
    "gn:name":"Urasca",
    "gn:population":0,
    "gn:timezone":"America/Costa_Rica",
    "iso:country":"CR",
    "name:und_x_variant":[
        "Utasca",
        "Urasca"
    ],
    "wof:name":"Urasca",
    "wof:placetype":"locality"
},
  "geometry": {"coordinates":[-83.78843000000001,9.83974],"type":"Point"}
}