{
  "type": "Feature",
  "properties": {
    "iso:country":"CR",
    "qs:gn_pop":0,
    "qs:name":"Bratsi",
    "qs:name_adm0":"Costa Rica",
    "qs:name_adm1":"Limon",
    "qs:photos":2,
    "qs:photos_1k":1,
    "qs:photos_9k":2,
    "qs:photos_9r":5,
    "qs:photos_all":376,
    "qs:photos_sr":1,
    "qs:placetype":"LocalAdmin",
    "qs:pop_sr":"0",
    "qs:woe_adm0":23424791,
    "wof:name":"Bratsi",
    "wof:placetype":"localadmin"
},
  "geometry": {"coordinates":[-82.87631,9.518227],"type":"Point"}
}