{
  "type": "Feature",
  "properties": {
    "gn:admin1_code":"04",
    "gn:admin2_code":"408",
    "gn:admin3_code":"40802.0",
    "gn:asciiname":"Barrantes",
    "gn:country_code":"CR",
    "gn:dem":1082,
    "gn:feature_class":"P",
    "gn:feature_code":"PPL",
    "gn:name":"Barrantes",
    "gn:population":0,
    "gn:timezone":"America/Costa_Rica",
    "iso:country":"CR",
    "wof:name":"Barrantes",
    "wof:placetype":"locality"
},
  "geometry": {"coordinates":[-84.14693,10.01378],"type":"Point"}
}