{
  "type": "Feature",
  "properties": {
    "gn:admin1_code":"08",
    "gn:admin2_code":"112",
    "gn:admin3_code":"11204.0",
    "gn:asciiname":"Ceiba Este",
    "gn:country_code":"CR",
    "gn:dem":1047,
    "gn:feature_class":"P",
    "gn:feature_code":"PPL",
    "gn:name":"Ceiba Este",
    "gn:population":0,
    "gn:timezone":"America/Costa_Rica",
    "iso:country":"CR",
    "wof:name":"Ceiba Este",
    "wof:placetype":"locality"
},
  "geometry": {"coordinates":[-84.17016,9.75582],"type":"Point"}
}