{
  "type": "Feature",
  "properties": {
    "gn:admin1_code":"03",
    "gn:admin2_code":"501",
    "gn:admin3_code":"50103.0",
    "gn:asciiname":"Argentina",
    "gn:country_code":"CR",
    "gn:dem":335,
    "gn:feature_class":"P",
    "gn:feature_code":"PPL",
    "gn:name":"Argentina",
    "gn:population":0,
    "gn:timezone":"America/Costa_Rica",
    "iso:country":"CR",
    "wof:name":"Argentina",
    "wof:placetype":"locality"
},
  "geometry": {"coordinates":[-85.47839,10.82871],"type":"Point"}
}