{
  "type": "Feature",
  "properties": {
    "iso:country":"CR",
    "name:ceb_x_preferred":[
        "Puerto Viejo"
    ],
    "name:eng_x_preferred":[
        "Puerto Viejo de Sarapiqu\u00ed"
    ],
    "name:fra_x_preferred":[
        "Puerto Viejo de Sarapiqu\u00ed"
    ],
    "name:ita_x_preferred":[
        "Puerto Viejo"
    ],
    "name:lit_x_preferred":[
        "Sarapiki Puerto Vjechas"
    ],
    "name:nld_x_preferred":[
        "Sarapiqu\u00ed"
    ],
    "name:nob_x_preferred":[
        "Puerto Viejo"
    ],
    "name:nor_x_preferred":[
        "Puerto Viejo"
    ],
    "name:spa_x_preferred":[
        "Puerto Viejo"
    ],
    "name:swe_x_preferred":[
        "Puerto Viejo"
    ],
    "qs:gn_country":"CR",
    "qs:gn_fcode":"PPL",
    "qs:gn_pop":0,
    "qs:name":"Puerto Viejo",
    "qs:name_adm0":"Costa Rica",
    "qs:name_adm1":"Heredia",
    "qs:photos":1515,
    "qs:photos_1k":307,
    "qs:photos_9k":7,
    "qs:photos_9r":8,
    "qs:photos_all":1515,
    "qs:photos_sr":13,
    "qs:placetype":"Town",
    "qs:pop_sr":"0",
    "qs:woe_adm0":23424791,
    "wd:wordcount":25,
    "wof:name":"Puerto Viejo",
    "wof:placetype":"locality"
},
  "geometry": {"coordinates":[-84.00557999999999,10.46142],"type":"Point"}
}