{
  "type": "Feature",
  "properties": {
    "gn:admin1_code":"03",
    "gn:admin2_code":"502",
    "gn:admin3_code":"50202.0",
    "gn:asciiname":"Monte Galan",
    "gn:country_code":"CR",
    "gn:dem":361,
    "gn:feature_class":"P",
    "gn:feature_code":"PPL",
    "gn:name":"Monte Gal\u00e1n",
    "gn:population":0,
    "gn:timezone":"America/Costa_Rica",
    "iso:country":"CR",
    "wof:name":"Monte Galan",
    "wof:placetype":"locality"
},
  "geometry": {"coordinates":[-85.38333,10.13333],"type":"Point"}
}