{
  "type": "Feature",
  "properties": {
    "gn:admin1_code":"08",
    "gn:admin2_code":"106",
    "gn:admin3_code":"10602.0",
    "gn:asciiname":"Tarbaca",
    "gn:country_code":"CR",
    "gn:dem":1777,
    "gn:feature_class":"P",
    "gn:feature_code":"PPL",
    "gn:name":"Tarbaca",
    "gn:population":0,
    "gn:timezone":"America/Costa_Rica",
    "iso:country":"CR",
    "name:und_x_variant":[
        "Praga",
        "Tarbaca"
    ],
    "wof:name":"Tarbaca",
    "wof:placetype":"locality"
},
  "geometry": {"coordinates":[-84.11284999999999,9.81688],"type":"Point"}
}