{
  "type": "Feature",
  "properties": {
    "gn:admin1_code":"08",
    "gn:admin2_code":"112",
    "gn:admin3_code":"11201.0",
    "gn:asciiname":"Purrujal",
    "gn:country_code":"CR",
    "gn:dem":1137,
    "gn:feature_class":"P",
    "gn:feature_code":"PPL",
    "gn:name":"Purrujal",
    "gn:population":0,
    "gn:timezone":"America/Costa_Rica",
    "iso:country":"CR",
    "wof:name":"Purrujal",
    "wof:placetype":"locality"
},
  "geometry": {"coordinates":[-84.17184,9.7979],"type":"Point"}
}