{
  "type": "Feature",
  "properties": {
    "iso:country":"CR",
    "name:ben_x_preferred":[
        "\u09b8\u09be\u09a8 \u09ae\u09be\u09b0\u09cd\u0995\u09cb\u09b8"
    ],
    "name:ceb_x_preferred":[
        "San Marcos"
    ],
    "name:ell_x_preferred":[
        "\u03a3\u03b1\u03bd \u039c\u03ac\u03c1\u03ba\u03bf\u03c2"
    ],
    "name:eng_x_preferred":[
        "San Marcos"
    ],
    "name:fas_x_preferred":[
        "\u0633\u0627\u0646 \u0645\u0627\u0631\u06a9\u0648\u0633"
    ],
    "name:fra_x_preferred":[
        "San Marcos"
    ],
    "name:heb_x_preferred":[
        "\u05e1\u05df \u05de\u05e8\u05e7\u05d5\u05e1"
    ],
    "name:hin_x_preferred":[
        "\u0938\u0948\u0928 \u092e\u093e\u0930\u094d\u0915\u0949\u0938"
    ],
    "name:hun_x_preferred":[
        "San Marcos"
    ],
    "name:ind_x_preferred":[
        "San Marcos"
    ],
    "name:ita_x_preferred":[
        "San Marcos"
    ],
    "name:kor_x_preferred":[
        "\uc0b0 \ub9c8\ub974\ucf54\uc2a4"
    ],
    "name:lit_x_preferred":[
        "Tarasu San Markosas"
    ],
    "name:nld_x_preferred":[
        "San Marcos"
    ],
    "name:nob_x_preferred":[
        "San Marcos"
    ],
    "name:nor_x_preferred":[
        "San Marcos"
    ],
    "name:spa_x_preferred":[
        "San Marcos de Tarraz\u00fa"
    ],
    "name:swe_x_preferred":[
        "San Marcos"
    ],
    "name:tur_x_preferred":[
        "San Marcos"
    ],
    "name:und_x_variant":[
        "Marcos"
    ],
    "name:vie_x_preferred":[
        "San Marcos"
    ],
    "name:zho_x_preferred":[
        "\u8056\u99ac\u79d1\u65af\u5fb7\u5854\u62c9\u8607\u5340"
    ],
    "qs:gn_country":"CR",
    "qs:gn_fcode":"PPL",
    "qs:gn_pop":4255,
    "qs:name":"San Marcos",
    "qs:name_adm0":"Costa Rica",
    "qs:name_adm1":"San Jose",
    "qs:photos":68,
    "qs:photos_1k":14,
    "qs:photos_9k":1,
    "qs:photos_9r":2,
    "qs:photos_all":68,
    "qs:photos_sr":2,
    "qs:placetype":"Town",
    "qs:pop_sr":"4",
    "qs:woe_adm0":23424791,
    "wd:wordcount":831,
    "wof:name":"San Marcos",
    "wof:placetype":"locality",
    "wof:population":4255
},
  "geometry": {"coordinates":[-84.02025999999999,9.6601],"type":"Point"}
}