{
  "type": "Feature",
  "properties": {
    "iso:country":"CR",
    "name:bre_x_preferred":[
        "San Marcos"
    ],
    "name:bul_x_preferred":[
        "\u0421\u0430\u043d \u041c\u0430\u0440\u043a\u043e\u0441"
    ],
    "name:cat_x_preferred":[
        "San Marcos"
    ],
    "name:ceb_x_preferred":[
        "San Marcos"
    ],
    "name:deu_x_preferred":[
        "San Marcos"
    ],
    "name:ell_x_preferred":[
        "\u03a3\u03b1\u03bd \u039c\u03ac\u03c1\u03ba\u03bf\u03c2"
    ],
    "name:eng_x_preferred":[
        "San Marcos"
    ],
    "name:est_x_preferred":[
        "San Marcos"
    ],
    "name:fin_x_preferred":[
        "San Marcos"
    ],
    "name:fra_x_preferred":[
        "San Marcos"
    ],
    "name:glg_x_preferred":[
        "San Marcos"
    ],
    "name:ita_x_preferred":[
        "San Marcos"
    ],
    "name:kor_x_preferred":[
        "\uc0b0\ub9c8\ub974\ucf54\uc2a4"
    ],
    "name:lit_x_preferred":[
        "Tarasu San Markosas"
    ],
    "name:lit_x_variant":[
        "San Markosas"
    ],
    "name:nds_x_preferred":[
        "San Marcos"
    ],
    "name:nld_x_preferred":[
        "San Marcos"
    ],
    "name:nob_x_preferred":[
        "San Marcos"
    ],
    "name:nor_x_preferred":[
        "San Marcos"
    ],
    "name:pol_x_preferred":[
        "San Marcos"
    ],
    "name:por_x_preferred":[
        "San Marcos"
    ],
    "name:rus_x_preferred":[
        "\u0421\u0430\u043d-\u041c\u0430\u0440\u043a\u043e\u0441"
    ],
    "name:sco_x_preferred":[
        "San Marcos"
    ],
    "name:spa_x_preferred":[
        "San Marcos de Tarraz\u00fa"
    ],
    "name:spa_x_variant":[
        "San Marcos"
    ],
    "name:srp_x_preferred":[
        "\u0421\u0430\u043d \u041c\u0430\u0440\u043a\u043e\u0441"
    ],
    "name:swa_x_preferred":[
        "San Marcos"
    ],
    "name:swe_x_preferred":[
        "San Marcos"
    ],
    "name:unk_x_variant":[
        "Marcos"
    ],
    "name:vol_x_preferred":[
        "San Marcos"
    ],
    "name:war_x_preferred":[
        "San Marcos"
    ],
    "name:zho_x_preferred":[
        "\u8056\u99ac\u79d1\u65af\u5fb7\u5854\u62c9\u8607\u5340"
    ],
    "qs:gn_country":"CR",
    "qs:gn_fcode":"PPL",
    "qs:gn_pop":4255,
    "qs:name":"San Marcos",
    "qs:name_adm0":"Costa Rica",
    "qs:name_adm1":"San Jose",
    "qs:photos":68,
    "qs:photos_1k":14,
    "qs:photos_9k":1,
    "qs:photos_9r":2,
    "qs:photos_all":68,
    "qs:photos_sr":2,
    "qs:placetype":"Town",
    "qs:pop_sr":"4",
    "qs:woe_adm0":23424791,
    "wd:wordcount":831,
    "wof:name":"San Marcos",
    "wof:placetype":"locality",
    "wof:population":4255
},
  "geometry": {"coordinates":[-84.02025999999999,9.6601],"type":"Point"}
}