{
  "type": "Feature",
  "properties": {
    "iso:country":"CR",
    "name:eng_x_preferred":[
        "Tigra"
    ],
    "name:fra_x_preferred":[
        "Tigra"
    ],
    "name:ita_x_preferred":[
        "Tigra"
    ],
    "name:jpn_x_preferred":[
        "\u30c6\u30a3\u30b0\u30e9"
    ],
    "name:kor_x_preferred":[
        "\ud0c0\uc774\uadf8\ub77c"
    ],
    "name:nld_x_preferred":[
        "Tigra"
    ],
    "name:por_x_preferred":[
        "Tigresa"
    ],
    "name:rus_x_preferred":[
        "\u0422\u0438\u0433\u0440\u0430"
    ],
    "name:spa_x_preferred":[
        "Tigra"
    ],
    "name:tat_x_preferred":[
        "\u042e\u043b\u0431\u0430\u0440\u044b\u0441"
    ],
    "name:zho_x_preferred":[
        "\u864e\u5973\u90ce"
    ],
    "qs:gn_country":"CR",
    "qs:gn_fcode":"PPL",
    "qs:gn_pop":194,
    "qs:name":"Tigra",
    "qs:name_adm0":"Costa Rica",
    "qs:name_adm1":"Alajuela",
    "qs:photos":0,
    "qs:photos_1k":0,
    "qs:photos_9k":1,
    "qs:photos_9r":1,
    "qs:photos_all":1,
    "qs:photos_sr":0,
    "qs:placetype":"Town",
    "qs:pop_sr":"1",
    "qs:woe_adm0":23424791,
    "wd:wordcount":6645,
    "wof:name":"Tigra",
    "wof:placetype":"locality",
    "wof:population":194
},
  "geometry": {"coordinates":[-84.58083999999999,10.3406],"type":"Point"}
}