{
  "type": "Feature",
  "properties": {
    "gn:admin1_code":"08",
    "gn:admin2_code":"116",
    "gn:admin3_code":"11602.0",
    "gn:asciiname":"Florecilla",
    "gn:country_code":"CR",
    "gn:dem":459,
    "gn:feature_class":"P",
    "gn:feature_code":"PPL",
    "gn:name":"Florecilla",
    "gn:population":0,
    "gn:timezone":"America/Costa_Rica",
    "iso:country":"CR",
    "wof:name":"Florecilla",
    "wof:placetype":"locality"
},
  "geometry": {"coordinates":[-84.42815,9.85005],"type":"Point"}
}