{
  "type": "Feature",
  "properties": {
    "iso:country":"CR",
    "qs:gn_country":"CR",
    "qs:gn_fcode":"PPL",
    "qs:gn_pop":0,
    "qs:name":"Honduras",
    "qs:name_adm0":"Costa Rica",
    "qs:name_adm1":"San Jose",
    "qs:photos":183,
    "qs:photos_1k":37,
    "qs:photos_9k":1,
    "qs:photos_9r":4,
    "qs:photos_all":183,
    "qs:photos_sr":4,
    "qs:placetype":"Town",
    "qs:pop_sr":"0",
    "qs:woe_adm0":23424791,
    "wof:name":"Honduras",
    "wof:placetype":"locality"
},
  "geometry": {"coordinates":[-84.1788,9.96304],"type":"Point"}
}