{
  "type": "Feature",
  "properties": {
    "iso:country":"CR",
    "name:bre_x_preferred":[
        "Manzanillo"
    ],
    "name:ceb_x_preferred":[
        "Manzanillo"
    ],
    "name:deu_x_preferred":[
        "Manzanillo"
    ],
    "name:epo_x_preferred":[
        "Manzanillo"
    ],
    "name:fra_x_preferred":[
        "Manzanillo"
    ],
    "name:glg_x_preferred":[
        "Manzanillo"
    ],
    "name:heb_x_preferred":[
        "\u05de\u05e0\u05e1\u05e0\u05d9\u05d5"
    ],
    "name:ita_x_preferred":[
        "Manzanillo"
    ],
    "name:kor_x_preferred":[
        "\ub9cc\uc0ac\ub2c8\uc694"
    ],
    "name:lit_x_preferred":[
        "Mansaniljas"
    ],
    "name:nld_x_preferred":[
        "Manzanillo"
    ],
    "name:oci_x_preferred":[
        "Manzanillo"
    ],
    "name:pol_x_preferred":[
        "Manzanillo"
    ],
    "name:rus_x_preferred":[
        "\u041c\u0430\u043d\u0441\u0430\u043d\u0438\u043b\u044c\u043e"
    ],
    "name:spa_x_preferred":[
        "Manzanillo"
    ],
    "name:swe_x_preferred":[
        "Manzanillo"
    ],
    "name:ukr_x_preferred":[
        "\u041c\u0430\u043d\u0441\u0430\u043d\u0456\u043b\u044c\u0439\u043e"
    ],
    "name:unk_x_variant":[
        "Puerto Iglesias"
    ],
    "qs:gn_country":"CR",
    "qs:gn_fcode":"PPL",
    "qs:gn_pop":0,
    "qs:name":"Manzanillo",
    "qs:name_adm0":"Costa Rica",
    "qs:name_adm1":"Puntarenas",
    "qs:photos":22,
    "qs:photos_1k":4,
    "qs:photos_9k":1,
    "qs:photos_9r":1,
    "qs:photos_all":22,
    "qs:photos_sr":1,
    "qs:placetype":"Town",
    "qs:pop_sr":"3",
    "qs:woe_adm0":23424791,
    "wof:name":"Manzanillo",
    "wof:placetype":"locality"
},
  "geometry": {"coordinates":[-85.01776,10.1321],"type":"Point"}
}