{
  "type": "Feature",
  "properties": {
    "gn:admin1_code":"08",
    "gn:admin2_code":"119",
    "gn:admin3_code":"11901.0",
    "gn:asciiname":"Pedregoso",
    "gn:country_code":"CR",
    "gn:dem":726,
    "gn:feature_class":"P",
    "gn:feature_code":"PPL",
    "gn:name":"Pedregoso",
    "gn:population":0,
    "gn:timezone":"America/Costa_Rica",
    "iso:country":"CR",
    "wof:name":"Pedregoso",
    "wof:placetype":"locality"
},
  "geometry": {"coordinates":[-83.7206,9.37417],"type":"Point"}
}