{
  "type": "Feature",
  "properties": {
    "gn:admin1_code":"06",
    "gn:admin2_code":"706",
    "gn:admin3_code":"70601.0",
    "gn:asciiname":"Angelina",
    "gn:country_code":"CR",
    "gn:dem":217,
    "gn:feature_class":"P",
    "gn:feature_code":"PPL",
    "gn:name":"Angelina",
    "gn:population":0,
    "gn:timezone":"America/Costa_Rica",
    "iso:country":"CR",
    "wof:name":"Angelina",
    "wof:placetype":"locality"
},
  "geometry": {"coordinates":[-83.73770999999998,10.21078],"type":"Point"}
}