{
  "type": "Feature",
  "properties": {
    "gn:admin1_code":"01",
    "gn:admin2_code":"214",
    "gn:admin3_code":"21401.0",
    "gn:asciiname":"Cachito",
    "gn:country_code":"CR",
    "gn:dem":44,
    "gn:feature_class":"P",
    "gn:feature_code":"PPL",
    "gn:name":"Cachito",
    "gn:population":0,
    "gn:timezone":"America/Costa_Rica",
    "iso:country":"CR",
    "wof:name":"Cachito",
    "wof:placetype":"locality"
},
  "geometry": {"coordinates":[-84.64482,11.04209],"type":"Point"}
}