{
  "type": "Feature",
  "properties": {
    "iso:country":"CR",
    "name:ceb_x_preferred":[
        "Palmar Sur Airport"
    ],
    "name:eng_x_preferred":[
        "Palmar Sur Airport"
    ],
    "name:eng_x_variant":[
        "PMZ",
        "KPMZ"
    ],
    "name:fas_x_preferred":[
        "\u0641\u0631\u0648\u062f\u06af\u0627\u0647 \u067e\u0627\u0644\u0645\u0627\u0631 \u0633\u0648\u0631"
    ],
    "name:fre_x_preferred":[
        "a\u00e9rodrome de Palmar Sur"
    ],
    "name:jpn_x_preferred":[
        "\u30d1\u30eb\u30de\u30fb\u30b9\u30fc\u30eb\u7a7a\u6e2f"
    ],
    "name:may_x_preferred":[
        "Lapangan Terbang Palmar Sur"
    ],
    "name:msa_x_preferred":[
        "Lapangan Terbang Palmar Sur"
    ],
    "name:per_x_preferred":[
        "\u0641\u0631\u0648\u062f\u06af\u0627\u0647 \u067e\u0627\u0644\u0645\u0627\u0631 \u0633\u0648\u0631"
    ],
    "name:pol_x_preferred":[
        "Port lotniczy Palmar Sur"
    ],
    "name:spa_x_preferred":[
        "Aeropuerto de Palmar Sur"
    ],
    "name:swe_x_preferred":[
        "Aeropuerto de Palmar Sur"
    ],
    "name:tgk_x_preferred":[
        "\u0424\u0443\u0440\u0443\u0434\u0433\u043e\u04b3\u0438 \u043f\u043e\u043b\u043c\u043e\u0440 \u0441\u0443\u0440"
    ],
    "oa:elevation_ft":"49",
    "oa:type":"medium_airport",
    "wd:wordcount":228,
    "woe:hierarchy":{
        "country_id":23424791,
        "county_id":26808833,
        "localadmin_id":26809080,
        "planet_id":1,
        "state_id":2345087
    },
    "wof:name":"Palmar Sur Airport",
    "wof:placetype":"campus"
},
  "geometry": {"coordinates":[-83.468597,8.95103],"type":"Point"}
}