{
  "type": "Feature",
  "properties": {
    "gn:admin1_code":"02",
    "gn:admin2_code":"305",
    "gn:admin3_code":"30512.0",
    "gn:asciiname":"Moravia",
    "gn:country_code":"CR",
    "gn:dem":1127,
    "gn:feature_class":"P",
    "gn:feature_code":"PPL",
    "gn:name":"Moravia",
    "gn:population":0,
    "gn:timezone":"America/Costa_Rica",
    "iso:country":"CR",
    "wof:name":"Moravia",
    "wof:placetype":"locality"
},
  "geometry": {"coordinates":[-83.44059,9.82641],"type":"Point"}
}