{
  "type": "Feature",
  "properties": {
    "gn:admin1_code":"07",
    "gn:admin2_code":"604",
    "gn:admin3_code":"60401.0",
    "gn:asciiname":"Cebadilla",
    "gn:country_code":"CR",
    "gn:dem":360,
    "gn:feature_class":"P",
    "gn:feature_code":"PPL",
    "gn:name":"Cebadilla",
    "gn:population":0,
    "gn:timezone":"America/Costa_Rica",
    "iso:country":"CR",
    "wof:name":"Cebadilla",
    "wof:placetype":"locality"
},
  "geometry": {"coordinates":[-84.78333000000001,10.13333],"type":"Point"}
}