{
  "type": "Feature",
  "properties": {
    "iso:country":"CR",
    "name:eng_x_preferred":[
        "Bratsi"
    ],
    "name:ita_x_preferred":[
        "Bratsi"
    ],
    "name:nob_x_preferred":[
        "Bratsi"
    ],
    "name:spa_x_preferred":[
        "Bratsi"
    ],
    "name:und_x_variant":[
        "Bralsi"
    ],
    "qs:gn_country":"CR",
    "qs:gn_fcode":"PPL",
    "qs:gn_pop":0,
    "qs:name":"Bratsi",
    "qs:name_adm0":"Costa Rica",
    "qs:name_adm1":"Limon",
    "qs:photos":246,
    "qs:photos_1k":50,
    "qs:photos_9k":1,
    "qs:photos_9r":4,
    "qs:photos_all":246,
    "qs:photos_sr":4,
    "qs:placetype":"Town",
    "qs:pop_sr":"0",
    "qs:woe_adm0":23424791,
    "wof:name":"Bratsi",
    "wof:placetype":"locality"
},
  "geometry": {"coordinates":[-82.89257000000001,9.55392],"type":"Point"}
}