{
  "type": "Feature",
  "properties": {
    "gn:admin1_code":"03",
    "gn:admin2_code":"510",
    "gn:admin3_code":"51003.0",
    "gn:asciiname":"Santa Rogelia",
    "gn:country_code":"CR",
    "gn:dem":366,
    "gn:feature_class":"P",
    "gn:feature_code":"PPL",
    "gn:name":"Santa Rogelia",
    "gn:population":0,
    "gn:timezone":"America/Costa_Rica",
    "iso:country":"CR",
    "wof:name":"Santa Rogelia",
    "wof:placetype":"locality"
},
  "geometry": {"coordinates":[-85.55,11.13333],"type":"Point"}
}