{
  "type": "Feature",
  "properties": {
    "gn:admin1_code":"03",
    "gn:admin2_code":"501",
    "gn:admin3_code":"50102.0",
    "gn:asciiname":"Piedras Grandes",
    "gn:country_code":"CR",
    "gn:dem":95,
    "gn:feature_class":"P",
    "gn:feature_code":"PPL",
    "gn:name":"Piedras Grandes",
    "gn:population":0,
    "gn:timezone":"America/Costa_Rica",
    "iso:country":"CR",
    "wof:name":"Piedras Grandes",
    "wof:placetype":"locality"
},
  "geometry": {"coordinates":[-85.50112,10.70838],"type":"Point"}
}