{
  "type": "Feature",
  "properties": {
    "gn:admin1_code":"03",
    "gn:admin2_code":"511",
    "gn:admin3_code":"51102.0",
    "gn:asciiname":"Monte Romo",
    "gn:country_code":"CR",
    "gn:dem":699,
    "gn:feature_class":"P",
    "gn:feature_code":"PPL",
    "gn:name":"Monte Romo",
    "gn:population":0,
    "gn:timezone":"America/Costa_Rica",
    "iso:country":"CR",
    "name:und_x_variant":[
        "\u00c1ngeles de Monte Romo",
        "Monte Romo"
    ],
    "wof:name":"Monte Romo",
    "wof:placetype":"locality"
},
  "geometry": {"coordinates":[-85.38075000000001,9.99748],"type":"Point"}
}