{
  "type": "Feature",
  "properties": {
    "iso:country":"CR",
    "name:jpn_x_preferred":[
        "\u30ab\u30f3\u30dd\u30fb\u30a8\u30ea\u30a2\u30b9\u30fb\u30c7\u30eb\u30ac\u30fc\u30c9"
    ],
    "name:spa_x_preferred":[
        "Campo El\u00edas Delgado"
    ],
    "qs:gn_pop":0,
    "qs:name":"Rincon de Cubillos",
    "qs:name_adm0":"Costa Rica",
    "qs:name_adm1":"San Jose",
    "qs:photos":30,
    "qs:photos_1k":6,
    "qs:photos_9k":1,
    "qs:photos_9r":2,
    "qs:photos_all":30,
    "qs:photos_sr":2,
    "qs:placetype":"Suburb",
    "qs:pop_sr":"0",
    "qs:woe_adm0":23424791,
    "wof:name":"Rincon de Cubillos",
    "wof:placetype":"neighbourhood"
},
  "geometry": {"coordinates":[-84.099225,9.936091],"type":"Point"}
}