{
  "type": "Feature",
  "properties": {
    "gn:admin1_code":"08",
    "gn:admin2_code":"119",
    "gn:admin3_code":"11907.0",
    "gn:asciiname":"Aguila Abajo",
    "gn:country_code":"CR",
    "gn:dem":384,
    "gn:feature_class":"P",
    "gn:feature_code":"PPL",
    "gn:name":"\u00c1guila Abajo",
    "gn:population":0,
    "gn:timezone":"America/Costa_Rica",
    "iso:country":"CR",
    "wof:name":"Aguila Abajo",
    "wof:placetype":"locality"
},
  "geometry": {"coordinates":[-83.52609,9.12059],"type":"Point"}
}