{
  "type": "Feature",
  "properties": {
    "iso:country":"CR",
    "qs:gn_pop":0,
    "qs:name":"Florencia",
    "qs:name_adm0":"Costa Rica",
    "qs:name_adm1":"Alajuela",
    "qs:photos":17,
    "qs:photos_1k":3,
    "qs:photos_9k":1,
    "qs:photos_9r":4,
    "qs:photos_all":184,
    "qs:photos_sr":1,
    "qs:placetype":"LocalAdmin",
    "qs:pop_sr":"0",
    "qs:woe_adm0":23424791,
    "wof:name":"Florencia",
    "wof:placetype":"localadmin"
},
  "geometry": {"coordinates":[-84.46195,10.382466],"type":"Point"}
}