{
  "type": "Feature",
  "properties": {
    "iso:country":"CR",
    "name:ceb_x_preferred":[
        "Florencia"
    ],
    "name:dan_x_preferred":[
        "Florencia"
    ],
    "name:deu_x_preferred":[
        "Florencia"
    ],
    "name:fra_x_preferred":[
        "Florencia"
    ],
    "name:glg_x_preferred":[
        "Florencia"
    ],
    "name:hun_x_preferred":[
        "Florencia"
    ],
    "name:ita_x_preferred":[
        "Florencia"
    ],
    "name:kor_x_preferred":[
        "\ud50c\ub85c\ub80c\uc2dc\uc544"
    ],
    "name:nld_x_preferred":[
        "Florencia"
    ],
    "name:por_x_preferred":[
        "Florencia"
    ],
    "name:sco_x_preferred":[
        "Florencia"
    ],
    "name:spa_x_preferred":[
        "Florencia"
    ],
    "name:swe_x_preferred":[
        "Florencia"
    ],
    "name:tgl_x_preferred":[
        "Florencia"
    ],
    "name:ukr_x_preferred":[
        "\u0424\u043b\u043e\u0440\u0435\u043d\u0446\u0456\u044f"
    ],
    "name:vie_x_preferred":[
        "Florencia"
    ],
    "name:war_x_preferred":[
        "Florencia"
    ],
    "qs:gn_pop":0,
    "qs:name":"Florencia",
    "qs:name_adm0":"Costa Rica",
    "qs:name_adm1":"Alajuela",
    "qs:photos":17,
    "qs:photos_1k":3,
    "qs:photos_9k":1,
    "qs:photos_9r":4,
    "qs:photos_all":184,
    "qs:photos_sr":1,
    "qs:placetype":"LocalAdmin",
    "qs:pop_sr":"0",
    "qs:woe_adm0":23424791,
    "wof:name":"Florencia",
    "wof:placetype":"localadmin"
},
  "geometry": {"coordinates":[-84.46195,10.382466],"type":"Point"}
}