{
  "type": "Feature",
  "properties": {
    "gn:admin1_code":"03",
    "gn:admin2_code":"510",
    "gn:admin3_code":"51001.0",
    "gn:asciiname":"Copalchi",
    "gn:country_code":"CR",
    "gn:dem":70,
    "gn:feature_class":"P",
    "gn:feature_code":"PPL",
    "gn:name":"Copalch\u00ed",
    "gn:population":0,
    "gn:timezone":"America/Costa_Rica",
    "iso:country":"CR",
    "name:und_x_variant":[
        "Copach\u00ed",
        "Copalch\u00ed"
    ],
    "wof:name":"Copalchi",
    "wof:placetype":"locality"
},
  "geometry": {"coordinates":[-85.61563000000002,11.18264],"type":"Point"}
}