{
  "type": "Feature",
  "properties": {
    "gn:admin1_code":"08",
    "gn:admin2_code":"103",
    "gn:admin3_code":"10308.0",
    "gn:asciiname":"San Cristobal Norte",
    "gn:country_code":"CR",
    "gn:dem":1695,
    "gn:feature_class":"P",
    "gn:feature_code":"PPL",
    "gn:name":"San Crist\u00f3bal Norte",
    "gn:population":0,
    "gn:timezone":"America/Costa_Rica",
    "iso:country":"CR",
    "name:und_x_variant":[
        "Crist\u00f3bal Norte",
        "San Crist\u00f3bal Norte"
    ],
    "wof:name":"San Cristobal Norte",
    "wof:placetype":"locality"
},
  "geometry": {"coordinates":[-84.00633000000001,9.77076],"type":"Point"}
}