{
  "type": "Feature",
  "properties": {
    "gn:admin1_code":"02",
    "gn:admin2_code":"308",
    "gn:admin3_code":"30802.0",
    "gn:asciiname":"Higuito",
    "gn:country_code":"CR",
    "gn:dem":1458,
    "gn:feature_class":"P",
    "gn:feature_code":"PPL",
    "gn:name":"Higuito",
    "gn:population":0,
    "gn:timezone":"America/Costa_Rica",
    "iso:country":"CR",
    "wof:name":"Higuito",
    "wof:placetype":"locality"
},
  "geometry": {"coordinates":[-83.95936999999998,9.82087],"type":"Point"}
}