{
  "type": "Feature",
  "properties": {
    "gn:admin1_code":"03",
    "gn:admin2_code":"502",
    "gn:admin3_code":"50207.0",
    "gn:asciiname":"Chumburan",
    "gn:country_code":"CR",
    "gn:dem":232,
    "gn:feature_class":"P",
    "gn:feature_code":"PPL",
    "gn:name":"Chumbur\u00e1n",
    "gn:population":0,
    "gn:timezone":"America/Costa_Rica",
    "iso:country":"CR",
    "wof:name":"Chumburan",
    "wof:placetype":"locality"
},
  "geometry": {"coordinates":[-85.51487,9.9778],"type":"Point"}
}