{
  "type": "Feature",
  "properties": {
    "gn:admin1_code":"08",
    "gn:admin2_code":"106",
    "gn:admin3_code":"10607.0",
    "gn:asciiname":"Rincon",
    "gn:country_code":"CR",
    "gn:dem":1602,
    "gn:feature_class":"P",
    "gn:feature_code":"PPL",
    "gn:name":"Rinc\u00f3n",
    "gn:population":0,
    "gn:timezone":"America/Costa_Rica",
    "iso:country":"CR",
    "name:cat_x_preferred":[
        "Rincon"
    ],
    "name:ceb_x_preferred":[
        "Rincon"
    ],
    "name:ita_x_preferred":[
        "Rincon"
    ],
    "name:jpn_x_preferred":[
        "\u30ea\u30f3\u30b3\u30f3"
    ],
    "name:nld_x_preferred":[
        "Rincon"
    ],
    "name:pol_x_preferred":[
        "Rincon"
    ],
    "name:por_x_preferred":[
        "Rincon"
    ],
    "name:rus_x_preferred":[
        "\u0420\u0438\u043d\u043a\u043e\u043d"
    ],
    "name:srp_x_preferred":[
        "\u0420\u0438\u043d\u043a\u043e\u043d"
    ],
    "name:swe_x_preferred":[
        "Rincon"
    ],
    "name:ukr_x_preferred":[
        "\u0420\u0456\u043d\u043a\u043e\u043d"
    ],
    "name:vol_x_preferred":[
        "Rincon"
    ],
    "wof:name":"Rincon",
    "wof:placetype":"locality"
},
  "geometry": {"coordinates":[-84.07271,9.83505],"type":"Point"}
}