{
  "type": "Feature",
  "properties": {
    "gn:admin1_code":"03",
    "gn:admin2_code":"501",
    "gn:admin3_code":"50102.0",
    "gn:asciiname":"Ahogados",
    "gn:country_code":"CR",
    "gn:dem":85,
    "gn:feature_class":"P",
    "gn:feature_code":"PPL",
    "gn:name":"Ahogados",
    "gn:population":0,
    "gn:timezone":"America/Costa_Rica",
    "iso:country":"CR",
    "name:und_x_variant":[
        "Los Ahogados",
        "Hacienda Los Ahogados",
        "Ahogados"
    ],
    "wof:name":"Ahogados",
    "wof:placetype":"locality"
},
  "geometry": {"coordinates":[-85.51612,10.7499],"type":"Point"}
}