{
  "type": "Feature",
  "properties": {
    "iso:country":"CR",
    "name:ceb_x_preferred":[
        "Oros\u00ed"
    ],
    "name:eng_x_preferred":[
        "Oros\u00ed"
    ],
    "name:fra_x_preferred":[
        "Oros\u00ed"
    ],
    "name:ita_x_preferred":[
        "Orosi"
    ],
    "name:nld_x_preferred":[
        "Oros\u00ed"
    ],
    "name:nob_x_preferred":[
        "Orosi"
    ],
    "name:nor_x_preferred":[
        "Orosi"
    ],
    "name:spa_x_preferred":[
        "Orosi"
    ],
    "name:swe_x_preferred":[
        "Oros\u00ed"
    ],
    "name:zho_x_preferred":[
        "\u5967\u7f85\u897f\u5340"
    ],
    "qs:gn_country":"CR",
    "qs:gn_fcode":"PPL",
    "qs:gn_pop":4350,
    "qs:name":"Oros\u00ed",
    "qs:name_adm0":"Costa Rica",
    "qs:name_adm1":"Cartago",
    "qs:photos":114,
    "qs:photos_1k":23,
    "qs:photos_9k":1,
    "qs:photos_9r":3,
    "qs:photos_all":114,
    "qs:photos_sr":3,
    "qs:placetype":"Town",
    "qs:pop_sr":"4",
    "qs:woe_adm0":23424791,
    "wd:wordcount":452,
    "wof:name":"Oros\u00ed",
    "wof:placetype":"locality",
    "wof:population":4350
},
  "geometry": {"coordinates":[-83.85383,9.79617],"type":"Point"}
}