{
  "type": "Feature",
  "properties": {
    "gn:admin1_code":"01",
    "gn:admin2_code":"210",
    "gn:admin3_code":"21012.0",
    "gn:asciiname":"Pataste",
    "gn:country_code":"CR",
    "gn:dem":299,
    "gn:feature_class":"P",
    "gn:feature_code":"PPL",
    "gn:name":"Pataste",
    "gn:population":0,
    "gn:timezone":"America/Costa_Rica",
    "iso:country":"CR",
    "name:und_x_variant":[
        "Pataste Arriba",
        "Pataste"
    ],
    "wof:name":"Pataste",
    "wof:placetype":"locality"
},
  "geometry": {"coordinates":[-84.68129,10.55631],"type":"Point"}
}