{
  "type": "Feature",
  "properties": {
    "gn:admin1_code":"02",
    "gn:admin2_code":"302",
    "gn:admin3_code":"30203.0",
    "gn:asciiname":"Sitio",
    "gn:country_code":"CR",
    "gn:dem":1391,
    "gn:feature_class":"P",
    "gn:feature_code":"PPL",
    "gn:name":"Sitio",
    "gn:population":0,
    "gn:timezone":"America/Costa_Rica",
    "iso:country":"CR",
    "name:deu_x_preferred":[
        "Sitio"
    ],
    "name:ilo_x_preferred":[
        "Sitio"
    ],
    "wof:name":"Sitio",
    "wof:placetype":"locality"
},
  "geometry": {"coordinates":[-83.82512,9.78596],"type":"Point"}
}