{
  "type": "Feature",
  "properties": {
    "gn:admin1_code":"01",
    "gn:admin2_code":"211",
    "gn:admin3_code":"21105.0",
    "gn:asciiname":"Picada",
    "gn:country_code":"CR",
    "gn:dem":2074,
    "gn:feature_class":"P",
    "gn:feature_code":"PPL",
    "gn:name":"Picada",
    "gn:population":0,
    "gn:timezone":"America/Costa_Rica",
    "iso:country":"CR",
    "name:cat_x_preferred":[
        "Picada"
    ],
    "name:ces_x_preferred":[
        "Picada"
    ],
    "name:fra_x_preferred":[
        "Picada"
    ],
    "name:ita_x_preferred":[
        "Picada"
    ],
    "name:spa_x_preferred":[
        "Picada"
    ],
    "wof:name":"Picada",
    "wof:placetype":"locality"
},
  "geometry": {"coordinates":[-84.35890000000001,10.20101],"type":"Point"}
}