{
  "type": "Feature",
  "properties": {
    "gn:admin1_code":"01",
    "gn:admin2_code":"210",
    "gn:admin3_code":"21004.0",
    "gn:asciiname":"Gloria",
    "gn:country_code":"CR",
    "gn:dem":70,
    "gn:feature_class":"P",
    "gn:feature_code":"PPL",
    "gn:name":"Gloria",
    "gn:population":0,
    "gn:timezone":"America/Costa_Rica",
    "iso:country":"CR",
    "wof:name":"Gloria",
    "wof:placetype":"locality"
},
  "geometry": {"coordinates":[-84.33199,10.54811],"type":"Point"}
}