{
  "type": "Feature",
  "properties": {
    "iso:country":"CR",
    "qs:gn_pop":0,
    "qs:name":"Toro Amarillo",
    "qs:name_adm0":"Costa Rica",
    "qs:name_adm1":"Alajuela",
    "qs:photos":383,
    "qs:photos_1k":78,
    "qs:photos_9k":3,
    "qs:photos_9r":5,
    "qs:photos_all":665,
    "qs:photos_sr":6,
    "qs:placetype":"LocalAdmin",
    "qs:pop_sr":"0",
    "qs:woe_adm0":23424791,
    "wof:name":"Toro Amarillo",
    "wof:placetype":"localadmin"
},
  "geometry": {"coordinates":[-84.310197,10.250904],"type":"Point"}
}