{
  "type": "Feature",
  "properties": {
    "iso:country":"CR",
    "qs:gn_pop":0,
    "qs:name":"Limon",
    "qs:name_adm0":"Costa Rica",
    "qs:name_adm1":"Limon",
    "qs:photos":184,
    "qs:photos_1k":37,
    "qs:photos_9k":9,
    "qs:photos_9r":9,
    "qs:photos_all":2107,
    "qs:photos_sr":4,
    "qs:placetype":"LocalAdmin",
    "qs:pop_sr":"0",
    "qs:woe_adm0":23424791,
    "wof:name":"Limon",
    "wof:placetype":"localadmin"
},
  "geometry": {"coordinates":[-83.03762999999999,9.991833],"type":"Point"}
}