{
  "type": "Feature",
  "properties": {
    "gn:admin1_code":"08",
    "gn:admin2_code":"109",
    "gn:admin3_code":"10902.0",
    "gn:asciiname":"Matinilla",
    "gn:country_code":"CR",
    "gn:dem":1239,
    "gn:feature_class":"P",
    "gn:feature_code":"PPL",
    "gn:name":"Matinilla",
    "gn:population":0,
    "gn:timezone":"America/Costa_Rica",
    "iso:country":"CR",
    "name:und_x_variant":[
        "Cedral",
        "Matinilla"
    ],
    "wof:name":"Matinilla",
    "wof:placetype":"locality"
},
  "geometry": {"coordinates":[-84.17276,9.89186],"type":"Point"}
}