{
  "type": "Feature",
  "properties": {
    "gn:admin1_code":"07",
    "gn:admin2_code":"601",
    "gn:admin3_code":"60104.0",
    "gn:asciiname":"Ilusion",
    "gn:country_code":"CR",
    "gn:dem":328,
    "gn:feature_class":"P",
    "gn:feature_code":"PPL",
    "gn:name":"Ilusi\u00f3n",
    "gn:population":0,
    "gn:timezone":"America/Costa_Rica",
    "iso:country":"CR",
    "wof:name":"Ilusion",
    "wof:placetype":"locality"
},
  "geometry": {"coordinates":[-85.06683000000002,9.90167],"type":"Point"}
}