{
  "type": "Feature",
  "properties": {
    "gn:admin1_code":"01",
    "gn:admin2_code":"209",
    "gn:admin3_code":"20904.0",
    "gn:asciiname":"Coyolar",
    "gn:country_code":"CR",
    "gn:dem":164,
    "gn:feature_class":"P",
    "gn:feature_code":"PPL",
    "gn:name":"Coyolar",
    "gn:population":0,
    "gn:timezone":"America/Costa_Rica",
    "iso:country":"CR",
    "wof:name":"Coyolar",
    "wof:placetype":"locality"
},
  "geometry": {"coordinates":[-84.55686999999998,9.89699],"type":"Point"}
}