{
  "type": "Feature",
  "properties": {
    "gn:admin1_code":"07",
    "gn:admin2_code":"608",
    "gn:admin3_code":"60804.0",
    "gn:asciiname":"Platanillo",
    "gn:cc2":"CR",
    "gn:country_code":"CR",
    "gn:dem":676,
    "gn:feature_class":"P",
    "gn:feature_code":"PPL",
    "gn:name":"Platanillo",
    "gn:population":0,
    "gn:timezone":"America/Costa_Rica",
    "iso:country":"CR",
    "name:ceb_x_preferred":[
        "Platanillo"
    ],
    "name:spa_x_preferred":[
        "Platanillo"
    ],
    "name:swe_x_preferred":[
        "Platanillo"
    ],
    "name:und_x_variant":[
        "Platanilla",
        "Platanillo"
    ],
    "wof:name":"Platanillo",
    "wof:placetype":"locality"
},
  "geometry": {"coordinates":[-83.06667,8.85],"type":"Point"}
}