{
  "type": "Feature",
  "properties": {
    "iso:country":"CR",
    "qs:gn_country":"CR",
    "qs:gn_fcode":"PPL",
    "qs:gn_pop":0,
    "qs:name":"Bar\u00fa",
    "qs:name_adm0":"Costa Rica",
    "qs:name_adm1":"San Jose",
    "qs:photos":123,
    "qs:photos_1k":25,
    "qs:photos_9k":1,
    "qs:photos_9r":3,
    "qs:photos_all":123,
    "qs:photos_sr":3,
    "qs:placetype":"Town",
    "qs:pop_sr":"0",
    "qs:woe_adm0":23424791,
    "wof:name":"Bar\u00fa",
    "wof:placetype":"locality"
},
  "geometry": {"coordinates":[-83.84428,9.28132],"type":"Point"}
}