{
  "type": "Feature",
  "properties": {
    "gn:admin1_code":"07",
    "gn:admin2_code":"601",
    "gn:admin3_code":"60105.0",
    "gn:asciiname":"Panica",
    "gn:country_code":"CR",
    "gn:dem":19,
    "gn:feature_class":"P",
    "gn:feature_code":"PPL",
    "gn:name":"P\u00e1nica",
    "gn:population":0,
    "gn:timezone":"America/Costa_Rica",
    "iso:country":"CR",
    "name:und_x_variant":[
        "Tambor",
        "P\u00e1nica"
    ],
    "wof:name":"Panica",
    "wof:placetype":"locality"
},
  "geometry": {"coordinates":[-85.04082,9.71711],"type":"Point"}
}