{
  "type": "Feature",
  "properties": {
    "iso:country":"CR",
    "name:eng_x_preferred":[
        "Colorado"
    ],
    "name:fra_x_preferred":[
        "Colorado"
    ],
    "name:spa_x_preferred":[
        "Colorado"
    ],
    "qs:gn_country":"CR",
    "qs:gn_fcode":"PPL",
    "qs:gn_pop":0,
    "qs:name":"Colorado",
    "qs:name_adm0":"Costa Rica",
    "qs:name_adm1":"Limon",
    "qs:photos":267,
    "qs:photos_1k":54,
    "qs:photos_9k":1,
    "qs:photos_9r":4,
    "qs:photos_all":267,
    "qs:photos_sr":5,
    "qs:placetype":"Town",
    "qs:pop_sr":"0",
    "qs:woe_adm0":23424791,
    "wof:name":"Colorado",
    "wof:placetype":"locality"
},
  "geometry": {"coordinates":[-83.59999999999999,10.78333],"type":"Point"}
}