{
  "type": "Feature",
  "properties": {
    "iso:country":"CR",
    "name:ceb_x_preferred":[
        "Siquirres"
    ],
    "name:ell_x_preferred":[
        "\u03a3\u03b9\u03ba\u03af\u03c1\u03c1\u03b5\u03c2"
    ],
    "name:fra_x_preferred":[
        "Siquirres"
    ],
    "name:heb_x_preferred":[
        "\u05e1\u05d9\u05e7\u05d9\u05e8\u05e1"
    ],
    "name:ita_x_preferred":[
        "Siquirres"
    ],
    "name:nor_x_preferred":[
        "Siquirres"
    ],
    "name:spa_x_preferred":[
        "Siquirres"
    ],
    "name:swe_x_preferred":[
        "Siquirres"
    ],
    "name:zho_x_preferred":[
        "\u932b\u57fa\u96f7\u65af\u5340"
    ],
    "qs:gn_pop":0,
    "qs:name":"Siquirres",
    "qs:name_adm0":"Costa Rica",
    "qs:name_adm1":"Limon",
    "qs:photos":1,
    "qs:photos_1k":1,
    "qs:photos_9k":1,
    "qs:photos_9r":4,
    "qs:photos_all":292,
    "qs:photos_sr":1,
    "qs:placetype":"LocalAdmin",
    "qs:pop_sr":"0",
    "qs:woe_adm0":23424791,
    "wof:name":"Siquirres",
    "wof:placetype":"localadmin"
},
  "geometry": {"coordinates":[-83.53815,10.08958],"type":"Point"}
}