{
  "type": "Feature",
  "properties": {
    "gn:admin1_code":"07",
    "gn:admin2_code":"601",
    "gn:admin3_code":"60115.0",
    "gn:asciiname":"Carrizal",
    "gn:country_code":"CR",
    "gn:dem":14,
    "gn:feature_class":"P",
    "gn:feature_code":"PPL",
    "gn:name":"Carrizal",
    "gn:population":0,
    "gn:timezone":"America/Costa_Rica",
    "iso:country":"CR",
    "name:ceb_x_preferred":[
        "Carrizal"
    ],
    "name:fra_x_preferred":[
        "Carrizal"
    ],
    "name:ita_x_preferred":[
        "Carrizal"
    ],
    "name:jpn_x_preferred":[
        "\u30ab\u30ea\u30b5\u30eb"
    ],
    "name:mlg_x_preferred":[
        "Carrizal"
    ],
    "name:por_x_preferred":[
        "Carrizal"
    ],
    "name:rus_x_preferred":[
        "\u041a\u0430\u0440\u0440\u0438\u0441\u0430\u043b\u044c"
    ],
    "name:spa_x_preferred":[
        "Carrizal"
    ],
    "name:swe_x_preferred":[
        "Carrizal"
    ],
    "name:und_x_variant":[
        "Hacienda Carrizal"
    ],
    "wof:name":"Carrizal",
    "wof:placetype":"locality"
},
  "geometry": {"coordinates":[-84.73334,9.98776],"type":"Point"}
}