{
  "type": "Feature",
  "properties": {
    "gn:admin1_code":"06",
    "gn:admin2_code":"702",
    "gn:admin3_code":"70206.0",
    "gn:asciiname":"Siete",
    "gn:country_code":"CR",
    "gn:dem":1,
    "gn:feature_class":"P",
    "gn:feature_code":"PPL",
    "gn:name":"Siete",
    "gn:population":0,
    "gn:timezone":"America/Costa_Rica",
    "iso:country":"CR",
    "name:deu_x_preferred":[
        "Siete"
    ],
    "wof:name":"Siete",
    "wof:placetype":"locality"
},
  "geometry": {"coordinates":[-83.42650999999999,10.39443],"type":"Point"}
}