{
  "type": "Feature",
  "properties": {
    "gn:admin1_code":"08",
    "gn:admin2_code":"112",
    "gn:admin3_code":"11204.0",
    "gn:asciiname":"Escuadra",
    "gn:country_code":"CR",
    "gn:dem":1203,
    "gn:feature_class":"P",
    "gn:feature_code":"PPL",
    "gn:name":"Escuadra",
    "gn:population":0,
    "gn:timezone":"America/Costa_Rica",
    "iso:country":"CR",
    "wof:name":"Escuadra",
    "wof:placetype":"locality"
},
  "geometry": {"coordinates":[-84.20262,9.74584],"type":"Point"}
}