{
  "type": "Feature",
  "properties": {
    "gn:admin1_code":"03",
    "gn:admin2_code":"506",
    "gn:admin3_code":"50601.0",
    "gn:asciiname":"Hotel",
    "gn:country_code":"CR",
    "gn:dem":32,
    "gn:feature_class":"P",
    "gn:feature_code":"PPL",
    "gn:name":"Hotel",
    "gn:population":0,
    "gn:timezone":"America/Costa_Rica",
    "iso:country":"CR",
    "wof:name":"Hotel",
    "wof:placetype":"locality"
},
  "geometry": {"coordinates":[-85.12139999999999,10.3749],"type":"Point"}
}