{
  "type": "Feature",
  "properties": {
    "gn:admin1_code":"07",
    "gn:admin2_code":"611",
    "gn:admin3_code":"61101.0",
    "gn:asciiname":"La Mona",
    "gn:country_code":"CR",
    "gn:dem":68,
    "gn:feature_class":"P",
    "gn:feature_code":"PPL",
    "gn:name":"La Mona",
    "gn:population":0,
    "gn:timezone":"America/Costa_Rica",
    "iso:country":"CR",
    "wof:name":"La Mona",
    "wof:placetype":"locality"
},
  "geometry": {"coordinates":[-84.61951999999999,9.65486],"type":"Point"}
}