{
  "type": "Feature",
  "properties": {
    "gn:admin1_code":"01",
    "gn:admin2_code":"201",
    "gn:admin3_code":"20113.0",
    "gn:asciiname":"Siquiares",
    "gn:country_code":"CR",
    "gn:dem":750,
    "gn:feature_class":"P",
    "gn:feature_code":"PPL",
    "gn:name":"Siquiares",
    "gn:population":0,
    "gn:timezone":"America/Costa_Rica",
    "iso:country":"CR",
    "wof:name":"Siquiares",
    "wof:placetype":"locality"
},
  "geometry": {"coordinates":[-84.28679,9.97295],"type":"Point"}
}