{
  "type": "Feature",
  "properties": {
    "gn:admin1_code":"02",
    "gn:admin2_code":"305",
    "gn:admin3_code":"30504.0",
    "gn:asciiname":"La Pastora",
    "gn:country_code":"CR",
    "gn:dem":1694,
    "gn:feature_class":"P",
    "gn:feature_code":"PPL",
    "gn:name":"La Pastora",
    "gn:population":0,
    "gn:timezone":"America/Costa_Rica",
    "iso:country":"CR",
    "name:eus_x_preferred":[
        "La Pastora"
    ],
    "name:ita_x_preferred":[
        "La Pastora"
    ],
    "name:por_x_preferred":[
        "La Pastora"
    ],
    "name:spa_x_preferred":[
        "La Pastora"
    ],
    "name:und_x_variant":[
        "Pastora"
    ],
    "name:urd_x_preferred":[
        "\u0644\u0627 \u067e\u0627\u0633\u0679\u0648\u0631\u0627"
    ],
    "name:zho_x_preferred":[
        "\u62c9\u5e15\u65af\u6258\u62c9"
    ],
    "wof:name":"La Pastora",
    "wof:placetype":"locality"
},
  "geometry": {"coordinates":[-83.75305999999998,9.96364],"type":"Point"}
}