{
  "type": "Feature",
  "properties": {
    "gn:admin1_code":"02",
    "gn:admin2_code":"308",
    "gn:admin3_code":"30802.0",
    "gn:asciiname":"Vara de Roble",
    "gn:country_code":"CR",
    "gn:dem":2036,
    "gn:feature_class":"P",
    "gn:feature_code":"PPL",
    "gn:name":"Vara de Roble",
    "gn:population":0,
    "gn:timezone":"America/Costa_Rica",
    "iso:country":"CR",
    "wof:name":"Vara de Roble",
    "wof:placetype":"locality"
},
  "geometry": {"coordinates":[-83.95879000000002,9.74268],"type":"Point"}
}