{
  "type": "Feature",
  "properties": {
    "gn:admin1_code":"08",
    "gn:admin2_code":"109",
    "gn:admin3_code":"10903.0",
    "gn:asciiname":"Pozos",
    "gn:country_code":"CR",
    "gn:dem":851,
    "gn:feature_class":"P",
    "gn:feature_code":"PPL",
    "gn:name":"Pozos",
    "gn:population":0,
    "gn:timezone":"America/Costa_Rica",
    "iso:country":"CR",
    "name:und_x_variant":[
        "Los Pozos",
        "Pozos"
    ],
    "wof:name":"Pozos",
    "wof:placetype":"locality"
},
  "geometry": {"coordinates":[-84.19031,9.94953],"type":"Point"}
}