{
  "type": "Feature",
  "properties": {
    "gn:admin1_code":"08",
    "gn:admin2_code":"103",
    "gn:admin3_code":"10309.0",
    "gn:asciiname":"Villa Nueva",
    "gn:country_code":"CR",
    "gn:dem":1339,
    "gn:feature_class":"P",
    "gn:feature_code":"PPL",
    "gn:name":"Villa Nueva",
    "gn:population":0,
    "gn:timezone":"America/Costa_Rica",
    "iso:country":"CR",
    "name:ceb_x_preferred":[
        "Villa Nueva"
    ],
    "name:deu_x_preferred":[
        "Villa Nueva"
    ],
    "name:fra_x_preferred":[
        "Villa Nueva"
    ],
    "name:ita_x_preferred":[
        "Villa Nueva"
    ],
    "name:nld_x_preferred":[
        "Villa Nueva"
    ],
    "name:pol_x_preferred":[
        "Villa Nueva"
    ],
    "name:por_x_preferred":[
        "Villa Nueva"
    ],
    "name:sco_x_preferred":[
        "Villa Nueva"
    ],
    "name:spa_x_preferred":[
        "Villa Nueva"
    ],
    "name:swe_x_preferred":[
        "Villa Nueva"
    ],
    "wof:name":"Villa Nueva",
    "wof:placetype":"locality"
},
  "geometry": {"coordinates":[-84.10566999999998,9.76819],"type":"Point"}
}