{
  "type": "Feature",
  "properties": {
    "gn:admin1_code":"01",
    "gn:admin2_code":"203",
    "gn:admin3_code":"20306.0",
    "gn:asciiname":"Chaparron",
    "gn:country_code":"CR",
    "gn:dem":68,
    "gn:feature_class":"P",
    "gn:feature_code":"PPL",
    "gn:name":"Chaparr\u00f3n",
    "gn:population":0,
    "gn:timezone":"America/Costa_Rica",
    "iso:country":"CR",
    "wof:name":"Chaparron",
    "wof:placetype":"locality"
},
  "geometry": {"coordinates":[-84.2032,10.55542],"type":"Point"}
}