{
  "type": "Feature",
  "properties": {
    "iso:country":"CR",
    "name:unk_x_variant":[
        "La Comunidad"
    ],
    "qs:gn_country":"CR",
    "qs:gn_fcode":"PPL",
    "qs:gn_pop":0,
    "qs:name":"Comunidad",
    "qs:name_adm0":"Costa Rica",
    "qs:name_adm1":"Guanacaste",
    "qs:photos":14,
    "qs:photos_1k":3,
    "qs:photos_9k":1,
    "qs:photos_9r":1,
    "qs:photos_all":14,
    "qs:photos_sr":1,
    "qs:placetype":"Town",
    "qs:pop_sr":"0",
    "qs:woe_adm0":23424791,
    "wof:name":"Comunidad",
    "wof:placetype":"locality"
},
  "geometry": {"coordinates":[-85.59003,10.54937],"type":"Point"}
}