{
  "type": "Feature",
  "properties": {
    "iso:country":"CR",
    "name:arz_x_preferred":[
        "\u062f\u0648\u0645\u064a\u0646\u064a\u0643\u0627\u0644"
    ],
    "name:eng_x_preferred":[
        "Dominical"
    ],
    "name:fra_x_preferred":[
        "Dominical"
    ],
    "name:nld_x_preferred":[
        "Dominical"
    ],
    "name:nob_x_preferred":[
        "Dominical"
    ],
    "name:nor_x_preferred":[
        "Dominical"
    ],
    "name:spa_x_preferred":[
        "Playa Dominical"
    ],
    "name:spa_x_variant":[
        "Dominical"
    ],
    "name:und_x_variant":[
        "Puerto Dominical"
    ],
    "qs:gn_country":"CR",
    "qs:gn_fcode":"PPL",
    "qs:gn_pop":0,
    "qs:name":"Dominical",
    "qs:name_adm0":"Costa Rica",
    "qs:name_adm1":"Puntarenas",
    "qs:photos":2010,
    "qs:photos_1k":407,
    "qs:photos_9k":9,
    "qs:photos_9r":9,
    "qs:photos_all":2010,
    "qs:photos_sr":15,
    "qs:placetype":"Town",
    "qs:pop_sr":"3",
    "qs:woe_adm0":23424791,
    "wd:wordcount":160,
    "wof:name":"Dominical",
    "wof:placetype":"locality"
},
  "geometry": {"coordinates":[-83.86135,9.25483],"type":"Point"}
}