{
  "type": "Feature",
  "properties": {
    "gn:admin1_code":"08",
    "gn:admin2_code":"106",
    "gn:admin3_code":"10604.0",
    "gn:asciiname":"San Gabriel de Aserri",
    "gn:country_code":"CR",
    "gn:dem":1334,
    "gn:feature_class":"P",
    "gn:feature_code":"PPL",
    "gn:name":"San Gabriel de Aserr\u00ed",
    "gn:population":0,
    "gn:timezone":"America/Costa_Rica",
    "iso:country":"CR",
    "wof:name":"San Gabriel de Aserri",
    "wof:placetype":"locality"
},
  "geometry": {"coordinates":[-84.1053,9.78617],"type":"Point"}
}