{
  "type": "Feature",
  "properties": {
    "gn:admin1_code":"07",
    "gn:admin2_code":"604",
    "gn:admin3_code":"60401.0",
    "gn:asciiname":"Bellavista",
    "gn:country_code":"CR",
    "gn:dem":591,
    "gn:feature_class":"P",
    "gn:feature_code":"PPL",
    "gn:name":"Bellavista",
    "gn:population":0,
    "gn:timezone":"America/Costa_Rica",
    "iso:country":"CR",
    "name:cat_x_preferred":[
        "Bellavista"
    ],
    "name:ceb_x_preferred":[
        "Bellavista"
    ],
    "name:deu_x_preferred":[
        "Bellavista"
    ],
    "name:fra_x_preferred":[
        "Bellavista"
    ],
    "name:ita_x_preferred":[
        "Bellavista"
    ],
    "name:kor_x_preferred":[
        "\ubca8\ub77c\ube44\uc2a4\ud0c0"
    ],
    "name:nld_x_preferred":[
        "Bellavista"
    ],
    "name:pol_x_preferred":[
        "Bellavista"
    ],
    "name:por_x_preferred":[
        "Bellavista"
    ],
    "name:spa_x_preferred":[
        "Bellavista"
    ],
    "name:srp_x_preferred":[
        "Bellavista"
    ],
    "name:swe_x_preferred":[
        "Bellavista"
    ],
    "wof:name":"Bellavista",
    "wof:placetype":"locality"
},
  "geometry": {"coordinates":[-84.70968000000001,10.10756],"type":"Point"}
}