{
  "type": "Feature",
  "properties": {
    "iso:country":"CR",
    "qs:gn_country":"CR",
    "qs:gn_fcode":"PPL",
    "qs:gn_pop":0,
    "qs:name":"Coliblanco",
    "qs:name_adm0":"Costa Rica",
    "qs:name_adm1":"Cartago",
    "qs:photos":25,
    "qs:photos_1k":5,
    "qs:photos_9k":1,
    "qs:photos_9r":1,
    "qs:photos_all":25,
    "qs:photos_sr":1,
    "qs:placetype":"Town",
    "qs:pop_sr":"0",
    "qs:woe_adm0":23424791,
    "wof:name":"Coliblanco",
    "wof:placetype":"locality"
},
  "geometry": {"coordinates":[-83.81138,9.94915],"type":"Point"}
}