{
  "type": "Feature",
  "properties": {
    "iso:country":"CR",
    "name:und_x_variant":[
        "San Rafael"
    ],
    "qs:gn_country":"CR",
    "qs:gn_fcode":"PPL",
    "qs:gn_pop":15051,
    "qs:name":"San Rafael Arriba",
    "qs:name_adm0":"Costa Rica",
    "qs:name_adm1":"San Jose",
    "qs:photos":0,
    "qs:photos_1k":0,
    "qs:photos_9k":1,
    "qs:photos_9r":1,
    "qs:photos_all":3,
    "qs:photos_sr":0,
    "qs:placetype":"Town",
    "qs:pop_sr":"6",
    "qs:woe_adm0":23424791,
    "wof:name":"San Rafael Arriba",
    "wof:placetype":"locality",
    "wof:population":15051
},
  "geometry": {"coordinates":[-84.07661,9.87556],"type":"Point"}
}