{
  "type": "Feature",
  "properties": {
    "iso:country":"CR",
    "name:bre_x_preferred":[
        "San Marcos"
    ],
    "name:bul_x_preferred":[
        "\u0421\u0430\u043d \u041c\u0430\u0440\u043a\u043e\u0441"
    ],
    "name:cat_x_preferred":[
        "San Marcos"
    ],
    "name:ceb_x_preferred":[
        "San Marcos"
    ],
    "name:deu_x_preferred":[
        "San Marcos"
    ],
    "name:est_x_preferred":[
        "San Marcos"
    ],
    "name:fin_x_preferred":[
        "San Marcos"
    ],
    "name:fra_x_preferred":[
        "San Marcos"
    ],
    "name:glg_x_preferred":[
        "San Marcos"
    ],
    "name:ita_x_preferred":[
        "San Marcos"
    ],
    "name:kor_x_preferred":[
        "\uc0b0\ub9c8\ub974\ucf54\uc2a4"
    ],
    "name:lit_x_preferred":[
        "San Markosas"
    ],
    "name:nds_x_preferred":[
        "San Marcos"
    ],
    "name:nld_x_preferred":[
        "San Marcos"
    ],
    "name:pol_x_preferred":[
        "San Marcos"
    ],
    "name:por_x_preferred":[
        "San Marcos"
    ],
    "name:rus_x_preferred":[
        "\u0421\u0430\u043d-\u041c\u0430\u0440\u043a\u043e\u0441"
    ],
    "name:sco_x_preferred":[
        "San Marcos"
    ],
    "name:spa_x_preferred":[
        "San Marcos"
    ],
    "name:srp_x_preferred":[
        "\u0421\u0430\u043d \u041c\u0430\u0440\u043a\u043e\u0441"
    ],
    "name:swa_x_preferred":[
        "San Marcos"
    ],
    "name:swe_x_preferred":[
        "San Marcos"
    ],
    "name:vol_x_preferred":[
        "San Marcos"
    ],
    "name:war_x_preferred":[
        "San Marcos"
    ],
    "qs:gn_pop":0,
    "qs:name":"San Marcos",
    "qs:name_adm0":"Costa Rica",
    "qs:name_adm1":"San Jose",
    "qs:photos":3,
    "qs:photos_1k":1,
    "qs:photos_9k":1,
    "qs:photos_9r":2,
    "qs:photos_all":71,
    "qs:photos_sr":1,
    "qs:placetype":"LocalAdmin",
    "qs:pop_sr":"0",
    "qs:woe_adm0":23424791,
    "wof:name":"San Marcos",
    "wof:placetype":"localadmin"
},
  "geometry": {"coordinates":[-84.02086199999999,9.657023],"type":"Point"}
}