{
  "type": "Feature",
  "properties": {
    "gn:admin1_code":"02",
    "gn:admin2_code":"308",
    "gn:admin3_code":"30802.0",
    "gn:asciiname":"Palmital",
    "gn:country_code":"CR",
    "gn:dem":1804,
    "gn:feature_class":"P",
    "gn:feature_code":"PPL",
    "gn:name":"Palmital",
    "gn:population":0,
    "gn:timezone":"America/Costa_Rica",
    "iso:country":"CR",
    "name:ceb_x_preferred":[
        "Palmital"
    ],
    "name:ita_x_preferred":[
        "Palmital"
    ],
    "name:nld_x_preferred":[
        "Palmital"
    ],
    "name:nor_x_preferred":[
        "Palmital"
    ],
    "name:por_x_preferred":[
        "Palmital"
    ],
    "name:rus_x_preferred":[
        "\u041f\u0430\u043b\u043c\u0438\u0442\u0430\u043b"
    ],
    "name:swe_x_preferred":[
        "Palmital"
    ],
    "name:vol_x_preferred":[
        "Palmital"
    ],
    "wof:name":"Palmital",
    "wof:placetype":"locality"
},
  "geometry": {"coordinates":[-83.97960999999999,9.78459],"type":"Point"}
}