{
  "type": "Feature",
  "properties": {
    "gn:admin1_code":"08",
    "gn:admin2_code":"104",
    "gn:admin3_code":"10402.0",
    "gn:asciiname":"Llano Hermoso",
    "gn:country_code":"CR",
    "gn:dem":481,
    "gn:feature_class":"P",
    "gn:feature_code":"PPL",
    "gn:name":"Llano Hermoso",
    "gn:population":0,
    "gn:timezone":"America/Costa_Rica",
    "iso:country":"CR",
    "wof:name":"Llano Hermoso",
    "wof:placetype":"locality"
},
  "geometry": {"coordinates":[-84.42486,9.82613],"type":"Point"}
}