{
  "type": "Feature",
  "properties": {
    "gn:admin1_code":"02",
    "gn:admin2_code":"302",
    "gn:admin3_code":"30203.0",
    "gn:asciiname":"Patillos",
    "gn:country_code":"CR",
    "gn:dem":1272,
    "gn:feature_class":"P",
    "gn:feature_code":"PPL",
    "gn:name":"Patillos",
    "gn:population":0,
    "gn:timezone":"America/Costa_Rica",
    "iso:country":"CR",
    "wof:name":"Patillos",
    "wof:placetype":"locality"
},
  "geometry": {"coordinates":[-83.78296999999998,9.75205],"type":"Point"}
}