{
  "type": "Feature",
  "properties": {
    "iso:country":"CR",
    "name:spa_x_preferred":[
        "Hatillo No.5"
    ],
    "qs:gn_adm0_cc":"CR",
    "qs:gn_local":3621849,
    "qs:gn_nam_loc":"San Jose, San Jos\u00e9, San Jos\u00e9, CR",
    "qs:gn_namadm1":"08",
    "qs:local_max":6857,
    "qs:local_sum":19186,
    "qs:localhoods":27,
    "qs:name":"Hatillo No.5",
    "qs:name_adm0":"Costa Rica",
    "qs:name_adm1":"San Jose",
    "qs:name_adm2":"San Jos\u00e9",
    "qs:name_lau":"Hatillo",
    "qs:name_local":"San Jos\u00e9",
    "qs:photo_max":931,
    "qs:photo_sum":2010,
    "qs:placetype":"Suburb",
    "qs:quad_count":7,
    "qs:woe_adm0":23424791,
    "qs:woe_adm1":2345088,
    "qs:woe_adm2":26808844,
    "qs:woe_lau":26809010,
    "qs:woe_local":59426,
    "qs:woe_ver":"7.10.0",
    "wof:lang":[
        "spa"
    ],
    "wof:name":"Hatillo No.5",
    "wof:placetype":"neighbourhood"
},
  "geometry": {"coordinates":[-84.115782,9.909107],"type":"Point"}
}