{
  "type": "Feature",
  "properties": {
    "gn:admin1_code":"08",
    "gn:admin2_code":"116",
    "gn:admin3_code":"11601.0",
    "gn:asciiname":"Bolson",
    "gn:country_code":"CR",
    "gn:dem":337,
    "gn:feature_class":"P",
    "gn:feature_code":"PPL",
    "gn:name":"Bols\u00f3n",
    "gn:population":0,
    "gn:timezone":"America/Costa_Rica",
    "iso:country":"CR",
    "name:nno_x_preferred":[
        "Bolson"
    ],
    "name:pol_x_preferred":[
        "Bolson"
    ],
    "name:slk_x_preferred":[
        "Bolson"
    ],
    "name:spa_x_preferred":[
        "Bols\u00f3n"
    ],
    "name:ukr_x_preferred":[
        "\u0411\u043e\u043b\u044c\u0441\u043e\u043d\u0438"
    ],
    "wof:name":"Bolson",
    "wof:placetype":"locality"
},
  "geometry": {"coordinates":[-84.46365,9.9113],"type":"Point"}
}