{
  "type": "Feature",
  "properties": {
    "gn:admin1_code":"03",
    "gn:admin2_code":"511",
    "gn:admin3_code":"51103.0",
    "gn:asciiname":"Carrillo",
    "gn:country_code":"CR",
    "gn:dem":36,
    "gn:feature_class":"P",
    "gn:feature_code":"PPL",
    "gn:name":"Carrillo",
    "gn:population":0,
    "gn:timezone":"America/Costa_Rica",
    "iso:country":"CR",
    "name:cat_x_preferred":[
        "Carrillo"
    ],
    "name:ceb_x_preferred":[
        "Carrillo"
    ],
    "name:deu_x_preferred":[
        "Carrillo"
    ],
    "name:eng_x_preferred":[
        "Carrillo"
    ],
    "name:fra_x_preferred":[
        "Carrillo"
    ],
    "name:glg_x_preferred":[
        "Carrillo"
    ],
    "name:ita_x_preferred":[
        "Carrillo"
    ],
    "name:nds_x_preferred":[
        "Carrillo"
    ],
    "name:ron_x_preferred":[
        "Carrillo"
    ],
    "name:rus_x_preferred":[
        "\u041a\u0430\u0440\u0440\u0438\u043b\u044c\u043e"
    ],
    "name:spa_x_preferred":[
        "Carrillo"
    ],
    "name:swe_x_preferred":[
        "Carrillo"
    ],
    "name:war_x_preferred":[
        "Carrillo"
    ],
    "wof:name":"Carrillo",
    "wof:placetype":"locality"
},
  "geometry": {"coordinates":[-85.48050000000001,9.86591],"type":"Point"}
}