{
  "type": "Feature",
  "properties": {
    "gn:admin1_code":"03",
    "gn:admin2_code":"511",
    "gn:admin3_code":"51103.0",
    "gn:asciiname":"Carrillo",
    "gn:country_code":"CR",
    "gn:dem":36,
    "gn:feature_class":"P",
    "gn:feature_code":"PPL",
    "gn:name":"Carrillo",
    "gn:population":0,
    "gn:timezone":"America/Costa_Rica",
    "iso:country":"CR",
    "name:eng_x_preferred":[
        "Carrillo"
    ],
    "wof:name":"Carrillo",
    "wof:placetype":"locality"
},
  "geometry": {"coordinates":[-85.48050000000001,9.86591],"type":"Point"}
}