{
  "type": "Feature",
  "properties": {
    "gn:admin1_code":"03",
    "gn:admin2_code":"502",
    "gn:admin3_code":"50201.0",
    "gn:asciiname":"Esperanza",
    "gn:country_code":"CR",
    "gn:dem":611,
    "gn:feature_class":"P",
    "gn:feature_code":"PPL",
    "gn:name":"Esperanza",
    "gn:population":0,
    "gn:timezone":"America/Costa_Rica",
    "iso:country":"CR",
    "name:und_x_variant":[
        "La Esperanza",
        "Esperanza"
    ],
    "wof:name":"Esperanza",
    "wof:placetype":"locality"
},
  "geometry": {"coordinates":[-85.56595,10.14116],"type":"Point"}
}