{
  "type": "Feature",
  "properties": {
    "iso:country":"CR",
    "name:unk_x_variant":[
        "La Palma"
    ],
    "qs:gn_country":"CR",
    "qs:gn_fcode":"PPL",
    "qs:gn_pop":0,
    "qs:name":"Palma",
    "qs:name_adm0":"Costa Rica",
    "qs:name_adm1":"Alajuela",
    "qs:photos":2487,
    "qs:photos_1k":504,
    "qs:photos_9k":11,
    "qs:photos_9r":10,
    "qs:photos_all":2487,
    "qs:photos_sr":17,
    "qs:placetype":"Town",
    "qs:pop_sr":"0",
    "qs:woe_adm0":23424791,
    "wof:name":"Palma",
    "wof:placetype":"locality"
},
  "geometry": {"coordinates":[-84.69184,10.49958],"type":"Point"}
}