{
  "type": "Feature",
  "properties": {
    "iso:country":"CR",
    "name:ast_x_preferred":[
        "Palma"
    ],
    "name:bre_x_preferred":[
        "Palma"
    ],
    "name:cat_x_preferred":[
        "Palma"
    ],
    "name:ceb_x_preferred":[
        "Palma"
    ],
    "name:ces_x_preferred":[
        "Palma"
    ],
    "name:deu_x_preferred":[
        "Palma"
    ],
    "name:ell_x_preferred":[
        "\u03a0\u03ac\u03bb\u03bc\u03b1"
    ],
    "name:epo_x_preferred":[
        "Palma"
    ],
    "name:fas_x_preferred":[
        "\u067e\u0627\u0644\u0645\u0627"
    ],
    "name:fin_x_preferred":[
        "Palma"
    ],
    "name:fra_x_preferred":[
        "Palma"
    ],
    "name:heb_x_preferred":[
        "\u05e4\u05dc\u05de\u05d4"
    ],
    "name:hun_x_preferred":[
        "P\u00e1lma"
    ],
    "name:ita_x_preferred":[
        "Palma"
    ],
    "name:lat_x_preferred":[
        "Palma"
    ],
    "name:lav_x_preferred":[
        "Palma"
    ],
    "name:nld_x_preferred":[
        "Palma"
    ],
    "name:nor_x_preferred":[
        "Palma"
    ],
    "name:oci_x_preferred":[
        "Palma"
    ],
    "name:pol_x_preferred":[
        "Palma"
    ],
    "name:por_x_preferred":[
        "Palma"
    ],
    "name:que_x_preferred":[
        "Palma"
    ],
    "name:rus_x_preferred":[
        "\u041f\u0430\u043b\u044c\u043c\u0430"
    ],
    "name:scn_x_preferred":[
        "Palma"
    ],
    "name:sco_x_preferred":[
        "Palma"
    ],
    "name:slk_x_preferred":[
        "Palma"
    ],
    "name:slv_x_preferred":[
        "Palma"
    ],
    "name:spa_x_preferred":[
        "Palma"
    ],
    "name:swe_x_preferred":[
        "Palma"
    ],
    "name:ukr_x_preferred":[
        "\u041f\u0430\u043b\u044c\u043c\u0430"
    ],
    "name:und_x_variant":[
        "La Palma"
    ],
    "name:vie_x_preferred":[
        "Palma"
    ],
    "name:war_x_preferred":[
        "Palma"
    ],
    "qs:gn_country":"CR",
    "qs:gn_fcode":"PPL",
    "qs:gn_pop":0,
    "qs:name":"Palma",
    "qs:name_adm0":"Costa Rica",
    "qs:name_adm1":"Alajuela",
    "qs:photos":2487,
    "qs:photos_1k":504,
    "qs:photos_9k":11,
    "qs:photos_9r":10,
    "qs:photos_all":2487,
    "qs:photos_sr":17,
    "qs:placetype":"Town",
    "qs:pop_sr":"0",
    "qs:woe_adm0":23424791,
    "wof:name":"Palma",
    "wof:placetype":"locality"
},
  "geometry": {"coordinates":[-84.69184,10.49958],"type":"Point"}
}