{
  "type": "Feature",
  "properties": {
    "gn:admin1_code":"02",
    "gn:admin2_code":"305",
    "gn:admin3_code":"30501.0",
    "gn:asciiname":"Dominica",
    "gn:country_code":"CR",
    "gn:dem":645,
    "gn:feature_class":"P",
    "gn:feature_code":"PPL",
    "gn:name":"Dom\u00ednica",
    "gn:population":0,
    "gn:timezone":"America/Costa_Rica",
    "iso:country":"CR",
    "wof:name":"Dominica",
    "wof:placetype":"locality"
},
  "geometry": {"coordinates":[-83.67983000000002,9.91641],"type":"Point"}
}